Workbook

Sheet RESUMEN
A1: FULL — RESUMEN
A2: Se calcula solo desde la hoja FULL.
A4: ALERTA | B4: SKUs | C4: Unid. en Full | D4: Falta enviar | E4: Se puede enviar
A5: QUIEBRE Y SIN STOCK PARA ENVIAR | B5: =COUNTIF(FULL!$AL$7:$AL$128,$A5) -> 6 | C5: =SUMIF(FULL!$AL$7:$AL$128,$A5,FULL!$F$7:$F$128) -> 0 | D5: =SUMIF(FULL!$AL$7:$AL$128,$A5,FULL!$L$7:$L$128) -> 300 | E5: =SUMIF(FULL!$AL$7:$AL$128,$A5,FULL!$P$7:$P$128) -> 0
A6: QUIEBRE | B6: =COUNTIF(FULL!$AL$7:$AL$128,$A6) -> 39 | C6: =SUMIF(FULL!$AL$7:$AL$128,$A6,FULL!$F$7:$F$128) -> 0 | D6: =SUMIF(FULL!$AL$7:$AL$128,$A6,FULL!$L$7:$L$128) -> 1380 | E6: =SUMIF(FULL!$AL$7:$AL$128,$A6,FULL!$P$7:$P$128) -> 941
A7: REPONER | B7: =COUNTIF(FULL!$AL$7:$AL$128,$A7) -> 8 | C7: =SUMIF(FULL!$AL$7:$AL$128,$A7,FULL!$F$7:$F$128) -> 643 | D7: =SUMIF(FULL!$AL$7:$AL$128,$A7,FULL!$L$7:$L$128) -> 917 | E7: =SUMIF(FULL!$AL$7:$AL$128,$A7,FULL!$P$7:$P$128) -> 342
A8: EN RANGO | B8: =COUNTIF(FULL!$AL$7:$AL$128,$A8) -> 23 | C8: =SUMIF(FULL!$AL$7:$AL$128,$A8,FULL!$F$7:$F$128) -> 785 | D8: =SUMIF(FULL!$AL$7:$AL$128,$A8,FULL!$L$7:$L$128) -> 5 | E8: =SUMIF(FULL!$AL$7:$AL$128,$A8,FULL!$P$7:$P$128) -> 5
A9: SOBRE-STOCK | B9: =COUNTIF(FULL!$AL$7:$AL$128,$A9) -> 19 | C9: =SUMIF(FULL!$AL$7:$AL$128,$A9,FULL!$F$7:$F$128) -> 491 | D9: =SUMIF(FULL!$AL$7:$AL$128,$A9,FULL!$L$7:$L$128) -> 0 | E9: =SUMIF(FULL!$AL$7:$AL$128,$A9,FULL!$P$7:$P$128) -> 0
A10: SIN ROTACION | B10: =COUNTIF(FULL!$AL$7:$AL$128,$A10) -> 8 | C10: =SUMIF(FULL!$AL$7:$AL$128,$A10,FULL!$F$7:$F$128) -> 110 | D10: =SUMIF(FULL!$AL$7:$AL$128,$A10,FULL!$L$7:$L$128) -> 0 | E10: =SUMIF(FULL!$AL$7:$AL$128,$A10,FULL!$P$7:$P$128) -> 0
A11: STOCK VIEJO EN RIESGO | B11: =COUNTIF(FULL!$AL$7:$AL$128,$A11) -> 9 | C11: =SUMIF(FULL!$AL$7:$AL$128,$A11,FULL!$F$7:$F$128) -> 154 | D11: =SUMIF(FULL!$AL$7:$AL$128,$A11,FULL!$L$7:$L$128) -> 26 | E11: =SUMIF(FULL!$AL$7:$AL$128,$A11,FULL!$P$7:$P$128) -> 26
A12: SIN STOCK SIN DEMANDA | B12: =COUNTIF(FULL!$AL$7:$AL$128,$A12) -> 10 | C12: =SUMIF(FULL!$AL$7:$AL$128,$A12,FULL!$F$7:$F$128) -> 0 | D12: =SUMIF(FULL!$AL$7:$AL$128,$A12,FULL!$L$7:$L$128) -> 0 | E12: =SUMIF(FULL!$AL$7:$AL$128,$A12,FULL!$P$7:$P$128) -> 0
A13: - | B13: =COUNTIF(FULL!$AL$7:$AL$128,$A13) -> 0 | C13: =SUMIF(FULL!$AL$7:$AL$128,$A13,FULL!$F$7:$F$128) -> 0 | D13: =SUMIF(FULL!$AL$7:$AL$128,$A13,FULL!$L$7:$L$128) -> 0 | E13: =SUMIF(FULL!$AL$7:$AL$128,$A13,FULL!$P$7:$P$128) -> 0
A14: TOTAL | B14: =SUM(B5:B13) -> 122 | C14: =SUM(C5:C13) -> 2183 | D14: =SUM(D5:D13) -> 2628 | E14: =SUM(E5:E13) -> 1314
A16: CONFIABILIDAD DEL DATO
A17: SKUs con dato censurado | B17: =COUNTIF(FULL!$Z$7:$Z$128,"CENSURADO") -> 32 | C17: SKUs
A18: SKUs con dato confiable | B18: =COUNTIF(FULL!$Z$7:$Z$128,"CONFIABLE") -> 72 | C18: SKUs
A19: SKUs sin ventas en el período | B19: =COUNTIF(FULL!$Z$7:$Z$128,"SIN DATO") -> 18 | C19: SKUs
A20: Ventas diarias según reporte mensual | B20: =ROUND(SUMIF(FULL!$Z$7:$Z$128,"CENSURADO",FULL!$I$7:$I$128),1) -> 40.5 | C20: u/día
A21: Ventas diarias corregidas | B21: =ROUND(SUMIF(FULL!$Z$7:$Z$128,"CENSURADO",FULL!$J$7:$J$128),1) -> 76.1 | C21: u/día
A22: Cuánto subestima el reporte | B22: =IFERROR(ROUND(B21/B20,2),"") -> 1.88 | C22: veces
A24: ENVÍO
A25: Falta enviar (total) | B25: =SUM(FULL!$L$7:$L$128) -> 2628 | C25: u
A26: Se puede enviar con stock Táctica+ECOM | B26: =SUM(FULL!$P$7:$P$128) -> 1314 | C26: u
A27: No se puede cubrir por falta de stock propio | B27: =SUM(FULL!$L$7:$L$128)-SUM(FULL!$P$7:$P$128) -> 1314 | C27: u
A28: SKUs en cero en Full y sin stock para enviar | B28: =SUMPRODUCT((FULL!$F$7:$F$128=0)*(FULL!$L$7:$L$128>0)*(FULL!$O$7:$O$128=0)) -> 6 | C28: SKUs
A30: COSTO DEL MES
A31: Servicio de almacenamiento (30/06 al 29/07) | B31: 394485
A32: Cargo por stock antiguo | B32: =SUM(FULL!$AH$7:$AH$128) -> 482230
A33: Total | B33: =B31+B32 -> 876715
A35: LÍMITE DE LOS 180 DÍAS
A36: Unidades en franja 4-6 meses | B36: =SUM(FULL!$AF$7:$AF$128) -> 875 | C36: u
A37: Aumento total si todas cruzaran | B37: =SUM(FULL!$AI$7:$AI$128) -> 3513125
A38: Solo las marcadas STOCK VIEJO EN RIESGO — unidades | B38: =SUMIF(FULL!$AL$7:$AL$128,"STOCK VIEJO EN RIESGO",FULL!$AF$7:$AF$128) -> 81 | C38: u
A39: Solo las marcadas STOCK VIEJO EN RIESGO — aumento | B39: =SUMIF(FULL!$AL$7:$AL$128,"STOCK VIEJO EN RIESGO",FULL!$AI$7:$AI$128) -> 325215
A41: VALOR
A42: Unidades en Full | B42: =SUM(FULL!$F$7:$F$128) -> 2183 | C42: u
A43: Valor del stock en Full | B43: =SUM(FULL!$AK$7:$AK$128) -> 14766
A44: SKUs sin costo cargado | B44: =COUNTIF(FULL!$AJ$7:$AJ$128,0) -> 19 | C44: SKUs

Sheet FULL
A1: FULL — TABLA OPERATIVA
A2: Cuenta IT (115764017) · Ventas: 32 días al 11/08/2026 · Stock Full y cargos al 11/08/2026 · Stock Táctica/ECOM al 03/08/2026
A3: Semanas objetivo | C3: 3 | D3: Días del período de ventas | G3: 32 | H3: Fecha de corte | J3: 46245 | K3: Cargo unidad 4-6 meses | N3: 470 | O3: Cargo unidad +6 meses | Q3: 4485
A5: PARA ARMAR EL ENVÍO | Q5: CONTROL DE LA PUBLICACIÓN | T5: CÓMO SE MIDIÓ LA DEMANDA | AB5: CUÁNDO SE QUIEBRA | AD5: ANTIGÜEDAD Y CARGOS | AJ5: VALOR | AL5: ESTADO
A6: Cuenta | B6: Código ML | C6: SKU | D6: MLA (publicación) | E6: Título | F6: Stock en Full | G6: Envíos pendientes | H6: Ventas 30 días | I6: Ventas diarias simple | J6: Ventas diarias corregida | K6: Stock objetivo (semanas) | L6: Falta enviar | M6: Stock Táctica | N6: Stock ECOM | O6: Disponible T+E | P6: ENVIAR POSIBLE | Q6: Estado publicación | R6: Publ. | S6: Tamaño | T6: Unidades 32d | U6: Días con venta | V6: Ventana con stock | W6: Días sin vender | X6: Stock prom 30d ML | Y6: Rotación | Z6: Estado del dato | AA6: Factor | AB6: Cobertura (días) | AC6: Quiebre estimado | AD6: No aptas | AE6: Antigüedad máx | AF6: Unid. 4-6 meses | AG6: Días al límite 180 | AH6: Cargo actual | AI6: Aumento si cruza | AJ6: Costo USD | AK6: Valor en Full USD | AL6: ALERTA
A7: IT | B7: TNSC93322 | C7: CB435A-436A-CE285AUNIVCOMP | D7: 616880448 | E7: Toner Alternativo Para Cb436a 435a 36a P1505 M1120 M1522 Negro | F7: 566 | G7: 0 | H7: 1835 | I7: =ROUND($H7/30,2) -> 61.17 | J7: =IF($Z7="CENSURADO",ROUND($T7/MAX($V7,3),2),ROUND($T7/$G$3,2)) -> 61.47 | K7: =ROUNDUP($J7*$C$3*7,0) -> 1291 | L7: =MAX(0,$K7-$F7-$G7) -> 725 | M7: 160 | N7: -1 | O7: =$M7+$N7 -> 159 | P7: =MIN($L7,$O7) -> 159 | Q7: Activa | R7: 12 | S7: Mediano | T7: 1967 | U7: 32 | V7: 32 | W7: 0 | X7: 1560 | Y7: =IF($X7=0,"",ROUND($H7/$X7,2)) -> 1.18 | Z7: =IF(AND($F7=0,$T7>=5,$W7>=3),"CENSURADO",IF(AND($Y7<>"",$Y7>=3,$T7>=10),"CENSURADO",IF($T7=0,"SIN DATO","CONFIABLE"))) -> CONFIABLE | AA7: =IF($I7=0,"",ROUND($J7/MAX($I7,0.01),2)) -> 1 | AB7: =IF($J7<=0,"",ROUND(($F7+$G7)/$J7,0)) -> 9 | AC7: =IF($AB7="","",$J$3+$AB7) -> 46254 | AD7: 0 | AE7: 170 | AF7: 681 | AG7: =IF($AF7=0,"",MAX(0,180-$AE7)) -> 10 | AH7: 320070 | AI7: =IF($AF7=0,"",$AF7*$Q$3-$AF7*$N$3) -> 2734215 | AJ7: 2.81 | AK7: =ROUND($F7*$AJ7,0) -> 1590 | AL7: =IF(AND($F7=0,$T7>0,$O7=0),"QUIEBRE Y SIN STOCK PARA ENVIAR",IF(AND($F7=0,$T7>0),"QUIEBRE",IF($F7=0,"SIN STOCK SIN DEMANDA",IF(AND($AF7>0,$AG7<>"",OR($AB7="",$AB7>$AG7)),"STOCK VIEJO EN RIESGO",IF(AND($T7=0,$H7=0),"SIN ROTACION",IF($AB7="","-",IF($AB7<14,"REPONER",IF($AB7>84,"SOBRE-STOCK","EN RANGO")))))))) -> REPONER
A8: IT | B8: WRRA16826 | C8: MLTD111SCOMPV2 | D8: 1431106425 | 630220607 | E8: Toner Alternativo Para Samsung D111 M2020w 2020 M2070w 2070w Negro | F8: 0 | G8: 0 | H8: 396 | I8: =ROUND($H8/30,2) -> 13.2 | J8: =IF($Z8="CENSURADO",ROUND($T8/MAX($V8,3),2),ROUND($T8/$G$3,2)) -> 15.88 | K8: =ROUNDUP($J8*$C$3*7,0) -> 334 | L8: =MAX(0,$K8-$F8-$G8) -> 334 | M8: 30 | N8: -5 | O8: =$M8+$N8 -> 25 | P8: =MIN($L8,$O8) -> 25 | R8: 2 | S8: Mediano | T8: 397 | U8: 25 | V8: 25 | W8: 7 | X8: 155 | Y8: =IF($X8=0,"",ROUND($H8/$X8,2)) -> 2.55 | Z8: =IF(AND($F8=0,$T8>=5,$W8>=3),"CENSURADO",IF(AND($Y8<>"",$Y8>=3,$T8>=10),"CENSURADO",IF($T8=0,"SIN DATO","CONFIABLE"))) -> CENSURADO | AA8: =IF($I8=0,"",ROUND($J8/MAX($I8,0.01),2)) -> 1.2 | AB8: =IF($J8<=0,"",ROUND(($F8+$G8)/$J8,0)) -> 0 | AC8: =IF($AB8="","",$J$3+$AB8) -> 46245 | AD8: 0 | AE8: 0 | AF8: 0 | AG8: =IF($AF8=0,"",MAX(0,180-$AE8)) | AH8: 0 | AI8: =IF($AF8=0,"",$AF8*$Q$3-$AF8*$N$3) | AJ8: 2.64 | AK8: =ROUND($F8*$AJ8,0) -> 0 | AL8: =IF(AND($F8=0,$T8>0,$O8=0),"QUIEBRE Y SIN STOCK PARA ENVIAR",IF(AND($F8=0,$T8>0),"QUIEBRE",IF($F8=0,"SIN STOCK SIN DEMANDA",IF(AND($AF8>0,$AG8<>"",OR($AB8="",$AB8>$AG8)),"STOCK VIEJO EN RIESGO",IF(AND($T8=0,$H8=0),"SIN ROTACION",IF($AB8="","-",IF($AB8<14,"REPONER",IF($AB8>84,"SOBRE-STOCK","EN RANGO")))))))) -> QUIEBRE
A9: IT | B9: DUHF44843 | C9: CF217ACOMP | D9: 751602895 | E9: Toner Alternativo Para Cf217a M102 M130 217a 17a Con Chip Negro/tricolor Impreso | F9: 67 | G9: 210 | H9: 204 | I9: =ROUND($H9/30,2) -> 6.8 | J9: =IF($Z9="CENSURADO",ROUND($T9/MAX($V9,3),2),ROUND($T9/$G$3,2)) -> 9.69 | K9: =ROUNDUP($J9*$C$3*7,0) -> 204 | L9: =MAX(0,$K9-$F9-$G9) -> 0 | M9: 5687 | N9: 1169 | O9: =$M9+$N9 -> 6856 | P9: =MIN($L9,$O9) -> 0 | Q9: Activa | R9: 2 | S9: Mediano | T9: 310 | U9: 26 | V9: 30 | W9: 1 | X9: 153 | Y9: =IF($X9=0,"",ROUND($H9/$X9,2)) -> 1.33 | Z9: =IF(AND($F9=0,$T9>=5,$W9>=3),"CENSURADO",IF(AND($Y9<>"",$Y9>=3,$T9>=10),"CENSURADO",IF($T9=0,"SIN DATO","CONFIABLE"))) -> CONFIABLE | AA9: =IF($I9=0,"",ROUND($J9/MAX($I9,0.01),2)) -> 1.43 | AB9: =IF($J9<=0,"",ROUND(($F9+$G9)/$J9,0)) -> 29 | AC9: =IF($AB9="","",$J$3+$AB9) -> 46274 | AD9: 0 | AE9: 0 | AF9: 0 | AG9: =IF($AF9=0,"",MAX(0,180-$AE9)) | AH9: 0 | AI9: =IF($AF9=0,"",$AF9*$Q$3-$AF9*$N$3) | AJ9: 2.65 | AK9: =ROUND($F9*$AJ9,0) -> 178 | AL9: =IF(AND($F9=0,$T9>0,$O9=0),"QUIEBRE Y SIN STOCK PARA ENVIAR",IF(AND($F9=0,$T9>0),"QUIEBRE",IF($F9=0,"SIN STOCK SIN DEMANDA",IF(AND($AF9>0,$AG9<>"",OR($AB9="",$AB9>$AG9)),"STOCK VIEJO EN RIESGO",IF(AND($T9=0,$H9=0),"SIN ROTACION",IF($AB9="","-",IF($AB9<14,"REPONER",IF($AB9>84,"SOBRE-STOCK","EN RANGO")))))))) -> EN RANGO
A10: IT | B10: OJMY16755 | C10: CF279ACOMP | D10: 762970302 | E10: Toner Alternativo M12w M12 12w M26nw M12a M26 Cf279 79a 279a Negro | F10: 0 | G10: 0 | H10: 0 | I10: =ROUND($H10/30,2) -> 0 | J10: =IF($Z10="CENSURADO",ROUND($T10/MAX($V10,3),2),ROUND($T10/$G$3,2)) -> 9.16 | K10: =ROUNDUP($J10*$C$3*7,0) -> 193 | L10: =MAX(0,$K10-$F10-$G10) -> 193 | M10: 519 | N10: 1392 | O10: =$M10+$N10 -> 1911 | P10: =MIN($L10,$O10) -> 193 | Q10: Activa | R10: 1 | S10: Mediano | T10: 293 | U10: 28 | V10: 31 | W10: 1 | X10: 0 | Y10: =IF($X10=0,"",ROUND($H10/$X10,2)) | Z10: =IF(AND($F10=0,$T10>=5,$W10>=3),"CENSURADO",IF(AND($Y10<>"",$Y10>=3,$T10>=10),"CENSURADO",IF($T10=0,"SIN DATO","CONFIABLE"))) -> CONFIABLE | AA10: =IF($I10=0,"",ROUND($J10/MAX($I10,0.01),2)) | AB10: =IF($J10<=0,"",ROUND(($F10+$G10)/$J10,0)) -> 0 | AC10: =IF($AB10="","",$J$3+$AB10) -> 46245 | AD10: 0 | AE10: 0 | AF10: 0 | AG10: =IF($AF10=0,"",MAX(0,180-$AE10)) | AH10: 0 | AI10: =IF($AF10=0,"",$AF10*$Q$3-$AF10*$N$3) | AJ10: 2.15 | AK10: =ROUND($F10*$AJ10,0) -> 0 | AL10: =IF(AND($F10=0,$T10>0,$O10=0),"QUIEBRE Y SIN STOCK PARA ENVIAR",IF(AND($F10=0,$T10>0),"QUIEBRE",IF($F10=0,"SIN STOCK SIN DEMANDA",IF(AND($AF10>0,$AG10<>"",OR($AB10="",$AB10>$AG10)),"STOCK VIEJO EN RIESGO",IF(AND($T10=0,$H10=0),"SIN ROTACION",IF($AB10="","-",IF($AB10<14,"REPONER",IF($AB10>84,"SOBRE-STOCK","EN RANGO")))))))) -> QUIEBRE
A11: IT | B11: XACN86724 | C11: Q2612ACOMP | D11: 1457999139 | E11: Tóner Compatible Con Hp 2612a Para 1010 1012 1015 1018 - Rendimiendo De 2000 Pág | F11: 380 | G11: 150 | H11: 188 | I11: =ROUND($H11/30,2) -> 6.27 | J11: =IF($Z11="CENSURADO",ROUND($T11/MAX($V11,3),2),ROUND($T11/$G$3,2)) -> 8.56 | K11: =ROUNDUP($J11*$C$3*7,0) -> 180 | L11: =MAX(0,$K11-$F11-$G11) -> 0 | M11: 6241 | N11: 438 | O11: =$M11+$N11 -> 6679 | P11: =MIN($L11,$O11) -> 0 | Q11: Activa | R11: 4 | S11: Mediano | T11: 274 | U11: 27 | V11: 32 | W11: 0 | X11: 445 | Y11: =IF($X11=0,"",ROUND($H11/$X11,2)) -> 0.42 | Z11: =IF(AND($F11=0,$T11>=5,$W11>=3),"CENSURADO",IF(AND($Y11<>"",$Y11>=3,$T11>=10),"CENSURADO",IF($T11=0,"SIN DATO","CONFIABLE"))) -> CONFIABLE | AA11: =IF($I11=0,"",ROUND($J11/MAX($I11,0.01),2)) -> 1.37 | AB11: =IF($J11<=0,"",ROUND(($F11+$G11)/$J11,0)) -> 62 | AC11: =IF($AB11="","",$J$3+$AB11) -> 46307 | AD11: 0 | AE11: 0 | AF11: 0 | AG11: =IF($AF11=0,"",MAX(0,180-$AE11)) | AH11: 0 | AI11: =IF($AF11=0,"",$AF11*$Q$3-$AF11*$N$3) | AJ11: 2.84 | AK11: =ROUND($F11*$AJ11,0) -> 1079 | AL11: =IF(AND($F11=0,$T11>0,$O11=0),"QUIEBRE Y SIN STOCK PARA ENVIAR",IF(AND($F11=0,$T11>0),"QUIEBRE",IF($F11=0,"SIN STOCK SIN DEMANDA",IF(AND($AF11>0,$AG11<>"",OR($AB11="",$AB11>$AG11)),"STOCK VIEJO EN RIESGO",IF(AND($T11=0,$H11=0),"SIN ROTACION",IF($AB11="","-",IF($AB11<14,"REPONER",IF($AB11>84,"SOBRE-STOCK","EN RANGO")))))))) -> EN RANGO
A12: IT | B12: LRKS64658 | C12: LAM-ROLL-M-330MM-150MTS-32MIC | D12: 810844083 | E12: Rollo Para Laminar Mate 32 Micrones 330 Mm 150 Metros | F12: 0 | G12: 100 | H12: 123 | I12: =ROUND($H12/30,2) -> 4.1 | J12: =IF($Z12="CENSURADO",ROUND($T12/MAX($V12,3),2),ROUND($T12/$G$3,2)) -> 7.89 | K12: =ROUNDUP($J12*$C$3*7,0) -> 166 | L12: =MAX(0,$K12-$F12-$G12) -> 66 | M12: 174 | N12: 16 | O12: =$M12+$N12 -> 190 | P12: =MIN($L12,$O12) -> 66 | R12: 1 | S12: Mediano | T12: 213 | U12: 26 | V12: 27 | W12: 4 | X12: 45 | Y12: =IF($X12=0,"",ROUND($H12/$X12,2)) -> 2.73 | Z12: =IF(AND($F12=0,$T12>=5,$W12>=3),"CENSURADO",IF(AND($Y12<>"",$Y12>=3,$T12>=10),"CENSURADO",IF($T12=0,"SIN DATO","CONFIABLE"))) -> CENSURADO | AA12: =IF($I12=0,"",ROUND($J12/MAX($I12,0.01),2)) -> 1.92 | AB12: =IF($J12<=0,"",ROUND(($F12+$G12)/$J12,0)) -> 13 | AC12: =IF($AB12="","",$J$3+$AB12) -> 46258 | AD12: 0 | AE12: 0 | AF12: 0 | AG12: =IF($AF12=0,"",MAX(0,180-$AE12)) | AH12: 0 | AI12: =IF($AF12=0,"",$AF12*$Q$3-$AF12*$N$3) | AJ12: 5.74 | AK12: =ROUND($F12*$AJ12,0) -> 0 | AL12: =IF(AND($F12=0,$T12>0,$O12=0),"QUIEBRE Y SIN STOCK PARA ENVIAR",IF(AND($F12=0,$T12>0),"QUIEBRE",IF($F12=0,"SIN STOCK SIN DEMANDA",IF(AND($AF12>0,$AG12<>"",OR($AB12="",$AB12>$AG12)),"STOCK VIEJO EN RIESGO",IF(AND($T12=0,$H12=0),"SIN ROTACION",IF($AB12="","-",IF($AB12<14,"REPONER",IF($AB12>84,"SOBRE-STOCK","EN RANGO")))))))) -> QUIEBRE
A13: IT | B13: GKVM85194 | C13: MLTD101SCOMP | D13: 929612123 | E13: Toner Alternativo Para 101 Mlt D101l Ml 2165w 1500k Negro | F13: 57 | G13: 85 | H13: 105 | I13: =ROUND($H13/30,2) -> 3.5 | J13: =IF($Z13="CENSURADO",ROUND($T13/MAX($V13,3),2),ROUND($T13/$G$3,2)) -> 6 | K13: =ROUNDUP($J13*$C$3*7,0) -> 126 | L13: =MAX(0,$K13-$F13-$G13) -> 0 | M13: 9733 | N13: 202 | O13: =$M13+$N13 -> 9935 | P13: =MIN($L13,$O13) -> 0 | Q13: Activa | R13: 3 | S13: Mediano | T13: 192 | U13: 28 | V13: 32 | W13: 0 | X13: 99 | Y13: =IF($X13=0,"",ROUND($H13/$X13,2)) -> 1.06 | Z13: =IF(AND($F13=0,$T13>=5,$W13>=3),"CENSURADO",IF(AND($Y13<>"",$Y13>=3,$T13>=10),"CENSURADO",IF($T13=0,"SIN DATO","CONFIABLE"))) -> CONFIABLE | AA13: =IF($I13=0,"",ROUND($J13/MAX($I13,0.01),2)) -> 1.71 | AB13: =IF($J13<=0,"",ROUND(($F13+$G13)/$J13,0)) -> 24 | AC13: =IF($AB13="","",$J$3+$AB13) -> 46269 | AD13: 0 | AE13: 0 | AF13: 0 | AG13: =IF($AF13=0,"",MAX(0,180-$AE13)) | AH13: 0 | AI13: =IF($AF13=0,"",$AF13*$Q$3-$AF13*$N$3) | AJ13: 4.1 | AK13: =ROUND($F13*$AJ13,0) -> 234 | AL13: =IF(AND($F13=0,$T13>0,$O13=0),"QUIEBRE Y SIN STOCK PARA ENVIAR",IF(AND($F13=0,$T13>0),"QUIEBRE",IF($F13=0,"SIN STOCK SIN DEMANDA",IF(AND($AF13>0,$AG13<>"",OR($AB13="",$AB13>$AG13)),"STOCK VIEJO EN RIESGO",IF(AND($T13=0,$H13=0),"SIN ROTACION",IF($AB13="","-",IF($AB13<14,"REPONER",IF($AB13>84,"SOBRE-STOCK","EN RANGO")))))))) -> EN RANGO
A14: IT | B14: TGMU01761 | C14: CIZALLA-A4-12EN1 | D14: 1475792185 | 2384987536 | E14: Guillotina Rotativa Cizalla Corta Papel A4 300mm 12 En 1 | F14: 10 | G14: 50 | H14: 96 | I14: =ROUND($H14/30,2) -> 3.2 | J14: =IF($Z14="CENSURADO",ROUND($T14/MAX($V14,3),2),ROUND($T14/$G$3,2)) -> 4.78 | K14: =ROUNDUP($J14*$C$3*7,0) -> 101 | L14: =MAX(0,$K14-$F14-$G14) -> 41 | M14: 1217 | N14: 32 | O14: =$M14+$N14 -> 1249 | P14: =MIN($L14,$O14) -> 41 | Q14: Activa | R14: 1 | S14: Mediano | T14: 153 | U14: 30 | V14: 30 | W14: 0 | X14: 65 | Y14: =IF($X14=0,"",ROUND($H14/$X14,2)) -> 1.48 | Z14: =IF(AND($F14=0,$T14>=5,$W14>=3),"CENSURADO",IF(AND($Y14<>"",$Y14>=3,$T14>=10),"CENSURADO",IF($T14=0,"SIN DATO","CONFIABLE"))) -> CONFIABLE | AA14: =IF($I14=0,"",ROUND($J14/MAX($I14,0.01),2)) -> 1.49 | AB14: =IF($J14<=0,"",ROUND(($F14+$G14)/$J14,0)) -> 13 | AC14: =IF($AB14="","",$J$3+$AB14) -> 46258 | AD14: 0 | AE14: 0 | AF14: 0 | AG14: =IF($AF14=0,"",MAX(0,180-$AE14)) | AH14: 0 | AI14: =IF($AF14=0,"",$AF14*$Q$3-$AF14*$N$3) | AJ14: 6.1 | AK14: =ROUND($F14*$AJ14,0) -> 61 | AL14: =IF(AND($F14=0,$T14>0,$O14=0),"QUIEBRE Y SIN STOCK PARA ENVIAR",IF(AND($F14=0,$T14>0),"QUIEBRE",IF($F14=0,"SIN STOCK SIN DEMANDA",IF(AND($AF14>0,$AG14<>"",OR($AB14="",$AB14>$AG14)),"STOCK VIEJO EN RIESGO",IF(AND($T14=0,$H14=0),"SIN ROTACION",IF($AB14="","-",IF($AB14<14,"REPONER",IF($AB14>84,"SOBRE-STOCK","EN RANGO")))))))) -> REPONER
A15: IT | B15: VTUA74073 | C15: PLANCHA-SUB-PORTATIL | D15: 2091207644 | 3655836976 | E15: Estampadora Textil Portátil 10.5 Cm Blanco | F15: 56 | G15: 50 | H15: 9 | I15: =ROUND($H15/30,2) -> 0.3 | J15: =IF($Z15="CENSURADO",ROUND($T15/MAX($V15,3),2),ROUND($T15/$G$3,2)) -> 4.38 | K15: =ROUNDUP($J15*$C$3*7,0) -> 92 | L15: =MAX(0,$K15-$F15-$G15) -> 0 | M15: 167 | N15: 408 | O15: =$M15+$N15 -> 575 | P15: =MIN($L15,$O15) -> 0 | Q15: Activa | R15: 2 | S15: Pequeño | T15: 140 | U15: 24 | V15: 31 | W15: 0 | X15: 59 | Y15: =IF($X15=0,"",ROUND($H15/$X15,2)) -> 0.15 | Z15: =IF(AND($F15=0,$T15>=5,$W15>=3),"CENSURADO",IF(AND($Y15<>"",$Y15>=3,$T15>=10),"CENSURADO",IF($T15=0,"SIN DATO","CONFIABLE"))) -> CONFIABLE | AA15: =IF($I15=0,"",ROUND($J15/MAX($I15,0.01),2)) -> 14.6 | AB15: =IF($J15<=0,"",ROUND(($F15+$G15)/$J15,0)) -> 24 | AC15: =IF($AB15="","",$J$3+$AB15) -> 46269 | AD15: 0 | AE15: 0 | AF15: 0 | AG15: =IF($AF15=0,"",MAX(0,180-$AE15)) | AH15: 0 | AI15: =IF($AF15=0,"",$AF15*$Q$3-$AF15*$N$3) | AJ15: 13.25 | AK15: =ROUND($F15*$AJ15,0) -> 742 | AL15: =IF(AND($F15=0,$T15>0,$O15=0),"QUIEBRE Y SIN STOCK PARA ENVIAR",IF(AND($F15=0,$T15>0),"QUIEBRE",IF($F15=0,"SIN STOCK SIN DEMANDA",IF(AND($AF15>0,$AG15<>"",OR($AB15="",$AB15>$AG15)),"STOCK VIEJO EN RIESGO",IF(AND($T15=0,$H15=0),"SIN ROTACION",IF($AB15="","-",IF($AB15<14,"REPONER",IF($AB15>84,"SOBRE-STOCK","EN RANGO")))))))) -> EN RANGO
A16: IT | B16: GZFD15414 | C16: X2 CB435A-436A-CE285AUNIVCOMP | D16: 2693713220 | 606715836 | E16: Toner Alternativo Para 285a 435a 436a 1102w 1102 Pack X 2 Negro | F16: 0 | G16: 0 | H16: 119 | I16: =ROUND($H16/30,2) -> 3.97 | J16: =IF($Z16="CENSURADO",ROUND($T16/MAX($V16,3),2),ROUND($T16/$G$3,2)) -> 4.17 | K16: =ROUNDUP($J16*$C$3*7,0) -> 88 | L16: =MAX(0,$K16-$F16-$G16) -> 88 | M16: 0 | N16: 0 | O16: =$M16+$N16 -> 0 | P16: =MIN($L16,$O16) -> 0 | R16: 1 | S16: Mediano | T16: 121 | U16: 22 | V16: 29 | W16: 3 | X16: 70 | Y16: =IF($X16=0,"",ROUND($H16/$X16,2)) -> 1.7 | Z16: =IF(AND($F16=0,$T16>=5,$W16>=3),"CENSURADO",IF(AND($Y16<>"",$Y16>=3,$T16>=10),"CENSURADO",IF($T16=0,"SIN DATO","CONFIABLE"))) -> CENSURADO | AA16: =IF($I16=0,"",ROUND($J16/MAX($I16,0.01),2)) -> 1.05 | AB16: =IF($J16<=0,"",ROUND(($F16+$G16)/$J16,0)) -> 0 | AC16: =IF($AB16="","",$J$3+$AB16) -> 46245 | AD16: 0 | AE16: 0 | AF16: 0 | AG16: =IF($AF16=0,"",MAX(0,180-$AE16)) | AH16: 0 | AI16: =IF($AF16=0,"",$AF16*$Q$3-$AF16*$N$3) | AJ16: 0 | AK16: =ROUND($F16*$AJ16,0) -> 0 | AL16: =IF(AND($F16=0,$T16>0,$O16=0),"QUIEBRE Y SIN STOCK PARA ENVIAR",IF(AND($F16=0,$T16>0),"QUIEBRE",IF($F16=0,"SIN STOCK SIN DEMANDA",IF(AND($AF16>0,$AG16<>"",OR($AB16="",$AB16>$AG16)),"STOCK VIEJO EN RIESGO",IF(AND($T16=0,$H16=0),"SIN ROTACION",IF($AB16="","-",IF($AB16<14,"REPONER",IF($AB16>84,"SOBRE-STOCK","EN RANGO")))))))) -> QUIEBRE Y SIN STOCK PARA ENVIAR
A17: IT | B17: ESMW22207 | C17: EMERLIGHT-30LED | D17: 1607486745 | E17: Luces Luz De Emergencia 30 Leds Bateria Recargable Seguridad - Marca Global Elec | F17: 37 | G17: 0 | H17: 67 | I17: =ROUND($H17/30,2) -> 2.23 | J17: =IF($Z17="CENSURADO",ROUND($T17/MAX($V17,3),2),ROUND($T17/$G$3,2)) -> 3.69 | K17: =ROUNDUP($J17*$C$3*7,0) -> 78 | L17: =MAX(0,$K17-$F17-$G17) -> 41 | M17: 271 | N17: 88 | O17: =$M17+$N17 -> 359 | P17: =MIN($L17,$O17) -> 41 | Q17: Activa | R17: 1 | S17: Pequeño | T17: 118 | U17: 22 | V17: 30 | W17: 1 | X17: 83 | Y17: =IF($X17=0,"",ROUND($H17/$X17,2)) -> 0.81 | Z17: =IF(AND($F17=0,$T17>=5,$W17>=3),"CENSURADO",IF(AND($Y17<>"",$Y17>=3,$T17>=10),"CENSURADO",IF($T17=0,"SIN DATO","CONFIABLE"))) -> CONFIABLE | AA17: =IF($I17=0,"",ROUND($J17/MAX($I17,0.01),2)) -> 1.65 | AB17: =IF($J17<=0,"",ROUND(($F17+$G17)/$J17,0)) -> 10 | AC17: =IF($AB17="","",$J$3+$AB17) -> 46255 | AD17: 0 | AE17: 0 | AF17: 0 | AG17: =IF($AF17=0,"",MAX(0,180-$AE17)) | AH17: 0 | AI17: =IF($AF17=0,"",$AF17*$Q$3-$AF17*$N$3) | AJ17: 1.55 | AK17: =ROUND($F17*$AJ17,0) -> 57 | AL17: =IF(AND($F17=0,$T17>0,$O17=0),"QUIEBRE Y SIN STOCK PARA ENVIAR",IF(AND($F17=0,$T17>0),"QUIEBRE",IF($F17=0,"SIN STOCK SIN DEMANDA",IF(AND($AF17>0,$AG17<>"",OR($AB17="",$AB17>$AG17)),"STOCK VIEJO EN RIESGO",IF(AND($T17=0,$H17=0),"SIN ROTACION",IF($AB17="","-",IF($AB17<14,"REPONER",IF($AB17>84,"SOBRE-STOCK","EN RANGO")))))))) -> REPONER
A18: IT | B18: YAEM28869 | C18: CUTTERCIRCLE | D18: 2000771898 | E18: Cutter Compas Cortante Circular De 100 A 320 Mm | F18: 0 | G18: 50 | H18: 58 | I18: =ROUND($H18/30,2) -> 1.93 | J18: =IF($Z18="CENSURADO",ROUND($T18/MAX($V18,3),2),ROUND($T18/$G$3,2)) -> 3.34 | K18: =ROUNDUP($J18*$C$3*7,0) -> 71 | L18: =MAX(0,$K18-$F18-$G18) -> 21 | M18: 3338 | N18: 31 | O18: =$M18+$N18 -> 3369 | P18: =MIN($L18,$O18) -> 21 | Q18: Activa | R18: 1 | S18: Mediano | T18: 107 | U18: 30 | V18: 32 | W18: 0 | X18: 16 | Y18: =IF($X18=0,"",ROUND($H18/$X18,2)) -> 3.63 | Z18: =IF(AND($F18=0,$T18>=5,$W18>=3),"CENSURADO",IF(AND($Y18<>"",$Y18>=3,$T18>=10),"CENSURADO",IF($T18=0,"SIN DATO","CONFIABLE"))) -> CENSURADO | AA18: =IF($I18=0,"",ROUND($J18/MAX($I18,0.01),2)) -> 1.73 | AB18: =IF($J18<=0,"",ROUND(($F18+$G18)/$J18,0)) -> 15 | AC18: =IF($AB18="","",$J$3+$AB18) -> 46260 | AD18: 0 | AE18: 0 | AF18: 0 | AG18: =IF($AF18=0,"",MAX(0,180-$AE18)) | AH18: 0 | AI18: =IF($AF18=0,"",$AF18*$Q$3-$AF18*$N$3) | AJ18: 2.48 | AK18: =ROUND($F18*$AJ18,0) -> 0 | AL18: =IF(AND($F18=0,$T18>0,$O18=0),"QUIEBRE Y SIN STOCK PARA ENVIAR",IF(AND($F18=0,$T18>0),"QUIEBRE",IF($F18=0,"SIN STOCK SIN DEMANDA",IF(AND($AF18>0,$AG18<>"",OR($AB18="",$AB18>$AG18)),"STOCK VIEJO EN RIESGO",IF(AND($T18=0,$H18=0),"SIN ROTACION",IF($AB18="","-",IF($AB18<14,"REPONER",IF($AB18>84,"SOBRE-STOCK","EN RANGO")))))))) -> QUIEBRE
A19: IT | B19: HLNI07986 | C19: CABLETYPEC1MW | D19: 1144172936 | 2524776910 | E19: Cable Usb Para Carga Y Datos Tipo C De 1 Mt Blanco | F19: 0 | G19: 10 | H19: 77 | I19: =ROUND($H19/30,2) -> 2.57 | J19: =IF($Z19="CENSURADO",ROUND($T19/MAX($V19,3),2),ROUND($T19/$G$3,2)) -> 5.32 | K19: =ROUNDUP($J19*$C$3*7,0) -> 112 | L19: =MAX(0,$K19-$F19-$G19) -> 102 | M19: 3966 | N19: 35 | O19: =$M19+$N19 -> 4001 | P19: =MIN($L19,$O19) -> 102 | Q19: Activa | R19: 1 | S19: Pequeño | T19: 101 | U19: 10 | V19: 19 | W19: 5 | X19: 50 | Y19: =IF($X19=0,"",ROUND($H19/$X19,2)) -> 1.54 | Z19: =IF(AND($F19=0,$T19>=5,$W19>=3),"CENSURADO",IF(AND($Y19<>"",$Y19>=3,$T19>=10),"CENSURADO",IF($T19=0,"SIN DATO","CONFIABLE"))) -> CENSURADO | AA19: =IF($I19=0,"",ROUND($J19/MAX($I19,0.01),2)) -> 2.07 | AB19: =IF($J19<=0,"",ROUND(($F19+$G19)/$J19,0)) -> 2 | AC19: =IF($AB19="","",$J$3+$AB19) -> 46247 | AD19: 0 | AE19: 0 | AF19: 0 | AG19: =IF($AF19=0,"",MAX(0,180-$AE19)) | AH19: 0 | AI19: =IF($AF19=0,"",$AF19*$Q$3-$AF19*$N$3) | AJ19: 0.4 | AK19: =ROUND($F19*$AJ19,0) -> 0 | AL19: =IF(AND($F19=0,$T19>0,$O19=0),"QUIEBRE Y SIN STOCK PARA ENVIAR",IF(AND($F19=0,$T19>0),"QUIEBRE",IF($F19=0,"SIN STOCK SIN DEMANDA",IF(AND($AF19>0,$AG19<>"",OR($AB19="",$AB19>$AG19)),"STOCK VIEJO EN RIESGO",IF(AND($T19=0,$H19=0),"SIN ROTACION",IF($AB19="","-",IF($AB19<14,"REPONER",IF($AB19>84,"SOBRE-STOCK","EN RANGO")))))))) -> QUIEBRE
A20: IT | B20: RFFM10562 | C20: TVS-ARM-14-42I-200X200-V3 | D20: 2094731522 | E20: Soporte Tv Led Lcd Móvil Largo Simple De 14 A 42 Pulgadas Negro | F20: 0 | G20: 10 | H20: 73 | I20: =ROUND($H20/30,2) -> 2.43 | J20: =IF($Z20="CENSURADO",ROUND($T20/MAX($V20,3),2),ROUND($T20/$G$3,2)) -> 4.13 | K20: =ROUNDUP($J20*$C$3*7,0) -> 87 | L20: =MAX(0,$K20-$F20-$G20) -> 77 | M20: 1221 | N20: 15 | O20: =$M20+$N20 -> 1236 | P20: =MIN($L20,$O20) -> 77 | Q20: Activa | R20: 1 | S20: Mediano | T20: 95 | U20: 16 | V20: 23 | W20: 3 | X20: 54 | Y20: =IF($X20=0,"",ROUND($H20/$X20,2)) -> 1.35 | Z20: =IF(AND($F20=0,$T20>=5,$W20>=3),"CENSURADO",IF(AND($Y20<>"",$Y20>=3,$T20>=10),"CENSURADO",IF($T20=0,"SIN DATO","CONFIABLE"))) -> CENSURADO | AA20: =IF($I20=0,"",ROUND($J20/MAX($I20,0.01),2)) -> 1.7 | AB20: =IF($J20<=0,"",ROUND(($F20+$G20)/$J20,0)) -> 2 | AC20: =IF($AB20="","",$J$3+$AB20) -> 46247 | AD20: 0 | AE20: 0 | AF20: 0 | AG20: =IF($AF20=0,"",MAX(0,180-$AE20)) | AH20: 0 | AI20: =IF($AF20=0,"",$AF20*$Q$3-$AF20*$N$3) | AJ20: 3.16 | AK20: =ROUND($F20*$AJ20,0) -> 0 | AL20: =IF(AND($F20=0,$T20>0,$O20=0),"QUIEBRE Y SIN STOCK PARA ENVIAR",IF(AND($F20=0,$T20>0),"QUIEBRE",IF($F20=0,"SIN STOCK SIN DEMANDA",IF(AND($AF20>0,$AG20<>"",OR($AB20="",$AB20>$AG20)),"STOCK VIEJO EN RIESGO",IF(AND($T20=0,$H20=0),"SIN ROTACION",IF($AB20="","-",IF($AB20<14,"REPONER",IF($AB20>84,"SOBRE-STOCK","EN RANGO")))))))) -> QUIEBRE
A21: IT | B21: EYBK93102 | C21: CUTTERROTA-45MM | D21: 2012428570 | 2683194688 | E21: Cutter Rotativo De 45mm De Diámetro Para Corte Recto | F21: 0 | G21: 30 | H21: 44 | I21: =ROUND($H21/30,2) -> 1.47 | J21: =IF($Z21="CENSURADO",ROUND($T21/MAX($V21,3),2),ROUND($T21/$G$3,2)) -> 2.53 | K21: =ROUNDUP($J21*$C$3*7,0) -> 54 | L21: =MAX(0,$K21-$F21-$G21) -> 24 | M21: 677 | N21: 138 | O21: =$M21+$N21 -> 815 | P21: =MIN($L21,$O21) -> 24 | Q21: Activa | R21: 1 | S21: Pequeño | T21: 81 | U21: 28 | V21: 31 | W21: 0 | X21: 23 | Y21: =IF($X21=0,"",ROUND($H21/$X21,2)) -> 1.91 | Z21: =IF(AND($F21=0,$T21>=5,$W21>=3),"CENSURADO",IF(AND($Y21<>"",$Y21>=3,$T21>=10),"CENSURADO",IF($T21=0,"SIN DATO","CONFIABLE"))) -> CONFIABLE | AA21: =IF($I21=0,"",ROUND($J21/MAX($I21,0.01),2)) -> 1.72 | AB21: =IF($J21<=0,"",ROUND(($F21+$G21)/$J21,0)) -> 12 | AC21: =IF($AB21="","",$J$3+$AB21) -> 46257 | AD21: 0 | AE21: 0 | AF21: 0 | AG21: =IF($AF21=0,"",MAX(0,180-$AE21)) | AH21: 0 | AI21: =IF($AF21=0,"",$AF21*$Q$3-$AF21*$N$3) | AJ21: 1.44 | AK21: =ROUND($F21*$AJ21,0) -> 0 | AL21: =IF(AND($F21=0,$T21>0,$O21=0),"QUIEBRE Y SIN STOCK PARA ENVIAR",IF(AND($F21=0,$T21>0),"QUIEBRE",IF($F21=0,"SIN STOCK SIN DEMANDA",IF(AND($AF21>0,$AG21<>"",OR($AB21="",$AB21>$AG21)),"STOCK VIEJO EN RIESGO",IF(AND($T21=0,$H21=0),"SIN ROTACION",IF($AB21="","-",IF($AB21<14,"REPONER",IF($AB21>84,"SOBRE-STOCK","EN RANGO")))))))) -> QUIEBRE
A22: IT | B22: LKLY99491 | C22: PAPERDFG220A4-20 | D22: 1827462704 | E22: Papel Doble Faz Glossy A4 220 Grs Pack X20 Hojas Blanco | F22: 0 | G22: 0 | H22: 50 | I22: =ROUND($H22/30,2) -> 1.67 | J22: =IF($Z22="CENSURADO",ROUND($T22/MAX($V22,3),2),ROUND($T22/$G$3,2)) -> 5.2 | K22: =ROUNDUP($J22*$C$3*7,0) -> 110 | L22: =MAX(0,$K22-$F22-$G22) -> 110 | M22: 0 | N22: 0 | O22: =$M22+$N22 -> 0 | P22: =MIN($L22,$O22) -> 0 | R22: 2 | S22: Mediano | T22: 78 | U22: 13 | V22: 15 | W22: 17 | X22: 10 | Y22: =IF($X22=0,"",ROUND($H22/$X22,2)) -> 5 | Z22: =IF(AND($F22=0,$T22>=5,$W22>=3),"CENSURADO",IF(AND($Y22<>"",$Y22>=3,$T22>=10),"CENSURADO",IF($T22=0,"SIN DATO","CONFIABLE"))) -> CENSURADO | AA22: =IF($I22=0,"",ROUND($J22/MAX($I22,0.01),2)) -> 3.11 | AB22: =IF($J22<=0,"",ROUND(($F22+$G22)/$J22,0)) -> 0 | AC22: =IF($AB22="","",$J$3+$AB22) -> 46245 | AD22: 0 | AE22: 0 | AF22: 0 | AG22: =IF($AF22=0,"",MAX(0,180-$AE22)) | AH22: 0 | AI22: =IF($AF22=0,"",$AF22*$Q$3-$AF22*$N$3) | AJ22: 0.61 | AK22: =ROUND($F22*$AJ22,0) -> 0 | AL22: =IF(AND($F22=0,$T22>0,$O22=0),"QUIEBRE Y SIN STOCK PARA ENVIAR",IF(AND($F22=0,$T22>0),"QUIEBRE",IF($F22=0,"SIN STOCK SIN DEMANDA",IF(AND($AF22>0,$AG22<>"",OR($AB22="",$AB22>$AG22)),"STOCK VIEJO EN RIESGO",IF(AND($T22=0,$H22=0),"SIN ROTACION",IF($AB22="","-",IF($AB22<14,"REPONER",IF($AB22>84,"SOBRE-STOCK","EN RANGO")))))))) -> QUIEBRE Y SIN STOCK PARA ENVIAR
A23: IT | B23: PDOM19535 | C23: TVS-ARM-14-42I-200X200 | D23: 1458409112 | E23: Soporte Global Tvs-arm-14-42i-200x200 Tv Led Lcd Con Brazo Vesa 200x200 Color Ne | F23: 3 | G23: 10 | H23: 50 | I23: =ROUND($H23/30,2) -> 1.67 | J23: =IF($Z23="CENSURADO",ROUND($T23/MAX($V23,3),2),ROUND($T23/$G$3,2)) -> 2.44 | K23: =ROUNDUP($J23*$C$3*7,0) -> 52 | L23: =MAX(0,$K23-$F23-$G23) -> 39 | M23: 1470 | N23: 4 | O23: =$M23+$N23 -> 1474 | P23: =MIN($L23,$O23) -> 39 | Q23: Activa | R23: 1 | S23: Mediano | T23: 78 | U23: 24 | V23: 28 | W23: 0 | X23: 33 | Y23: =IF($X23=0,"",ROUND($H23/$X23,2)) -> 1.52 | Z23: =IF(AND($F23=0,$T23>=5,$W23>=3),"CENSURADO",IF(AND($Y23<>"",$Y23>=3,$T23>=10),"CENSURADO",IF($T23=0,"SIN DATO","CONFIABLE"))) -> CONFIABLE | AA23: =IF($I23=0,"",ROUND($J23/MAX($I23,0.01),2)) -> 1.46 | AB23: =IF($J23<=0,"",ROUND(($F23+$G23)/$J23,0)) -> 5 | AC23: =IF($AB23="","",$J$3+$AB23) -> 46250 | AD23: 0 | AE23: 0 | AF23: 0 | AG23: =IF($AF23=0,"",MAX(0,180-$AE23)) | AH23: 0 | AI23: =IF($AF23=0,"",$AF23*$Q$3-$AF23*$N$3) | AJ23: 3.84 | AK23: =ROUND($F23*$AJ23,0) -> 12 | AL23: =IF(AND($F23=0,$T23>0,$O23=0),"QUIEBRE Y SIN STOCK PARA ENVIAR",IF(AND($F23=0,$T23>0),"QUIEBRE",IF($F23=0,"SIN STOCK SIN DEMANDA",IF(AND($AF23>0,$AG23<>"",OR($AB23="",$AB23>$AG23)),"STOCK VIEJO EN RIESGO",IF(AND($T23=0,$H23=0),"SIN ROTACION",IF($AB23="","-",IF($AB23<14,"REPONER",IF($AB23>84,"SOBRE-STOCK","EN RANGO")))))))) -> REPONER
A24: IT | B24: FBAY21200 | C24: MLTD111LCOMPV2 | D24: 612395687 | E24: Toner Alternativo Para Samsung 111l Mlt D111l M2020w M2070w Negro | F24: 4 | G24: 0 | H24: 20 | I24: =ROUND($H24/30,2) -> 0.67 | J24: =IF($Z24="CENSURADO",ROUND($T24/MAX($V24,3),2),ROUND($T24/$G$3,2)) -> 2.25 | K24: =ROUNDUP($J24*$C$3*7,0) -> 48 | L24: =MAX(0,$K24-$F24-$G24) -> 44 | M24: 726 | N24: 2616 | O24: =$M24+$N24 -> 3342 | P24: =MIN($L24,$O24) -> 44 | Q24: Activa | R24: 1 | S24: Mediano | T24: 72 | U24: 21 | V24: 29 | W24: 0 | X24: 19 | Y24: =IF($X24=0,"",ROUND($H24/$X24,2)) -> 1.05 | Z24: =IF(AND($F24=0,$T24>=5,$W24>=3),"CENSURADO",IF(AND($Y24<>"",$Y24>=3,$T24>=10),"CENSURADO",IF($T24=0,"SIN DATO","CONFIABLE"))) -> CONFIABLE | AA24: =IF($I24=0,"",ROUND($J24/MAX($I24,0.01),2)) -> 3.36 | AB24: =IF($J24<=0,"",ROUND(($F24+$G24)/$J24,0)) -> 2 | AC24: =IF($AB24="","",$J$3+$AB24) -> 46247 | AD24: 0 | AE24: 0 | AF24: 0 | AG24: =IF($AF24=0,"",MAX(0,180-$AE24)) | AH24: 0 | AI24: =IF($AF24=0,"",$AF24*$Q$3-$AF24*$N$3) | AJ24: 2.66 | AK24: =ROUND($F24*$AJ24,0) -> 11 | AL24: =IF(AND($F24=0,$T24>0,$O24=0),"QUIEBRE Y SIN STOCK PARA ENVIAR",IF(AND($F24=0,$T24>0),"QUIEBRE",IF($F24=0,"SIN STOCK SIN DEMANDA",IF(AND($AF24>0,$AG24<>"",OR($AB24="",$AB24>$AG24)),"STOCK VIEJO EN RIESGO",IF(AND($T24=0,$H24=0),"SIN ROTACION",IF($AB24="","-",IF($AB24<14,"REPONER",IF($AB24>84,"SOBRE-STOCK","EN RANGO")))))))) -> REPONER
A25: IT | B25: COCF22823 | C25: X2 EMERLIGHT-30LED | D25: 1607512661 | E25: Pack De 2 Luces Luz De Emergencia 30 Leds Bateria Recargable Seguridad - Marca G | F25: 0 | G25: 0 | H25: 42 | I25: =ROUND($H25/30,2) -> 1.4 | J25: =IF($Z25="CENSURADO",ROUND($T25/MAX($V25,3),2),ROUND($T25/$G$3,2)) -> 1.72 | K25: =ROUNDUP($J25*$C$3*7,0) -> 37 | L25: =MAX(0,$K25-$F25-$G25) -> 37 | M25: 0 | N25: 0 | O25: =$M25+$N25 -> 0 | P25: =MIN($L25,$O25) -> 0 | Q25: Activa | R25: 1 | S25: Pequeño | T25: 55 | U25: 24 | V25: 32 | W25: 0 | X25: 15 | Y25: =IF($X25=0,"",ROUND($H25/$X25,2)) -> 2.8 | Z25: =IF(AND($F25=0,$T25>=5,$W25>=3),"CENSURADO",IF(AND($Y25<>"",$Y25>=3,$T25>=10),"CENSURADO",IF($T25=0,"SIN DATO","CONFIABLE"))) -> CONFIABLE | AA25: =IF($I25=0,"",ROUND($J25/MAX($I25,0.01),2)) -> 1.23 | AB25: =IF($J25<=0,"",ROUND(($F25+$G25)/$J25,0)) -> 0 | AC25: =IF($AB25="","",$J$3+$AB25) -> 46245 | AD25: 0 | AE25: 0 | AF25: 0 | AG25: =IF($AF25=0,"",MAX(0,180-$AE25)) | AH25: 0 | AI25: =IF($AF25=0,"",$AF25*$Q$3-$AF25*$N$3) | AJ25: 0 | AK25: =ROUND($F25*$AJ25,0) -> 0 | AL25: =IF(AND($F25=0,$T25>0,$O25=0),"QUIEBRE Y SIN STOCK PARA ENVIAR",IF(AND($F25=0,$T25>0),"QUIEBRE",IF($F25=0,"SIN STOCK SIN DEMANDA",IF(AND($AF25>0,$AG25<>"",OR($AB25="",$AB25>$AG25)),"STOCK VIEJO EN RIESGO",IF(AND($T25=0,$H25=0),"SIN ROTACION",IF($AB25="","-",IF($AB25<14,"REPONER",IF($AB25>84,"SOBRE-STOCK","EN RANGO")))))))) -> QUIEBRE Y SIN STOCK PARA ENVIAR
A26: IT | B26: GEQW17118 | C26: CF230ACOMP | D26: 708048237 | E26: Toner Alternativo Para Cf 230a M203dn M227fdw Con Chip Negro | F26: 18 | G26: 0 | H26: 12 | I26: =ROUND($H26/30,2) -> 0.4 | J26: =IF($Z26="CENSURADO",ROUND($T26/MAX($V26,3),2),ROUND($T26/$G$3,2)) -> 1.53 | K26: =ROUNDUP($J26*$C$3*7,0) -> 33 | L26: =MAX(0,$K26-$F26-$G26) -> 15 | M26: 525 | N26: 1016 | O26: =$M26+$N26 -> 1541 | P26: =MIN($L26,$O26) -> 15 | Q26: Activa | R26: 1 | S26: Mediano | T26: 49 | U26: 9 | V26: 24 | W26: 6 | X26: 25 | Y26: =IF($X26=0,"",ROUND($H26/$X26,2)) -> 0.48 | Z26: =IF(AND($F26=0,$T26>=5,$W26>=3),"CENSURADO",IF(AND($Y26<>"",$Y26>=3,$T26>=10),"CENSURADO",IF($T26=0,"SIN DATO","CONFIABLE"))) -> CONFIABLE | AA26: =IF($I26=0,"",ROUND($J26/MAX($I26,0.01),2)) -> 3.83 | AB26: =IF($J26<=0,"",ROUND(($F26+$G26)/$J26,0)) -> 12 | AC26: =IF($AB26="","",$J$3+$AB26) -> 46257 | AD26: 0 | AE26: 205 | AF26: 1 | AG26: =IF($AF26=0,"",MAX(0,180-$AE26)) -> 0 | AH26: 45320 | AI26: =IF($AF26=0,"",$AF26*$Q$3-$AF26*$N$3) -> 4015 | AJ26: 2.14 | AK26: =ROUND($F26*$AJ26,0) -> 39 | AL26: =IF(AND($F26=0,$T26>0,$O26=0),"QUIEBRE Y SIN STOCK PARA ENVIAR",IF(AND($F26=0,$T26>0),"QUIEBRE",IF($F26=0,"SIN STOCK SIN DEMANDA",IF(AND($AF26>0,$AG26<>"",OR($AB26="",$AB26>$AG26)),"STOCK VIEJO EN RIESGO",IF(AND($T26=0,$H26=0),"SIN ROTACION",IF($AB26="","-",IF($AB26<14,"REPONER",IF($AB26>84,"SOBRE-STOCK","EN RANGO")))))))) -> STOCK VIEJO EN RIESGO
A27: IT | B27: UIUW05655 | C27: 408161COMP | D27: 1431642515 | 719603965 | E27: Toner Alternativo Para Ricoh 408161 Sp377dnwx 377sfnwx Negro | F27: 0 | G27: 0 | H27: 40 | I27: =ROUND($H27/30,2) -> 1.33 | J27: =IF($Z27="CENSURADO",ROUND($T27/MAX($V27,3),2),ROUND($T27/$G$3,2)) -> 2 | K27: =ROUNDUP($J27*$C$3*7,0) -> 42 | L27: =MAX(0,$K27-$F27-$G27) -> 42 | M27: 10 | N27: 0 | O27: =$M27+$N27 -> 10 | P27: =MIN($L27,$O27) -> 10 | R27: 1 | S27: Mediano | T27: 46 | U27: 10 | V27: 23 | W27: 6 | X27: 14 | Y27: =IF($X27=0,"",ROUND($H27/$X27,2)) -> 2.86 | Z27: =IF(AND($F27=0,$T27>=5,$W27>=3),"CENSURADO",IF(AND($Y27<>"",$Y27>=3,$T27>=10),"CENSURADO",IF($T27=0,"SIN DATO","CONFIABLE"))) -> CENSURADO | AA27: =IF($I27=0,"",ROUND($J27/MAX($I27,0.01),2)) -> 1.5 | AB27: =IF($J27<=0,"",ROUND(($F27+$G27)/$J27,0)) -> 0 | AC27: =IF($AB27="","",$J$3+$AB27) -> 46245 | AD27: 0 | AE27: 170 | AF27: 51 | AG27: =IF($AF27=0,"",MAX(0,180-$AE27)) -> 10 | AH27: 23970 | AI27: =IF($AF27=0,"",$AF27*$Q$3-$AF27*$N$3) -> 204765 | AJ27: 5.95 | AK27: =ROUND($F27*$AJ27,0) -> 0 | AL27: =IF(AND($F27=0,$T27>0,$O27=0),"QUIEBRE Y SIN STOCK PARA ENVIAR",IF(AND($F27=0,$T27>0),"QUIEBRE",IF($F27=0,"SIN STOCK SIN DEMANDA",IF(AND($AF27>0,$AG27<>"",OR($AB27="",$AB27>$AG27)),"STOCK VIEJO EN RIESGO",IF(AND($T27=0,$H27=0),"SIN ROTACION",IF($AB27="","-",IF($AB27<14,"REPONER",IF($AB27>84,"SOBRE-STOCK","EN RANGO")))))))) -> QUIEBRE
A28: IT | B28: WIZE38075 | C28: CALCU-12D-1200V | D28: 1420753775 | 826774371 | E28: Calculadora Global 12 Digitos, Mod. 1200v Metalizada Metalizado | F28: 0 | G28: 10 | H28: 30 | I28: =ROUND($H28/30,2) -> 1 | J28: =IF($Z28="CENSURADO",ROUND($T28/MAX($V28,3),2),ROUND($T28/$G$3,2)) -> 1.41 | K28: =ROUNDUP($J28*$C$3*7,0) -> 30 | L28: =MAX(0,$K28-$F28-$G28) -> 20 | M28: 1799 | N28: 1295 | O28: =$M28+$N28 -> 3094 | P28: =MIN($L28,$O28) -> 20 | Q28: Activa | R28: 1 | S28: Mediano | T28: 45 | U28: 10 | V28: 20 | W28: 2 | X28: 20 | Y28: =IF($X28=0,"",ROUND($H28/$X28,2)) -> 1.5 | Z28: =IF(AND($F28=0,$T28>=5,$W28>=3),"CENSURADO",IF(AND($Y28<>"",$Y28>=3,$T28>=10),"CENSURADO",IF($T28=0,"SIN DATO","CONFIABLE"))) -> CONFIABLE | AA28: =IF($I28=0,"",ROUND($J28/MAX($I28,0.01),2)) -> 1.41 | AB28: =IF($J28<=0,"",ROUND(($F28+$G28)/$J28,0)) -> 7 | AC28: =IF($AB28="","",$J$3+$AB28) -> 46252 | AD28: 0 | AE28: 0 | AF28: 0 | AG28: =IF($AF28=0,"",MAX(0,180-$AE28)) | AH28: 0 | AI28: =IF($AF28=0,"",$AF28*$Q$3-$AF28*$N$3) | AJ28: 2.16 | AK28: =ROUND($F28*$AJ28,0) -> 0 | AL28: =IF(AND($F28=0,$T28>0,$O28=0),"QUIEBRE Y SIN STOCK PARA ENVIAR",IF(AND($F28=0,$T28>0),"QUIEBRE",IF($F28=0,"SIN STOCK SIN DEMANDA",IF(AND($AF28>0,$AG28<>"",OR($AB28="",$AB28>$AG28)),"STOCK VIEJO EN RIESGO",IF(AND($T28=0,$H28=0),"SIN ROTACION",IF($AB28="","-",IF($AB28<14,"REPONER",IF($AB28>84,"SOBRE-STOCK","EN RANGO")))))))) -> QUIEBRE
A29: IT | B29: FZLX96684 | C29: PROJS-ARM-UNIV-430-650MM | D29: 1377104819 | 1611159705 | E29: Soporte Proyector Universal Brazo Extensible De 430 A 650mm Blanco | F29: 0 | G29: 20 | H29: 26 | I29: =ROUND($H29/30,2) -> 0.87 | J29: =IF($Z29="CENSURADO",ROUND($T29/MAX($V29,3),2),ROUND($T29/$G$3,2)) -> 1.45 | K29: =ROUNDUP($J29*$C$3*7,0) -> 31 | L29: =MAX(0,$K29-$F29-$G29) -> 11 | M29: 422 | N29: 18 | O29: =$M29+$N29 -> 440 | P29: =MIN($L29,$O29) -> 11 | Q29: Activa | R29: 1 | S29: Mediano | T29: 42 | U29: 20 | V29: 29 | W29: 1 | X29: 6 | Y29: =IF($X29=0,"",ROUND($H29/$X29,2)) -> 4.33 | Z29: =IF(AND($F29=0,$T29>=5,$W29>=3),"CENSURADO",IF(AND($Y29<>"",$Y29>=3,$T29>=10),"CENSURADO",IF($T29=0,"SIN DATO","CONFIABLE"))) -> CENSURADO | AA29: =IF($I29=0,"",ROUND($J29/MAX($I29,0.01),2)) -> 1.67 | AB29: =IF($J29<=0,"",ROUND(($F29+$G29)/$J29,0)) -> 14 | AC29: =IF($AB29="","",$J$3+$AB29) -> 46259 | AD29: 0 | AE29: 0 | AF29: 0 | AG29: =IF($AF29=0,"",MAX(0,180-$AE29)) | AH29: 0 | AI29: =IF($AF29=0,"",$AF29*$Q$3-$AF29*$N$3) | AJ29: 6.83 | AK29: =ROUND($F29*$AJ29,0) -> 0 | AL29: =IF(AND($F29=0,$T29>0,$O29=0),"QUIEBRE Y SIN STOCK PARA ENVIAR",IF(AND($F29=0,$T29>0),"QUIEBRE",IF($F29=0,"SIN STOCK SIN DEMANDA",IF(AND($AF29>0,$AG29<>"",OR($AB29="",$AB29>$AG29)),"STOCK VIEJO EN RIESGO",IF(AND($T29=0,$H29=0),"SIN ROTACION",IF($AB29="","-",IF($AB29<14,"REPONER",IF($AB29>84,"SOBRE-STOCK","EN RANGO")))))))) -> QUIEBRE
A30: IT | B30: KNPR20887 | C30: TN450COMP | D30: 628912421 | E30: Toner Alternativo Para Brother Tn410 Tn450 Hl 2130 Dcp 7055 | F30: 0 | G30: 0 | H30: 0 | I30: =ROUND($H30/30,2) -> 0 | J30: =IF($Z30="CENSURADO",ROUND($T30/MAX($V30,3),2),ROUND($T30/$G$3,2)) -> 2.16 | K30: =ROUNDUP($J30*$C$3*7,0) -> 46 | L30: =MAX(0,$K30-$F30-$G30) -> 46 | M30: 15 | N30: 0 | O30: =$M30+$N30 -> 15 | P30: =MIN($L30,$O30) -> 15 | Q30: Inactiva | R30: 1 | S30: Mediano | T30: 41 | U30: 11 | V30: 19 | W30: 12 | X30: 0 | Y30: =IF($X30=0,"",ROUND($H30/$X30,2)) | Z30: =IF(AND($F30=0,$T30>=5,$W30>=3),"CENSURADO",IF(AND($Y30<>"",$Y30>=3,$T30>=10),"CENSURADO",IF($T30=0,"SIN DATO","CONFIABLE"))) -> CENSURADO | AA30: =IF($I30=0,"",ROUND($J30/MAX($I30,0.01),2)) | AB30: =IF($J30<=0,"",ROUND(($F30+$G30)/$J30,0)) -> 0 | AC30: =IF($AB30="","",$J$3+$AB30) -> 46245 | AD30: 0 | AE30: 0 | AF30: 0 | AG30: =IF($AF30=0,"",MAX(0,180-$AE30)) | AH30: 0 | AI30: =IF($AF30=0,"",$AF30*$Q$3-$AF30*$N$3) | AJ30: 2.37 | AK30: =ROUND($F30*$AJ30,0) -> 0 | AL30: =IF(AND($F30=0,$T30>0,$O30=0),"QUIEBRE Y SIN STOCK PARA ENVIAR",IF(AND($F30=0,$T30>0),"QUIEBRE",IF($F30=0,"SIN STOCK SIN DEMANDA",IF(AND($AF30>0,$AG30<>"",OR($AB30="",$AB30>$AG30)),"STOCK VIEJO EN RIESGO",IF(AND($T30=0,$H30=0),"SIN ROTACION",IF($AB30="","-",IF($AB30<14,"REPONER",IF($AB30>84,"SOBRE-STOCK","EN RANGO")))))))) -> QUIEBRE
A31: IT | B31: NJLU22691 | C31: TSHIRTGUIDERULE-AIO | D31: 1480466439 | E31: Regla Guía Para Centrar Sublimación De Remeras | F31: 0 | G31: 0 | H31: 38 | I31: =ROUND($H31/30,2) -> 1.27 | J31: =IF($Z31="CENSURADO",ROUND($T31/MAX($V31,3),2),ROUND($T31/$G$3,2)) -> 1.41 | K31: =ROUNDUP($J31*$C$3*7,0) -> 30 | L31: =MAX(0,$K31-$F31-$G31) -> 30 | M31: 1 | N31: -2 | O31: =$M31+$N31 -> -1 | P31: =MIN($L31,$O31) -> -1 | R31: 1 | S31: Mediano | T31: 38 | U31: 19 | V31: 27 | W31: 4 | X31: 18 | Y31: =IF($X31=0,"",ROUND($H31/$X31,2)) -> 2.11 | Z31: =IF(AND($F31=0,$T31>=5,$W31>=3),"CENSURADO",IF(AND($Y31<>"",$Y31>=3,$T31>=10),"CENSURADO",IF($T31=0,"SIN DATO","CONFIABLE"))) -> CENSURADO | AA31: =IF($I31=0,"",ROUND($J31/MAX($I31,0.01),2)) -> 1.11 | AB31: =IF($J31<=0,"",ROUND(($F31+$G31)/$J31,0)) -> 0 | AC31: =IF($AB31="","",$J$3+$AB31) -> 46245 | AD31: 0 | AE31: 0 | AF31: 0 | AG31: =IF($AF31=0,"",MAX(0,180-$AE31)) | AH31: 0 | AI31: =IF($AF31=0,"",$AF31*$Q$3-$AF31*$N$3) | AJ31: 1.67 | AK31: =ROUND($F31*$AJ31,0) -> 0 | AL31: =IF(AND($F31=0,$T31>0,$O31=0),"QUIEBRE Y SIN STOCK PARA ENVIAR",IF(AND($F31=0,$T31>0),"QUIEBRE",IF($F31=0,"SIN STOCK SIN DEMANDA",IF(AND($AF31>0,$AG31<>"",OR($AB31="",$AB31>$AG31)),"STOCK VIEJO EN RIESGO",IF(AND($T31=0,$H31=0),"SIN ROTACION",IF($AB31="","-",IF($AB31<14,"REPONER",IF($AB31>84,"SOBRE-STOCK","EN RANGO")))))))) -> QUIEBRE
A32: IT | B32: UMOI01514 | C32: ESPATULA-UA02S | D32: 1124089712 | E32: Espatula Para Impresión Ua02s | F32: 24 | G32: 0 | H32: 24 | I32: =ROUND($H32/30,2) -> 0.8 | J32: =IF($Z32="CENSURADO",ROUND($T32/MAX($V32,3),2),ROUND($T32/$G$3,2)) -> 1.19 | K32: =ROUNDUP($J32*$C$3*7,0) -> 25 | L32: =MAX(0,$K32-$F32-$G32) -> 1 | M32: 4324 | N32: 219 | O32: =$M32+$N32 -> 4543 | P32: =MIN($L32,$O32) -> 1 | Q32: Activa | R32: 1 | S32: Pequeño | T32: 38 | U32: 18 | V32: 29 | W32: 1 | X32: 40 | Y32: =IF($X32=0,"",ROUND($H32/$X32,2)) -> 0.6 | Z32: =IF(AND($F32=0,$T32>=5,$W32>=3),"CENSURADO",IF(AND($Y32<>"",$Y32>=3,$T32>=10),"CENSURADO",IF($T32=0,"SIN DATO","CONFIABLE"))) -> CONFIABLE | AA32: =IF($I32=0,"",ROUND($J32/MAX($I32,0.01),2)) -> 1.49 | AB32: =IF($J32<=0,"",ROUND(($F32+$G32)/$J32,0)) -> 20 | AC32: =IF($AB32="","",$J$3+$AB32) -> 46265 | AD32: 0 | AE32: 0 | AF32: 0 | AG32: =IF($AF32=0,"",MAX(0,180-$AE32)) | AH32: 0 | AI32: =IF($AF32=0,"",$AF32*$Q$3-$AF32*$N$3) | AJ32: 0.46 | AK32: =ROUND($F32*$AJ32,0) -> 11 | AL32: =IF(AND($F32=0,$T32>0,$O32=0),"QUIEBRE Y SIN STOCK PARA ENVIAR",IF(AND($F32=0,$T32>0),"QUIEBRE",IF($F32=0,"SIN STOCK SIN DEMANDA",IF(AND($AF32>0,$AG32<>"",OR($AB32="",$AB32>$AG32)),"STOCK VIEJO EN RIESGO",IF(AND($T32=0,$H32=0),"SIN ROTACION",IF($AB32="","-",IF($AB32<14,"REPONER",IF($AB32>84,"SOBRE-STOCK","EN RANGO")))))))) -> EN RANGO
A33: IT | B33: CPKK59309 | C33: EPGMR035BLACK | D33: 1130272651 | E33: Auricular Epgmr035 Gaming Con Microfono Stereo Negro Negro | F33: 0 | G33: 0 | H33: 26 | I33: =ROUND($H33/30,2) -> 0.87 | J33: =IF($Z33="CENSURADO",ROUND($T33/MAX($V33,3),2),ROUND($T33/$G$3,2)) -> 1.38 | K33: =ROUNDUP($J33*$C$3*7,0) -> 29 | L33: =MAX(0,$K33-$F33-$G33) -> 29 | M33: 540 | N33: 78 | O33: =$M33+$N33 -> 618 | P33: =MIN($L33,$O33) -> 29 | Q33: Activa | R33: 1 | S33: Pequeño | T33: 36 | U33: 14 | V33: 26 | W33: 5 | X33: 8 | Y33: =IF($X33=0,"",ROUND($H33/$X33,2)) -> 3.25 | Z33: =IF(AND($F33=0,$T33>=5,$W33>=3),"CENSURADO",IF(AND($Y33<>"",$Y33>=3,$T33>=10),"CENSURADO",IF($T33=0,"SIN DATO","CONFIABLE"))) -> CENSURADO | AA33: =IF($I33=0,"",ROUND($J33/MAX($I33,0.01),2)) -> 1.59 | AB33: =IF($J33<=0,"",ROUND(($F33+$G33)/$J33,0)) -> 0 | AC33: =IF($AB33="","",$J$3+$AB33) -> 46245 | AD33: 0 | AE33: 0 | AF33: 0 | AG33: =IF($AF33=0,"",MAX(0,180-$AE33)) | AH33: 0 | AI33: =IF($AF33=0,"",$AF33*$Q$3-$AF33*$N$3) | AJ33: 0 | AK33: =ROUND($F33*$AJ33,0) -> 0 | AL33: =IF(AND($F33=0,$T33>0,$O33=0),"QUIEBRE Y SIN STOCK PARA ENVIAR",IF(AND($F33=0,$T33>0),"QUIEBRE",IF($F33=0,"SIN STOCK SIN DEMANDA",IF(AND($AF33>0,$AG33<>"",OR($AB33="",$AB33>$AG33)),"STOCK VIEJO EN RIESGO",IF(AND($T33=0,$H33=0),"SIN ROTACION",IF($AB33="","-",IF($AB33<14,"REPONER",IF($AB33>84,"SOBRE-STOCK","EN RANGO")))))))) -> QUIEBRE
A34: IT | B34: YNEY91417 | C34: KMG20BKCOMBOWLS | D34: 3415097238 | 674608017 | E34: Kit Teclado + Mouse Inalambrico Wireless Smart Pc Notebook Negro | F34: 0 | G34: 0 | H34: 20 | I34: =ROUND($H34/30,2) -> 0.67 | J34: =IF($Z34="CENSURADO",ROUND($T34/MAX($V34,3),2),ROUND($T34/$G$3,2)) -> 1.09 | K34: =ROUNDUP($J34*$C$3*7,0) -> 23 | L34: =MAX(0,$K34-$F34-$G34) -> 23 | M34: 2756 | N34: 132 | O34: =$M34+$N34 -> 2888 | P34: =MIN($L34,$O34) -> 23 | Q34: Activa | R34: 2 | S34: Grande | T34: 35 | U34: 14 | V34: 27 | W34: 2 | X34: 13 | Y34: =IF($X34=0,"",ROUND($H34/$X34,2)) -> 1.54 | Z34: =IF(AND($F34=0,$T34>=5,$W34>=3),"CENSURADO",IF(AND($Y34<>"",$Y34>=3,$T34>=10),"CENSURADO",IF($T34=0,"SIN DATO","CONFIABLE"))) -> CONFIABLE | AA34: =IF($I34=0,"",ROUND($J34/MAX($I34,0.01),2)) -> 1.63 | AB34: =IF($J34<=0,"",ROUND(($F34+$G34)/$J34,0)) -> 0 | AC34: =IF($AB34="","",$J$3+$AB34) -> 46245 | AD34: 0 | AE34: 0 | AF34: 0 | AG34: =IF($AF34=0,"",MAX(0,180-$AE34)) | AH34: 0 | AI34: =IF($AF34=0,"",$AF34*$Q$3-$AF34*$N$3) | AJ34: 5.52 | AK34: =ROUND($F34*$AJ34,0) -> 0 | AL34: =IF(AND($F34=0,$T34>0,$O34=0),"QUIEBRE Y SIN STOCK PARA ENVIAR",IF(AND($F34=0,$T34>0),"QUIEBRE",IF($F34=0,"SIN STOCK SIN DEMANDA",IF(AND($AF34>0,$AG34<>"",OR($AB34="",$AB34>$AG34)),"STOCK VIEJO EN RIESGO",IF(AND($T34=0,$H34=0),"SIN ROTACION",IF($AB34="","-",IF($AB34<14,"REPONER",IF($AB34>84,"SOBRE-STOCK","EN RANGO")))))))) -> QUIEBRE
A35: IT | B35: NDSR37556 | C35: MLTD104SCOMP | D35: 1432333579 | 615899768 | E35: Toner Alternativo Para Samsung 1665 104s 104 Ml1665 Ml1865 Negro | F35: 28 | G35: 15 | H35: 26 | I35: =ROUND($H35/30,2) -> 0.87 | J35: =IF($Z35="CENSURADO",ROUND($T35/MAX($V35,3),2),ROUND($T35/$G$3,2)) -> 1 | K35: =ROUNDUP($J35*$C$3*7,0) -> 21 | L35: =MAX(0,$K35-$F35-$G35) -> 0 | M35: 6091 | N35: 1209 | O35: =$M35+$N35 -> 7300 | P35: =MIN($L35,$O35) -> 0 | Q35: Activa | R35: 1 | S35: Mediano | T35: 32 | U35: 16 | V35: 29 | W35: 1 | X35: 41 | Y35: =IF($X35=0,"",ROUND($H35/$X35,2)) -> 0.63 | Z35: =IF(AND($F35=0,$T35>=5,$W35>=3),"CENSURADO",IF(AND($Y35<>"",$Y35>=3,$T35>=10),"CENSURADO",IF($T35=0,"SIN DATO","CONFIABLE"))) -> CONFIABLE | AA35: =IF($I35=0,"",ROUND($J35/MAX($I35,0.01),2)) -> 1.15 | AB35: =IF($J35<=0,"",ROUND(($F35+$G35)/$J35,0)) -> 43 | AC35: =IF($AB35="","",$J$3+$AB35) -> 46288 | AD35: 0 | AE35: 0 | AF35: 0 | AG35: =IF($AF35=0,"",MAX(0,180-$AE35)) | AH35: 0 | AI35: =IF($AF35=0,"",$AF35*$Q$3-$AF35*$N$3) | AJ35: 4.48 | AK35: =ROUND($F35*$AJ35,0) -> 125 | AL35: =IF(AND($F35=0,$T35>0,$O35=0),"QUIEBRE Y SIN STOCK PARA ENVIAR",IF(AND($F35=0,$T35>0),"QUIEBRE",IF($F35=0,"SIN STOCK SIN DEMANDA",IF(AND($AF35>0,$AG35<>"",OR($AB35="",$AB35>$AG35)),"STOCK VIEJO EN RIESGO",IF(AND($T35=0,$H35=0),"SIN ROTACION",IF($AB35="","-",IF($AB35<14,"REPONER",IF($AB35>84,"SOBRE-STOCK","EN RANGO")))))))) -> EN RANGO
A36: IT | B36: LGAM05574 | C36: CABLEREDCAT5RJ2MY | D36: 1960865546 | 660810957 | E36: Cable De Red Utp 2 Metros Rj45 Cat 5e Patch Cord Ethernet | F36: 0 | G36: 0 | H36: 5 | I36: =ROUND($H36/30,2) -> 0.17 | J36: =IF($Z36="CENSURADO",ROUND($T36/MAX($V36,3),2),ROUND($T36/$G$3,2)) -> 2.13 | K36: =ROUNDUP($J36*$C$3*7,0) -> 45 | L36: =MAX(0,$K36-$F36-$G36) -> 45 | M36: 3089 | N36: 74 | O36: =$M36+$N36 -> 3163 | P36: =MIN($L36,$O36) -> 45 | Q36: Activa | R36: 1 | S36: Pequeño | T36: 32 | U36: 3 | V36: 15 | W36: 11 | X36: 2 | Y36: =IF($X36=0,"",ROUND($H36/$X36,2)) -> 2.5 | Z36: =IF(AND($F36=0,$T36>=5,$W36>=3),"CENSURADO",IF(AND($Y36<>"",$Y36>=3,$T36>=10),"CENSURADO",IF($T36=0,"SIN DATO","CONFIABLE"))) -> CENSURADO | AA36: =IF($I36=0,"",ROUND($J36/MAX($I36,0.01),2)) -> 12.53 | AB36: =IF($J36<=0,"",ROUND(($F36+$G36)/$J36,0)) -> 0 | AC36: =IF($AB36="","",$J$3+$AB36) -> 46245 | AD36: 0 | AE36: 163 | AF36: 6 | AG36: =IF($AF36=0,"",MAX(0,180-$AE36)) -> 17 | AH36: 2100 | AI36: =IF($AF36=0,"",$AF36*$Q$3-$AF36*$N$3) -> 24090 | AJ36: 0.47 | AK36: =ROUND($F36*$AJ36,0) -> 0 | AL36: =IF(AND($F36=0,$T36>0,$O36=0),"QUIEBRE Y SIN STOCK PARA ENVIAR",IF(AND($F36=0,$T36>0),"QUIEBRE",IF($F36=0,"SIN STOCK SIN DEMANDA",IF(AND($AF36>0,$AG36<>"",OR($AB36="",$AB36>$AG36)),"STOCK VIEJO EN RIESGO",IF(AND($T36=0,$H36=0),"SIN ROTACION",IF($AB36="","-",IF($AB36<14,"REPONER",IF($AB36>84,"SOBRE-STOCK","EN RANGO")))))))) -> QUIEBRE
A37: IT | B37: UCKV77577 | C37: EPGMR029BLACK | D37: 1130780885 | 3274793040 | E37: Auricular Gamer Con Microfono Stereo Epgmr029 Negro Negro | F37: 0 | G37: 0 | H37: 11 | I37: =ROUND($H37/30,2) -> 0.37 | J37: =IF($Z37="CENSURADO",ROUND($T37/MAX($V37,3),2),ROUND($T37/$G$3,2)) -> 1.2 | K37: =ROUNDUP($J37*$C$3*7,0) -> 26 | L37: =MAX(0,$K37-$F37-$G37) -> 26 | M37: 29 | N37: 36 | O37: =$M37+$N37 -> 65 | P37: =MIN($L37,$O37) -> 26 | Q37: Activa | R37: 1 | S37: Pequeño | T37: 30 | U37: 18 | V37: 25 | W37: 7 | X37: 1 | Y37: =IF($X37=0,"",ROUND($H37/$X37,2)) -> 11 | Z37: =IF(AND($F37=0,$T37>=5,$W37>=3),"CENSURADO",IF(AND($Y37<>"",$Y37>=3,$T37>=10),"CENSURADO",IF($T37=0,"SIN DATO","CONFIABLE"))) -> CENSURADO | AA37: =IF($I37=0,"",ROUND($J37/MAX($I37,0.01),2)) -> 3.24 | AB37: =IF($J37<=0,"",ROUND(($F37+$G37)/$J37,0)) -> 0 | AC37: =IF($AB37="","",$J$3+$AB37) -> 46245 | AD37: 0 | AE37: 0 | AF37: 0 | AG37: =IF($AF37=0,"",MAX(0,180-$AE37)) | AH37: 0 | AI37: =IF($AF37=0,"",$AF37*$Q$3-$AF37*$N$3) | AJ37: 0 | AK37: =ROUND($F37*$AJ37,0) -> 0 | AL37: =IF(AND($F37=0,$T37>0,$O37=0),"QUIEBRE Y SIN STOCK PARA ENVIAR",IF(AND($F37=0,$T37>0),"QUIEBRE",IF($F37=0,"SIN STOCK SIN DEMANDA",IF(AND($AF37>0,$AG37<>"",OR($AB37="",$AB37>$AG37)),"STOCK VIEJO EN RIESGO",IF(AND($T37=0,$H37=0),"SIN ROTACION",IF($AB37="","-",IF($AB37<14,"REPONER",IF($AB37>84,"SOBRE-STOCK","EN RANGO")))))))) -> QUIEBRE
A38: IT | B38: FZBZ18741 | C38: FOILHOLOGOLDRAINBOW-G-32X6MT | D38: 1876051914 | 3374717672 | E38: Rollo Foil Holográfico Gold Rainbow Glossy, 32cm X 6m Gold Rainbown | F38: 0 | G38: 0 | H38: 25 | I38: =ROUND($H38/30,2) -> 0.83 | J38: =IF($Z38="CENSURADO",ROUND($T38/MAX($V38,3),2),ROUND($T38/$G$3,2)) -> 1.2 | K38: =ROUNDUP($J38*$C$3*7,0) -> 26 | L38: =MAX(0,$K38-$F38-$G38) -> 26 | M38: 910 | N38: 2134 | O38: =$M38+$N38 -> 3044 | P38: =MIN($L38,$O38) -> 26 | Q38: Activa | R38: 2 | S38: Mediano | T38: 30 | U38: 16 | V38: 25 | W38: 6 | X38: 9 | Y38: =IF($X38=0,"",ROUND($H38/$X38,2)) -> 2.78 | Z38: =IF(AND($F38=0,$T38>=5,$W38>=3),"CENSURADO",IF(AND($Y38<>"",$Y38>=3,$T38>=10),"CENSURADO",IF($T38=0,"SIN DATO","CONFIABLE"))) -> CENSURADO | AA38: =IF($I38=0,"",ROUND($J38/MAX($I38,0.01),2)) -> 1.45 | AB38: =IF($J38<=0,"",ROUND(($F38+$G38)/$J38,0)) -> 0 | AC38: =IF($AB38="","",$J$3+$AB38) -> 46245 | AD38: 0 | AE38: 0 | AF38: 0 | AG38: =IF($AF38=0,"",MAX(0,180-$AE38)) | AH38: 0 | AI38: =IF($AF38=0,"",$AF38*$Q$3-$AF38*$N$3) | AJ38: 0 | AK38: =ROUND($F38*$AJ38,0) -> 0 | AL38: =IF(AND($F38=0,$T38>0,$O38=0),"QUIEBRE Y SIN STOCK PARA ENVIAR",IF(AND($F38=0,$T38>0),"QUIEBRE",IF($F38=0,"SIN STOCK SIN DEMANDA",IF(AND($AF38>0,$AG38<>"",OR($AB38="",$AB38>$AG38)),"STOCK VIEJO EN RIESGO",IF(AND($T38=0,$H38=0),"SIN ROTACION",IF($AB38="","-",IF($AB38<14,"REPONER",IF($AB38>84,"SOBRE-STOCK","EN RANGO")))))))) -> QUIEBRE
A39: IT | B39: GKBT65516 | C39: WEEDINGTOOLS-SETX6 | D39: 3105334186 | E39: Kit De 6 Herramientas Basicas Para Manualidades | F39: 12 | G39: 0 | H39: 22 | I39: =ROUND($H39/30,2) -> 0.73 | J39: =IF($Z39="CENSURADO",ROUND($T39/MAX($V39,3),2),ROUND($T39/$G$3,2)) -> 0.91 | K39: =ROUNDUP($J39*$C$3*7,0) -> 20 | L39: =MAX(0,$K39-$F39-$G39) -> 8 | M39: 18 | N39: 0 | O39: =$M39+$N39 -> 18 | P39: =MIN($L39,$O39) -> 8 | Q39: Activa | R39: 1 | S39: Mediano | T39: 29 | U39: 20 | V39: 29 | W39: 1 | X39: 25 | Y39: =IF($X39=0,"",ROUND($H39/$X39,2)) -> 0.88 | Z39: =IF(AND($F39=0,$T39>=5,$W39>=3),"CENSURADO",IF(AND($Y39<>"",$Y39>=3,$T39>=10),"CENSURADO",IF($T39=0,"SIN DATO","CONFIABLE"))) -> CONFIABLE | AA39: =IF($I39=0,"",ROUND($J39/MAX($I39,0.01),2)) -> 1.25 | AB39: =IF($J39<=0,"",ROUND(($F39+$G39)/$J39,0)) -> 13 | AC39: =IF($AB39="","",$J$3+$AB39) -> 46258 | AD39: 0 | AE39: 0 | AF39: 0 | AG39: =IF($AF39=0,"",MAX(0,180-$AE39)) | AH39: 0 | AI39: =IF($AF39=0,"",$AF39*$Q$3-$AF39*$N$3) | AJ39: 3.82 | AK39: =ROUND($F39*$AJ39,0) -> 46 | AL39: =IF(AND($F39=0,$T39>0,$O39=0),"QUIEBRE Y SIN STOCK PARA ENVIAR",IF(AND($F39=0,$T39>0),"QUIEBRE",IF($F39=0,"SIN STOCK SIN DEMANDA",IF(AND($AF39>0,$AG39<>"",OR($AB39="",$AB39>$AG39)),"STOCK VIEJO EN RIESGO",IF(AND($T39=0,$H39=0),"SIN ROTACION",IF($AB39="","-",IF($AB39<14,"REPONER",IF($AB39>84,"SOBRE-STOCK","EN RANGO")))))))) -> REPONER
A40: IT | B40: TBOR79704 | C40: CE278ACOMP | D40: 614120423 | E40: Toner Alternativo Para Ce278a 78a 278 P1606 P1606dn P1566 Negro | F40: 0 | G40: 0 | H40: 30 | I40: =ROUND($H40/30,2) -> 1 | J40: =IF($Z40="CENSURADO",ROUND($T40/MAX($V40,3),2),ROUND($T40/$G$3,2)) -> 2.55 | K40: =ROUNDUP($J40*$C$3*7,0) -> 54 | L40: =MAX(0,$K40-$F40-$G40) -> 54 | M40: 42 | N40: 0 | O40: =$M40+$N40 -> 42 | P40: =MIN($L40,$O40) -> 42 | R40: 1 | S40: Mediano | T40: 28 | U40: 7 | V40: 11 | W40: 18 | X40: 6 | Y40: =IF($X40=0,"",ROUND($H40/$X40,2)) -> 5 | Z40: =IF(AND($F40=0,$T40>=5,$W40>=3),"CENSURADO",IF(AND($Y40<>"",$Y40>=3,$T40>=10),"CENSURADO",IF($T40=0,"SIN DATO","CONFIABLE"))) -> CENSURADO | AA40: =IF($I40=0,"",ROUND($J40/MAX($I40,0.01),2)) -> 2.55 | AB40: =IF($J40<=0,"",ROUND(($F40+$G40)/$J40,0)) -> 0 | AC40: =IF($AB40="","",$J$3+$AB40) -> 46245 | AD40: 0 | AE40: 0 | AF40: 0 | AG40: =IF($AF40=0,"",MAX(0,180-$AE40)) | AH40: 0 | AI40: =IF($AF40=0,"",$AF40*$Q$3-$AF40*$N$3) | AJ40: 2.69 | AK40: =ROUND($F40*$AJ40,0) -> 0 | AL40: =IF(AND($F40=0,$T40>0,$O40=0),"QUIEBRE Y SIN STOCK PARA ENVIAR",IF(AND($F40=0,$T40>0),"QUIEBRE",IF($F40=0,"SIN STOCK SIN DEMANDA",IF(AND($AF40>0,$AG40<>"",OR($AB40="",$AB40>$AG40)),"STOCK VIEJO EN RIESGO",IF(AND($T40=0,$H40=0),"SIN ROTACION",IF($AB40="","-",IF($AB40<14,"REPONER",IF($AB40>84,"SOBRE-STOCK","EN RANGO")))))))) -> QUIEBRE
A41: IT | B41: HSXJ89262 | C41: K227BKMEDIAUSB | D41: 1377072473 | E41: Teclado Global K227 Multimedia Con Cable Usb Negro Negro Español De Latinoaméric | F41: 0 | G41: 20 | H41: 2 | I41: =ROUND($H41/30,2) -> 0.07 | J41: =IF($Z41="CENSURADO",ROUND($T41/MAX($V41,3),2),ROUND($T41/$G$3,2)) -> 1.17 | K41: =ROUNDUP($J41*$C$3*7,0) -> 25 | L41: =MAX(0,$K41-$F41-$G41) -> 5 | M41: 13623 | N41: 63 | O41: =$M41+$N41 -> 13686 | P41: =MIN($L41,$O41) -> 5 | Q41: Activa | R41: 2 | S41: Mediano | T41: 28 | U41: 6 | V41: 24 | W41: 7 | X41: 0 | Y41: =IF($X41=0,"",ROUND($H41/$X41,2)) | Z41: =IF(AND($F41=0,$T41>=5,$W41>=3),"CENSURADO",IF(AND($Y41<>"",$Y41>=3,$T41>=10),"CENSURADO",IF($T41=0,"SIN DATO","CONFIABLE"))) -> CENSURADO | AA41: =IF($I41=0,"",ROUND($J41/MAX($I41,0.01),2)) -> 16.71 | AB41: =IF($J41<=0,"",ROUND(($F41+$G41)/$J41,0)) -> 17 | AC41: =IF($AB41="","",$J$3+$AB41) -> 46262 | AD41: 0 | AE41: 166 | AF41: 7 | AG41: =IF($AF41=0,"",MAX(0,180-$AE41)) -> 14 | AH41: 3290 | AI41: =IF($AF41=0,"",$AF41*$Q$3-$AF41*$N$3) -> 28105 | AJ41: 2.34 | AK41: =ROUND($F41*$AJ41,0) -> 0 | AL41: =IF(AND($F41=0,$T41>0,$O41=0),"QUIEBRE Y SIN STOCK PARA ENVIAR",IF(AND($F41=0,$T41>0),"QUIEBRE",IF($F41=0,"SIN STOCK SIN DEMANDA",IF(AND($AF41>0,$AG41<>"",OR($AB41="",$AB41>$AG41)),"STOCK VIEJO EN RIESGO",IF(AND($T41=0,$H41=0),"SIN ROTACION",IF($AB41="","-",IF($AB41<14,"REPONER",IF($AB41>84,"SOBRE-STOCK","EN RANGO")))))))) -> QUIEBRE
A42: IT | B42: OCPL64984 | C42: LAM-POUCH-G-90X130MM-150MIC | D42: 1424824337 | 698469191 | E42: Pouch Para Plastificar 90x130mm X 150micr X 100 Unidades | F42: 0 | G42: 0 | H42: 24 | I42: =ROUND($H42/30,2) -> 0.8 | J42: =IF($Z42="CENSURADO",ROUND($T42/MAX($V42,3),2),ROUND($T42/$G$3,2)) -> 1.42 | K42: =ROUNDUP($J42*$C$3*7,0) -> 30 | L42: =MAX(0,$K42-$F42-$G42) -> 30 | M42: 0 | N42: 0 | O42: =$M42+$N42 -> 0 | P42: =MIN($L42,$O42) -> 0 | R42: 1 | S42: Pequeño | T42: 27 | U42: 11 | V42: 19 | W42: 13 | X42: 9 | Y42: =IF($X42=0,"",ROUND($H42/$X42,2)) -> 2.67 | Z42: =IF(AND($F42=0,$T42>=5,$W42>=3),"CENSURADO",IF(AND($Y42<>"",$Y42>=3,$T42>=10),"CENSURADO",IF($T42=0,"SIN DATO","CONFIABLE"))) -> CENSURADO | AA42: =IF($I42=0,"",ROUND($J42/MAX($I42,0.01),2)) -> 1.78 | AB42: =IF($J42<=0,"",ROUND(($F42+$G42)/$J42,0)) -> 0 | AC42: =IF($AB42="","",$J$3+$AB42) -> 46245 | AD42: 0 | AE42: 0 | AF42: 0 | AG42: =IF($AF42=0,"",MAX(0,180-$AE42)) | AH42: 0 | AI42: =IF($AF42=0,"",$AF42*$Q$3-$AF42*$N$3) | AJ42: 0.89 | AK42: =ROUND($F42*$AJ42,0) -> 0 | AL42: =IF(AND($F42=0,$T42>0,$O42=0),"QUIEBRE Y SIN STOCK PARA ENVIAR",IF(AND($F42=0,$T42>0),"QUIEBRE",IF($F42=0,"SIN STOCK SIN DEMANDA",IF(AND($AF42>0,$AG42<>"",OR($AB42="",$AB42>$AG42)),"STOCK VIEJO EN RIESGO",IF(AND($T42=0,$H42=0),"SIN ROTACION",IF($AB42="","-",IF($AB42<14,"REPONER",IF($AB42>84,"SOBRE-STOCK","EN RANGO")))))))) -> QUIEBRE Y SIN STOCK PARA ENVIAR
A43: IT | B43: XYUM78058 | C43: FOILSILVER-M-32X6MT | D43: 1441862783 | 2428489418 | E43: Rollo Foil Plata Metalizado Mate 32cm X 6mts Textil Sublimar Plata Metalizado | F43: 0 | G43: 0 | H43: 10 | I43: =ROUND($H43/30,2) -> 0.33 | J43: =IF($Z43="CENSURADO",ROUND($T43/MAX($V43,3),2),ROUND($T43/$G$3,2)) -> 0.96 | K43: =ROUNDUP($J43*$C$3*7,0) -> 21 | L43: =MAX(0,$K43-$F43-$G43) -> 21 | M43: 703 | N43: 124 | O43: =$M43+$N43 -> 827 | P43: =MIN($L43,$O43) -> 21 | Q43: Activa | R43: 2 | S43: Mediano | T43: 27 | U43: 17 | V43: 28 | W43: 3 | X43: 3 | Y43: =IF($X43=0,"",ROUND($H43/$X43,2)) -> 3.33 | Z43: =IF(AND($F43=0,$T43>=5,$W43>=3),"CENSURADO",IF(AND($Y43<>"",$Y43>=3,$T43>=10),"CENSURADO",IF($T43=0,"SIN DATO","CONFIABLE"))) -> CENSURADO | AA43: =IF($I43=0,"",ROUND($J43/MAX($I43,0.01),2)) -> 2.91 | AB43: =IF($J43<=0,"",ROUND(($F43+$G43)/$J43,0)) -> 0 | AC43: =IF($AB43="","",$J$3+$AB43) -> 46245 | AD43: 0 | AE43: 0 | AF43: 0 | AG43: =IF($AF43=0,"",MAX(0,180-$AE43)) | AH43: 0 | AI43: =IF($AF43=0,"",$AF43*$Q$3-$AF43*$N$3) | AJ43: 1.28 | AK43: =ROUND($F43*$AJ43,0) -> 0 | AL43: =IF(AND($F43=0,$T43>0,$O43=0),"QUIEBRE Y SIN STOCK PARA ENVIAR",IF(AND($F43=0,$T43>0),"QUIEBRE",IF($F43=0,"SIN STOCK SIN DEMANDA",IF(AND($AF43>0,$AG43<>"",OR($AB43="",$AB43>$AG43)),"STOCK VIEJO EN RIESGO",IF(AND($T43=0,$H43=0),"SIN ROTACION",IF($AB43="","-",IF($AB43<14,"REPONER",IF($AB43>84,"SOBRE-STOCK","EN RANGO")))))))) -> QUIEBRE
A44: IT | B44: HIZC37560 | C44: CF217ACOMPNOCHIP | D44: 674519456 | E44: Toner Alternativo 217a 17a Cf217a M102w M130fw M130f S/ Chip Negro | F44: 0 | G44: 10 | H44: 23 | I44: =ROUND($H44/30,2) -> 0.77 | J44: =IF($Z44="CENSURADO",ROUND($T44/MAX($V44,3),2),ROUND($T44/$G$3,2)) -> 1 | K44: =ROUNDUP($J44*$C$3*7,0) -> 21 | L44: =MAX(0,$K44-$F44-$G44) -> 11 | M44: 211 | N44: 14 | O44: =$M44+$N44 -> 225 | P44: =MIN($L44,$O44) -> 11 | Q44: Activa | R44: 1 | S44: Mediano | T44: 26 | U44: 9 | V44: 26 | W44: 3 | X44: 11 | Y44: =IF($X44=0,"",ROUND($H44/$X44,2)) -> 2.09 | Z44: =IF(AND($F44=0,$T44>=5,$W44>=3),"CENSURADO",IF(AND($Y44<>"",$Y44>=3,$T44>=10),"CENSURADO",IF($T44=0,"SIN DATO","CONFIABLE"))) -> CENSURADO | AA44: =IF($I44=0,"",ROUND($J44/MAX($I44,0.01),2)) -> 1.3 | AB44: =IF($J44<=0,"",ROUND(($F44+$G44)/$J44,0)) -> 10 | AC44: =IF($AB44="","",$J$3+$AB44) -> 46255 | AD44: 0 | AE44: 0 | AF44: 0 | AG44: =IF($AF44=0,"",MAX(0,180-$AE44)) | AH44: 0 | AI44: =IF($AF44=0,"",$AF44*$Q$3-$AF44*$N$3) | AJ44: 1.84 | AK44: =ROUND($F44*$AJ44,0) -> 0 | AL44: =IF(AND($F44=0,$T44>0,$O44=0),"QUIEBRE Y SIN STOCK PARA ENVIAR",IF(AND($F44=0,$T44>0),"QUIEBRE",IF($F44=0,"SIN STOCK SIN DEMANDA",IF(AND($AF44>0,$AG44<>"",OR($AB44="",$AB44>$AG44)),"STOCK VIEJO EN RIESGO",IF(AND($T44=0,$H44=0),"SIN ROTACION",IF($AB44="","-",IF($AB44<14,"REPONER",IF($AB44>84,"SOBRE-STOCK","EN RANGO")))))))) -> QUIEBRE
A45: IT | B45: RRCW75470 | C45: PLANCHA-SUB-GORRA-PORT | D45: 1737714493 | E45: Plancha Portátil Para Gorras 3 Niveles De Temperatura Blanco | F45: 6 | G45: 20 | H45: 7 | I45: =ROUND($H45/30,2) -> 0.23 | J45: =IF($Z45="CENSURADO",ROUND($T45/MAX($V45,3),2),ROUND($T45/$G$3,2)) -> 0.75 | K45: =ROUNDUP($J45*$C$3*7,0) -> 16 | L45: =MAX(0,$K45-$F45-$G45) -> 0 | M45: 410 | N45: 342 | O45: =$M45+$N45 -> 752 | P45: =MIN($L45,$O45) -> 0 | Q45: Activa | R45: 1 | S45: Mediano | T45: 24 | U45: 18 | V45: 30 | W45: 0 | X45: 10 | Y45: =IF($X45=0,"",ROUND($H45/$X45,2)) -> 0.7 | Z45: =IF(AND($F45=0,$T45>=5,$W45>=3),"CENSURADO",IF(AND($Y45<>"",$Y45>=3,$T45>=10),"CENSURADO",IF($T45=0,"SIN DATO","CONFIABLE"))) -> CONFIABLE | AA45: =IF($I45=0,"",ROUND($J45/MAX($I45,0.01),2)) -> 3.26 | AB45: =IF($J45<=0,"",ROUND(($F45+$G45)/$J45,0)) -> 35 | AC45: =IF($AB45="","",$J$3+$AB45) -> 46280 | AD45: 0 | AE45: 0 | AF45: 0 | AG45: =IF($AF45=0,"",MAX(0,180-$AE45)) | AH45: 0 | AI45: =IF($AF45=0,"",$AF45*$Q$3-$AF45*$N$3) | AJ45: 24.83 | AK45: =ROUND($F45*$AJ45,0) -> 149 | AL45: =IF(AND($F45=0,$T45>0,$O45=0),"QUIEBRE Y SIN STOCK PARA ENVIAR",IF(AND($F45=0,$T45>0),"QUIEBRE",IF($F45=0,"SIN STOCK SIN DEMANDA",IF(AND($AF45>0,$AG45<>"",OR($AB45="",$AB45>$AG45)),"STOCK VIEJO EN RIESGO",IF(AND($T45=0,$H45=0),"SIN ROTACION",IF($AB45="","-",IF($AB45<14,"REPONER",IF($AB45>84,"SOBRE-STOCK","EN RANGO")))))))) -> EN RANGO
A46: IT | B46: GJVP01454 | C46: TVS-FIX-26-63I-400X400 | D46: 899100645 | E46: Soporte De Tv Lcd Plasma Fijo 45kg De 26 A 63 400x400 Negro | F46: 6 | G46: 0 | H46: 0 | I46: =ROUND($H46/30,2) -> 0 | J46: =IF($Z46="CENSURADO",ROUND($T46/MAX($V46,3),2),ROUND($T46/$G$3,2)) -> 0.72 | K46: =ROUNDUP($J46*$C$3*7,0) -> 16 | L46: =MAX(0,$K46-$F46-$G46) -> 10 | M46: 36 | N46: 1090 | O46: =$M46+$N46 -> 1126 | P46: =MIN($L46,$O46) -> 10 | Q46: Activa | R46: 1 | S46: Mediano | T46: 23 | U46: 4 | V46: 7 | W46: 4 | X46: 6 | Y46: =IF($X46=0,"",ROUND($H46/$X46,2)) -> 0 | Z46: =IF(AND($F46=0,$T46>=5,$W46>=3),"CENSURADO",IF(AND($Y46<>"",$Y46>=3,$T46>=10),"CENSURADO",IF($T46=0,"SIN DATO","CONFIABLE"))) -> CONFIABLE | AA46: =IF($I46=0,"",ROUND($J46/MAX($I46,0.01),2)) | AB46: =IF($J46<=0,"",ROUND(($F46+$G46)/$J46,0)) -> 8 | AC46: =IF($AB46="","",$J$3+$AB46) -> 46253 | AD46: 0 | AE46: 215 | AF46: 0 | AG46: =IF($AF46=0,"",MAX(0,180-$AE46)) | AH46: 4485 | AI46: =IF($AF46=0,"",$AF46*$Q$3-$AF46*$N$3) | AJ46: 1.41 | AK46: =ROUND($F46*$AJ46,0) -> 8 | AL46: =IF(AND($F46=0,$T46>0,$O46=0),"QUIEBRE Y SIN STOCK PARA ENVIAR",IF(AND($F46=0,$T46>0),"QUIEBRE",IF($F46=0,"SIN STOCK SIN DEMANDA",IF(AND($AF46>0,$AG46<>"",OR($AB46="",$AB46>$AG46)),"STOCK VIEJO EN RIESGO",IF(AND($T46=0,$H46=0),"SIN ROTACION",IF($AB46="","-",IF($AB46<14,"REPONER",IF($AB46>84,"SOBRE-STOCK","EN RANGO")))))))) -> REPONER
A47: IT | B47: WLJX80862 | C47: X2 MLTD101SCOMP | D47: 1613067829 | E47: Pack Tóner Alternativo Global Electronics Mlt-d101s Negro Para Samsung Ml-2165w | F47: 0 | G47: 0 | H47: 0 | I47: =ROUND($H47/30,2) -> 0 | J47: =IF($Z47="CENSURADO",ROUND($T47/MAX($V47,3),2),ROUND($T47/$G$3,2)) -> 0.69 | K47: =ROUNDUP($J47*$C$3*7,0) -> 15 | L47: =MAX(0,$K47-$F47-$G47) -> 15 | M47: 0 | N47: 0 | O47: =$M47+$N47 -> 0 | P47: =MIN($L47,$O47) -> 0 | Q47: Activa | R47: 1 | S47: Mediano | T47: 22 | U47: 11 | V47: 31 | W47: 1 | X47: 0 | Y47: =IF($X47=0,"",ROUND($H47/$X47,2)) | Z47: =IF(AND($F47=0,$T47>=5,$W47>=3),"CENSURADO",IF(AND($Y47<>"",$Y47>=3,$T47>=10),"CENSURADO",IF($T47=0,"SIN DATO","CONFIABLE"))) -> CONFIABLE | AA47: =IF($I47=0,"",ROUND($J47/MAX($I47,0.01),2)) | AB47: =IF($J47<=0,"",ROUND(($F47+$G47)/$J47,0)) -> 0 | AC47: =IF($AB47="","",$J$3+$AB47) -> 46245 | AD47: 0 | AE47: 0 | AF47: 0 | AG47: =IF($AF47=0,"",MAX(0,180-$AE47)) | AH47: 0 | AI47: =IF($AF47=0,"",$AF47*$Q$3-$AF47*$N$3) | AJ47: 0 | AK47: =ROUND($F47*$AJ47,0) -> 0 | AL47: =IF(AND($F47=0,$T47>0,$O47=0),"QUIEBRE Y SIN STOCK PARA ENVIAR",IF(AND($F47=0,$T47>0),"QUIEBRE",IF($F47=0,"SIN STOCK SIN DEMANDA",IF(AND($AF47>0,$AG47<>"",OR($AB47="",$AB47>$AG47)),"STOCK VIEJO EN RIESGO",IF(AND($T47=0,$H47=0),"SIN ROTACION",IF($AB47="","-",IF($AB47<14,"REPONER",IF($AB47>84,"SOBRE-STOCK","EN RANGO")))))))) -> QUIEBRE Y SIN STOCK PARA ENVIAR
A48: IT | B48: VJLP05831 | C48: 407578COMP | D48: 659978583 | E48: Tóner Global Electronics Laserjet Sp 310 Dn 6400 Negro | F48: 4 | G48: 0 | H48: 1 | I48: =ROUND($H48/30,2) -> 0.03 | J48: =IF($Z48="CENSURADO",ROUND($T48/MAX($V48,3),2),ROUND($T48/$G$3,2)) -> 0.69 | K48: =ROUNDUP($J48*$C$3*7,0) -> 15 | L48: =MAX(0,$K48-$F48-$G48) -> 11 | M48: 88 | N48: 65 | O48: =$M48+$N48 -> 153 | P48: =MIN($L48,$O48) -> 11 | Q48: Activa | R48: 1 | S48: Mediano | T48: 22 | U48: 10 | V48: 24 | W48: 7 | X48: 5 | Y48: =IF($X48=0,"",ROUND($H48/$X48,2)) -> 0.2 | Z48: =IF(AND($F48=0,$T48>=5,$W48>=3),"CENSURADO",IF(AND($Y48<>"",$Y48>=3,$T48>=10),"CENSURADO",IF($T48=0,"SIN DATO","CONFIABLE"))) -> CONFIABLE | AA48: =IF($I48=0,"",ROUND($J48/MAX($I48,0.01),2)) -> 23 | AB48: =IF($J48<=0,"",ROUND(($F48+$G48)/$J48,0)) -> 6 | AC48: =IF($AB48="","",$J$3+$AB48) -> 46251 | AD48: 0 | AE48: 275 | AF48: 2 | AG48: =IF($AF48=0,"",MAX(0,180-$AE48)) -> 0 | AH48: 14395 | AI48: =IF($AF48=0,"",$AF48*$Q$3-$AF48*$N$3) -> 8030 | AJ48: 6.53 | AK48: =ROUND($F48*$AJ48,0) -> 26 | AL48: =IF(AND($F48=0,$T48>0,$O48=0),"QUIEBRE Y SIN STOCK PARA ENVIAR",IF(AND($F48=0,$T48>0),"QUIEBRE",IF($F48=0,"SIN STOCK SIN DEMANDA",IF(AND($AF48>0,$AG48<>"",OR($AB48="",$AB48>$AG48)),"STOCK VIEJO EN RIESGO",IF(AND($T48=0,$H48=0),"SIN ROTACION",IF($AB48="","-",IF($AB48<14,"REPONER",IF($AB48>84,"SOBRE-STOCK","EN RANGO")))))))) -> STOCK VIEJO EN RIESGO
A49: IT | B49: QKRV04417 | C49: K103BKUSB | D49: 905992334 | E49: Teclado Global Electronics Cable Usb K103bkusb Qwerty Español Para Oficina Negro | F49: 0 | G49: 15 | H49: 14 | I49: =ROUND($H49/30,2) -> 0.47 | J49: =IF($Z49="CENSURADO",ROUND($T49/MAX($V49,3),2),ROUND($T49/$G$3,2)) -> 0.91 | K49: =ROUNDUP($J49*$C$3*7,0) -> 20 | L49: =MAX(0,$K49-$F49-$G49) -> 5 | M49: 8164 | N49: 157 | O49: =$M49+$N49 -> 8321 | P49: =MIN($L49,$O49) -> 5 | Q49: Activa | R49: 1 | S49: Mediano | T49: 21 | U49: 6 | V49: 23 | W49: 7 | X49: 3 | Y49: =IF($X49=0,"",ROUND($H49/$X49,2)) -> 4.67 | Z49: =IF(AND($F49=0,$T49>=5,$W49>=3),"CENSURADO",IF(AND($Y49<>"",$Y49>=3,$T49>=10),"CENSURADO",IF($T49=0,"SIN DATO","CONFIABLE"))) -> CENSURADO | AA49: =IF($I49=0,"",ROUND($J49/MAX($I49,0.01),2)) -> 1.94 | AB49: =IF($J49<=0,"",ROUND(($F49+$G49)/$J49,0)) -> 16 | AC49: =IF($AB49="","",$J$3+$AB49) -> 46261 | AD49: 0 | AE49: 0 | AF49: 0 | AG49: =IF($AF49=0,"",MAX(0,180-$AE49)) | AH49: 0 | AI49: =IF($AF49=0,"",$AF49*$Q$3-$AF49*$N$3) | AJ49: 2.97 | AK49: =ROUND($F49*$AJ49,0) -> 0 | AL49: =IF(AND($F49=0,$T49>0,$O49=0),"QUIEBRE Y SIN STOCK PARA ENVIAR",IF(AND($F49=0,$T49>0),"QUIEBRE",IF($F49=0,"SIN STOCK SIN DEMANDA",IF(AND($AF49>0,$AG49<>"",OR($AB49="",$AB49>$AG49)),"STOCK VIEJO EN RIESGO",IF(AND($T49=0,$H49=0),"SIN ROTACION",IF($AB49="","-",IF($AB49<14,"REPONER",IF($AB49>84,"SOBRE-STOCK","EN RANGO")))))))) -> QUIEBRE
A50: IT | B50: NGFW33158 | C50: PLANCHA-SUB-AUTO-TERMO | D50: 1651532633 | E50: Plancha Sublimadora Estampadora Automatica De Termos Blanco | F50: 5 | G50: 0 | H50: 9 | I50: =ROUND($H50/30,2) -> 0.3 | J50: =IF($Z50="CENSURADO",ROUND($T50/MAX($V50,3),2),ROUND($T50/$G$3,2)) -> 0.66 | K50: =ROUNDUP($J50*$C$3*7,0) -> 14 | L50: =MAX(0,$K50-$F50-$G50) -> 9 | M50: 0 | N50: 0 | O50: =$M50+$N50 -> 0 | P50: =MIN($L50,$O50) -> 0 | Q50: Activa | R50: 1 | S50: Mediano | T50: 21 | U50: 15 | V50: 27 | W50: 4 | X50: 11 | Y50: =IF($X50=0,"",ROUND($H50/$X50,2)) -> 0.82 | Z50: =IF(AND($F50=0,$T50>=5,$W50>=3),"CENSURADO",IF(AND($Y50<>"",$Y50>=3,$T50>=10),"CENSURADO",IF($T50=0,"SIN DATO","CONFIABLE"))) -> CONFIABLE | AA50: =IF($I50=0,"",ROUND($J50/MAX($I50,0.01),2)) -> 2.2 | AB50: =IF($J50<=0,"",ROUND(($F50+$G50)/$J50,0)) -> 8 | AC50: =IF($AB50="","",$J$3+$AB50) -> 46253 | AD50: 0 | AE50: 0 | AF50: 0 | AG50: =IF($AF50=0,"",MAX(0,180-$AE50)) | AH50: 0 | AI50: =IF($AF50=0,"",$AF50*$Q$3-$AF50*$N$3) | AJ50: 74.26 | AK50: =ROUND($F50*$AJ50,0) -> 371 | AL50: =IF(AND($F50=0,$T50>0,$O50=0),"QUIEBRE Y SIN STOCK PARA ENVIAR",IF(AND($F50=0,$T50>0),"QUIEBRE",IF($F50=0,"SIN STOCK SIN DEMANDA",IF(AND($AF50>0,$AG50<>"",OR($AB50="",$AB50>$AG50)),"STOCK VIEJO EN RIESGO",IF(AND($T50=0,$H50=0),"SIN ROTACION",IF($AB50="","-",IF($AB50<14,"REPONER",IF($AB50>84,"SOBRE-STOCK","EN RANGO")))))))) -> REPONER
A51: IT | B51: PNJF09873 | C51: AURI-EP033BK | D51: 1723436608 | E51: Auriculares Con Cable Plug Fino Jack 3.5mm Stereo Color Negro | F51: 0 | G51: 0 | H51: 0 | I51: =ROUND($H51/30,2) -> 0 | J51: =IF($Z51="CENSURADO",ROUND($T51/MAX($V51,3),2),ROUND($T51/$G$3,2)) -> 0.94 | K51: =ROUNDUP($J51*$C$3*7,0) -> 20 | L51: =MAX(0,$K51-$F51-$G51) -> 20 | M51: 0 | N51: 0 | O51: =$M51+$N51 -> 0 | P51: =MIN($L51,$O51) -> 0 | Q51: Activa | R51: 1 | S51: Pequeño | T51: 16 | U51: 6 | V51: 17 | W51: 9 | X51: 0 | Y51: =IF($X51=0,"",ROUND($H51/$X51,2)) | Z51: =IF(AND($F51=0,$T51>=5,$W51>=3),"CENSURADO",IF(AND($Y51<>"",$Y51>=3,$T51>=10),"CENSURADO",IF($T51=0,"SIN DATO","CONFIABLE"))) -> CENSURADO | AA51: =IF($I51=0,"",ROUND($J51/MAX($I51,0.01),2)) | AB51: =IF($J51<=0,"",ROUND(($F51+$G51)/$J51,0)) -> 0 | AC51: =IF($AB51="","",$J$3+$AB51) -> 46245 | AD51: 0 | AE51: 0 | AF51: 0 | AG51: =IF($AF51=0,"",MAX(0,180-$AE51)) | AH51: 0 | AI51: =IF($AF51=0,"",$AF51*$Q$3-$AF51*$N$3) | AJ51: 0 | AK51: =ROUND($F51*$AJ51,0) -> 0 | AL51: =IF(AND($F51=0,$T51>0,$O51=0),"QUIEBRE Y SIN STOCK PARA ENVIAR",IF(AND($F51=0,$T51>0),"QUIEBRE",IF($F51=0,"SIN STOCK SIN DEMANDA",IF(AND($AF51>0,$AG51<>"",OR($AB51="",$AB51>$AG51)),"STOCK VIEJO EN RIESGO",IF(AND($T51=0,$H51=0),"SIN ROTACION",IF($AB51="","-",IF($AB51<14,"REPONER",IF($AB51>84,"SOBRE-STOCK","EN RANGO")))))))) -> QUIEBRE Y SIN STOCK PARA ENVIAR
A52: IT | B52: UTRJ91752 | C52: K601BKCOMBOWLS | D52: 1404033050 | 2797089614 | E52: Combo Teclado Y Mouse Unificado Inalámbrico 2.4ghz A Pilas Negro | F52: 7 | G52: 10 | H52: 13 | I52: =ROUND($H52/30,2) -> 0.43 | J52: =IF($Z52="CENSURADO",ROUND($T52/MAX($V52,3),2),ROUND($T52/$G$3,2)) -> 0.5 | K52: =ROUNDUP($J52*$C$3*7,0) -> 11 | L52: =MAX(0,$K52-$F52-$G52) -> 0 | M52: 1486 | N52: 157 | O52: =$M52+$N52 -> 1643 | P52: =MIN($L52,$O52) -> 0 | Q52: Activa | R52: 1 | S52: Mediano | T52: 16 | U52: 8 | V52: 22 | W52: 8 | X52: 12 | Y52: =IF($X52=0,"",ROUND($H52/$X52,2)) -> 1.08 | Z52: =IF(AND($F52=0,$T52>=5,$W52>=3),"CENSURADO",IF(AND($Y52<>"",$Y52>=3,$T52>=10),"CENSURADO",IF($T52=0,"SIN DATO","CONFIABLE"))) -> CONFIABLE | AA52: =IF($I52=0,"",ROUND($J52/MAX($I52,0.01),2)) -> 1.16 | AB52: =IF($J52<=0,"",ROUND(($F52+$G52)/$J52,0)) -> 34 | AC52: =IF($AB52="","",$J$3+$AB52) -> 46279 | AD52: 0 | AE52: 0 | AF52: 0 | AG52: =IF($AF52=0,"",MAX(0,180-$AE52)) | AH52: 0 | AI52: =IF($AF52=0,"",$AF52*$Q$3-$AF52*$N$3) | AJ52: 14.53 | AK52: =ROUND($F52*$AJ52,0) -> 102 | AL52: =IF(AND($F52=0,$T52>0,$O52=0),"QUIEBRE Y SIN STOCK PARA ENVIAR",IF(AND($F52=0,$T52>0),"QUIEBRE",IF($F52=0,"SIN STOCK SIN DEMANDA",IF(AND($AF52>0,$AG52<>"",OR($AB52="",$AB52>$AG52)),"STOCK VIEJO EN RIESGO",IF(AND($T52=0,$H52=0),"SIN ROTACION",IF($AB52="","-",IF($AB52<14,"REPONER",IF($AB52>84,"SOBRE-STOCK","EN RANGO")))))))) -> EN RANGO
A53: IT | B53: UIQJ99040 | C53: PAPERM110A4-100 | D53: 1142476023 | E53: Papel Fotográfico Sublimación Global A4 110g 100 Hojas Blanco | F53: 0 | G53: 0 | H53: 5 | I53: =ROUND($H53/30,2) -> 0.17 | J53: =IF($Z53="CENSURADO",ROUND($T53/MAX($V53,3),2),ROUND($T53/$G$3,2)) -> 0.54 | K53: =ROUNDUP($J53*$C$3*7,0) -> 12 | L53: =MAX(0,$K53-$F53-$G53) -> 12 | M53: 16248 | N53: 1525 | O53: =$M53+$N53 -> 17773 | P53: =MIN($L53,$O53) -> 12 | Q53: Activa | R53: 3 | S53: Mediano | T53: 14 | U53: 7 | V53: 26 | W53: 3 | X53: 1 | Y53: =IF($X53=0,"",ROUND($H53/$X53,2)) -> 5 | Z53: =IF(AND($F53=0,$T53>=5,$W53>=3),"CENSURADO",IF(AND($Y53<>"",$Y53>=3,$T53>=10),"CENSURADO",IF($T53=0,"SIN DATO","CONFIABLE"))) -> CENSURADO | AA53: =IF($I53=0,"",ROUND($J53/MAX($I53,0.01),2)) -> 3.18 | AB53: =IF($J53<=0,"",ROUND(($F53+$G53)/$J53,0)) -> 0 | AC53: =IF($AB53="","",$J$3+$AB53) -> 46245 | AD53: 0 | AE53: 0 | AF53: 0 | AG53: =IF($AF53=0,"",MAX(0,180-$AE53)) | AH53: 0 | AI53: =IF($AF53=0,"",$AF53*$Q$3-$AF53*$N$3) | AJ53: 2.09 | AK53: =ROUND($F53*$AJ53,0) -> 0 | AL53: =IF(AND($F53=0,$T53>0,$O53=0),"QUIEBRE Y SIN STOCK PARA ENVIAR",IF(AND($F53=0,$T53>0),"QUIEBRE",IF($F53=0,"SIN STOCK SIN DEMANDA",IF(AND($AF53>0,$AG53<>"",OR($AB53="",$AB53>$AG53)),"STOCK VIEJO EN RIESGO",IF(AND($T53=0,$H53=0),"SIN ROTACION",IF($AB53="","-",IF($AB53<14,"REPONER",IF($AB53>84,"SOBRE-STOCK","EN RANGO")))))))) -> QUIEBRE
A54: IT | B54: OVRA28323 | C54: LAM-POUCH-G-303X426MM-150MIC | D54: 2004823518 | 732536025 | E54: Sobres Pouch Para Plastificar Caliente A3 150mic X 100u - | F54: 15 | G54: 0 | H54: 5 | I54: =ROUND($H54/30,2) -> 0.17 | J54: =IF($Z54="CENSURADO",ROUND($T54/MAX($V54,3),2),ROUND($T54/$G$3,2)) -> 0.44 | K54: =ROUNDUP($J54*$C$3*7,0) -> 10 | L54: =MAX(0,$K54-$F54-$G54) -> 0 | M54: 269 | N54: 480 | O54: =$M54+$N54 -> 749 | P54: =MIN($L54,$O54) -> 0 | Q54: Activa | R54: 1 | S54: Mediano | T54: 14 | U54: 9 | V54: 23 | W54: 1 | X54: 17 | Y54: =IF($X54=0,"",ROUND($H54/$X54,2)) -> 0.29 | Z54: =IF(AND($F54=0,$T54>=5,$W54>=3),"CENSURADO",IF(AND($Y54<>"",$Y54>=3,$T54>=10),"CENSURADO",IF($T54=0,"SIN DATO","CONFIABLE"))) -> CONFIABLE | AA54: =IF($I54=0,"",ROUND($J54/MAX($I54,0.01),2)) -> 2.59 | AB54: =IF($J54<=0,"",ROUND(($F54+$G54)/$J54,0)) -> 34 | AC54: =IF($AB54="","",$J$3+$AB54) -> 46279 | AD54: 0 | AE54: 0 | AF54: 0 | AG54: =IF($AF54=0,"",MAX(0,180-$AE54)) | AH54: 0 | AI54: =IF($AF54=0,"",$AF54*$Q$3-$AF54*$N$3) | AJ54: 7.87 | AK54: =ROUND($F54*$AJ54,0) -> 118 | AL54: =IF(AND($F54=0,$T54>0,$O54=0),"QUIEBRE Y SIN STOCK PARA ENVIAR",IF(AND($F54=0,$T54>0),"QUIEBRE",IF($F54=0,"SIN STOCK SIN DEMANDA",IF(AND($AF54>0,$AG54<>"",OR($AB54="",$AB54>$AG54)),"STOCK VIEJO EN RIESGO",IF(AND($T54=0,$H54=0),"SIN ROTACION",IF($AB54="","-",IF($AB54<14,"REPONER",IF($AB54>84,"SOBRE-STOCK","EN RANGO")))))))) -> EN RANGO
... A77: IT | B77: LDZP98857 | C77: CABLEHDGOLD20M | D77: 1556438103 | 867773412 | E77: Cable Hd 20m Global Electronics 20m Mallado Oro 4k | F77: 21 | G77: 0 | H77: 2 | I77: =ROUND($H77/30,2) -> 0.07 | J77: =IF($Z77="CENSURADO",ROUND($T77/MAX($V77,3),2),ROUND($T77/$G$3,2)) -> 0.19 | K77: =ROUNDUP($J77*$C$3*7,0) -> 4 | L77: =MAX(0,$K77-$F77-$G77) -> 0 | M77: 2873 | N77: 52 | O77: =$M77+$N77 -> 2925 | P77: =MIN($L77,$O77) -> 0 | Q77: Activa | R77: 2 | S77: Pequeño | T77: 6 | U77: 5 | V77: 23 | W77: 3 | X77: 21 | Y77: =IF($X77=0,"",ROUND($H77/$X77,2)) -> 0.1 | Z77: =IF(AND($F77=0,$T77>=5,$W77>=3),"CENSURADO",IF(AND($Y77<>"",$Y77>=3,$T77>=10),"CENSURADO",IF($T77=0,"SIN DATO","CONFIABLE"))) -> CONFIABLE | AA77: =IF($I77=0,"",ROUND($J77/MAX($I77,0.01),2)) -> 2.71 | AB77: =IF($J77<=0,"",ROUND(($F77+$G77)/$J77,0)) -> 111 | AC77: =IF($AB77="","",$J$3+$AB77) -> 46356 | AD77: 0 | AE77: 123 | AF77: 13 | AG77: =IF($AF77=0,"",MAX(0,180-$AE77)) -> 57 | AH77: 6110 | AI77: =IF($AF77=0,"",$AF77*$Q$3-$AF77*$N$3) -> 52195 | AJ77: 8.97 | AK77: =ROUND($F77*$AJ77,0) -> 188 | AL77: =IF(AND($F77=0,$T77>0,$O77=0),"QUIEBRE Y SIN STOCK PARA ENVIAR",IF(AND($F77=0,$T77>0),"QUIEBRE",IF($F77=0,"SIN STOCK SIN DEMANDA",IF(AND($AF77>0,$AG77<>"",OR($AB77="",$AB77>$AG77)),"STOCK VIEJO EN RIESGO",IF(AND($T77=0,$H77=0),"SIN ROTACION",IF($AB77="","-",IF($AB77<14,"REPONER",IF($AB77>84,"SOBRE-STOCK","EN RANGO")))))))) -> STOCK VIEJO EN RIESGO
A78: IT | B78: DBVN94006 | C78: VACSEALER-0301W | D78: 1143875315 | E78: Selladora Envasadora Vacio Para Alimentos Plastico Blanca | F78: 0 | G78: 5 | H78: 5 | I78: =ROUND($H78/30,2) -> 0.17 | J78: =IF($Z78="CENSURADO",ROUND($T78/MAX($V78,3),2),ROUND($T78/$G$3,2)) -> 0.5 | K78: =ROUNDUP($J78*$C$3*7,0) -> 11 | L78: =MAX(0,$K78-$F78-$G78) -> 6 | M78: 0 | N78: 3 | O78: =$M78+$N78 -> 3 | P78: =MIN($L78,$O78) -> 3 | R78: 1 | S78: Mediano | T78: 5 | U78: 3 | V78: 10 | W78: 8 | X78: 2 | Y78: =IF($X78=0,"",ROUND($H78/$X78,2)) -> 2.5 | Z78: =IF(AND($F78=0,$T78>=5,$W78>=3),"CENSURADO",IF(AND($Y78<>"",$Y78>=3,$T78>=10),"CENSURADO",IF($T78=0,"SIN DATO","CONFIABLE"))) -> CENSURADO | AA78: =IF($I78=0,"",ROUND($J78/MAX($I78,0.01),2)) -> 2.94 | AB78: =IF($J78<=0,"",ROUND(($F78+$G78)/$J78,0)) -> 10 | AC78: =IF($AB78="","",$J$3+$AB78) -> 46255 | AD78: 0 | AE78: 121 | AF78: 5 | AG78: =IF($AF78=0,"",MAX(0,180-$AE78)) -> 59 | AH78: 2350 | AI78: =IF($AF78=0,"",$AF78*$Q$3-$AF78*$N$3) -> 20075 | AJ78: 0 | AK78: =ROUND($F78*$AJ78,0) -> 0 | AL78: =IF(AND($F78=0,$T78>0,$O78=0),"QUIEBRE Y SIN STOCK PARA ENVIAR",IF(AND($F78=0,$T78>0),"QUIEBRE",IF($F78=0,"SIN STOCK SIN DEMANDA",IF(AND($AF78>0,$AG78<>"",OR($AB78="",$AB78>$AG78)),"STOCK VIEJO EN RIESGO",IF(AND($T78=0,$H78=0),"SIN ROTACION",IF($AB78="","-",IF($AB78<14,"REPONER",IF($AB78>84,"SOBRE-STOCK","EN RANGO")))))))) -> QUIEBRE
A79: IT | B79: VKNN24062 | C79: KMG27BKCOMBOWLS | D79: 3346296206 | 3346296208 | E79: Combo Teclado Y Mouse Inalámbricos Kmg27 Negro Global Negro | F79: 20 | G79: 5 | H79: 4 | I79: =ROUND($H79/30,2) -> 0.13 | J79: =IF($Z79="CENSURADO",ROUND($T79/MAX($V79,3),2),ROUND($T79/$G$3,2)) -> 0.16 | K79: =ROUNDUP($J79*$C$3*7,0) -> 4 | L79: =MAX(0,$K79-$F79-$G79) -> 0 | M79: 667 | N79: 48 | O79: =$M79+$N79 -> 715 | P79: =MIN($L79,$O79) -> 0 | Q79: Activa | R79: 2 | S79: Mediano (Estimado) | T79: 5 | U79: 3 | V79: 24 | W79: 6 | X79: 23 | Y79: =IF($X79=0,"",ROUND($H79/$X79,2)) -> 0.17 | Z79: =IF(AND($F79=0,$T79>=5,$W79>=3),"CENSURADO",IF(AND($Y79<>"",$Y79>=3,$T79>=10),"CENSURADO",IF($T79=0,"SIN DATO","CONFIABLE"))) -> CONFIABLE | AA79: =IF($I79=0,"",ROUND($J79/MAX($I79,0.01),2)) -> 1.23 | AB79: =IF($J79<=0,"",ROUND(($F79+$G79)/$J79,0)) -> 156 | AC79: =IF($AB79="","",$J$3+$AB79) -> 46401 | AD79: 1 | AE79: 163 | AF79: 6 | AG79: =IF($AF79=0,"",MAX(0,180-$AE79)) -> 17 | AH79: 2820 | AI79: =IF($AF79=0,"",$AF79*$Q$3-$AF79*$N$3) -> 24090 | AJ79: 6.93 | AK79: =ROUND($F79*$AJ79,0) -> 139 | AL79: =IF(AND($F79=0,$T79>0,$O79=0),"QUIEBRE Y SIN STOCK PARA ENVIAR",IF(AND($F79=0,$T79>0),"QUIEBRE",IF($F79=0,"SIN STOCK SIN DEMANDA",IF(AND($AF79>0,$AG79<>"",OR($AB79="",$AB79>$AG79)),"STOCK VIEJO EN RIESGO",IF(AND($T79=0,$H79=0),"SIN ROTACION",IF($AB79="","-",IF($AB79<14,"REPONER",IF($AB79>84,"SOBRE-STOCK","EN RANGO")))))))) -> STOCK VIEJO EN RIESGO
A80: IT | B80: KXUD62443 | C80: HTV-PVC-WHITE-G-50X1MT | D80: 1516769711 | E80: Vinilo Termotransferible Pvc Textil Glossy 50cm X 1 Metro | F80: 0 | G80: 0 | H80: 5 | I80: =ROUND($H80/30,2) -> 0.17 | J80: =IF($Z80="CENSURADO",ROUND($T80/MAX($V80,3),2),ROUND($T80/$G$3,2)) -> 0.31 | K80: =ROUNDUP($J80*$C$3*7,0) -> 7 | L80: =MAX(0,$K80-$F80-$G80) -> 7 | M80: 0 | N80: 1 | O80: =$M80+$N80 -> 1 | P80: =MIN($L80,$O80) -> 1 | Q80: Activa | R80: 1 | S80: Mediano | T80: 5 | U80: 4 | V80: 16 | W80: 7 | X80: 2 | Y80: =IF($X80=0,"",ROUND($H80/$X80,2)) -> 2.5 | Z80: =IF(AND($F80=0,$T80>=5,$W80>=3),"CENSURADO",IF(AND($Y80<>"",$Y80>=3,$T80>=10),"CENSURADO",IF($T80=0,"SIN DATO","CONFIABLE"))) -> CENSURADO | AA80: =IF($I80=0,"",ROUND($J80/MAX($I80,0.01),2)) -> 1.82 | AB80: =IF($J80<=0,"",ROUND(($F80+$G80)/$J80,0)) -> 0 | AC80: =IF($AB80="","",$J$3+$AB80) -> 46245 | AD80: 0 | AE80: 0 | AF80: 0 | AG80: =IF($AF80=0,"",MAX(0,180-$AE80)) | AH80: 0 | AI80: =IF($AF80=0,"",$AF80*$Q$3-$AF80*$N$3) | AJ80: 0 | AK80: =ROUND($F80*$AJ80,0) -> 0 | AL80: =IF(AND($F80=0,$T80>0,$O80=0),"QUIEBRE Y SIN STOCK PARA ENVIAR",IF(AND($F80=0,$T80>0),"QUIEBRE",IF($F80=0,"SIN STOCK SIN DEMANDA",IF(AND($AF80>0,$AG80<>"",OR($AB80="",$AB80>$AG80)),"STOCK VIEJO EN RIESGO",IF(AND($T80=0,$H80=0),"SIN ROTACION",IF($AB80="","-",IF($AB80<14,"REPONER",IF($AB80>84,"SOBRE-STOCK","EN RANGO")))))))) -> QUIEBRE
A81: IT | B81: UKNM63522 | C81: CF258ACOMPNOCHIP | D81: 1431721297 | 824705993 | E81: Toner Alternativo S/chip Cf258a 258a 58a M404 M428 Negro | F81: 0 | G81: 0 | H81: 5 | I81: =ROUND($H81/30,2) -> 0.17 | J81: =IF($Z81="CENSURADO",ROUND($T81/MAX($V81,3),2),ROUND($T81/$G$3,2)) -> 0.25 | K81: =ROUNDUP($J81*$C$3*7,0) -> 6 | L81: =MAX(0,$K81-$F81-$G81) -> 6 | M81: 11 | N81: 0 | O81: =$M81+$N81 -> 11 | P81: =MIN($L81,$O81) -> 6 | R81: 1 | S81: Mediano | T81: 5 | U81: 2 | V81: 20 | W81: 7 | X81: 3 | Y81: =IF($X81=0,"",ROUND($H81/$X81,2)) -> 1.67 | Z81: =IF(AND($F81=0,$T81>=5,$W81>=3),"CENSURADO",IF(AND($Y81<>"",$Y81>=3,$T81>=10),"CENSURADO",IF($T81=0,"SIN DATO","CONFIABLE"))) -> CENSURADO | AA81: =IF($I81=0,"",ROUND($J81/MAX($I81,0.01),2)) -> 1.47 | AB81: =IF($J81<=0,"",ROUND(($F81+$G81)/$J81,0)) -> 0 | AC81: =IF($AB81="","",$J$3+$AB81) -> 46245 | AD81: 0 | AE81: 0 | AF81: 0 | AG81: =IF($AF81=0,"",MAX(0,180-$AE81)) | AH81: 0 | AI81: =IF($AF81=0,"",$AF81*$Q$3-$AF81*$N$3) | AJ81: 4.5 | AK81: =ROUND($F81*$AJ81,0) -> 0 | AL81: =IF(AND($F81=0,$T81>0,$O81=0),"QUIEBRE Y SIN STOCK PARA ENVIAR",IF(AND($F81=0,$T81>0),"QUIEBRE",IF($F81=0,"SIN STOCK SIN DEMANDA",IF(AND($AF81>0,$AG81<>"",OR($AB81="",$AB81>$AG81)),"STOCK VIEJO EN RIESGO",IF(AND($T81=0,$H81=0),"SIN ROTACION",IF($AB81="","-",IF($AB81<14,"REPONER",IF($AB81>84,"SOBRE-STOCK","EN RANGO")))))))) -> QUIEBRE
A82: IT | B82: SUPJ01892 | C82: PLANCHA-SUB-GORRA | D82: 1423295653 | 1443389055 | 2547006646 | E82: Estampadora Sublimadora De Gorras Potencia 110/220v 350w Negro | F82: 4 | G82: 0 | H82: 3 | I82: =ROUND($H82/30,2) -> 0.1 | J82: =IF($Z82="CENSURADO",ROUND($T82/MAX($V82,3),2),ROUND($T82/$G$3,2)) -> 0.16 | K82: =ROUNDUP($J82*$C$3*7,0) -> 4 | L82: =MAX(0,$K82-$F82-$G82) -> 0 | M82: 22 | N82: 0 | O82: =$M82+$N82 -> 22 | P82: =MIN($L82,$O82) -> 0 | Q82: Activa | R82: 1 | S82: Grande | T82: 5 | U82: 5 | V82: 17 | W82: 1 | X82: 8 | Y82: =IF($X82=0,"",ROUND($H82/$X82,2)) -> 0.38 | Z82: =IF(AND($F82=0,$T82>=5,$W82>=3),"CENSURADO",IF(AND($Y82<>"",$Y82>=3,$T82>=10),"CENSURADO",IF($T82=0,"SIN DATO","CONFIABLE"))) -> CONFIABLE | AA82: =IF($I82=0,"",ROUND($J82/MAX($I82,0.01),2)) -> 1.6 | AB82: =IF($J82<=0,"",ROUND(($F82+$G82)/$J82,0)) -> 25 | AC82: =IF($AB82="","",$J$3+$AB82) -> 46270 | AD82: 0 | AE82: 142 | AF82: 9 | AG82: =IF($AF82=0,"",MAX(0,180-$AE82)) -> 38 | AH82: 12195 | AI82: =IF($AF82=0,"",$AF82*$Q$3-$AF82*$N$3) -> 36135 | AJ82: 58.91 | AK82: =ROUND($F82*$AJ82,0) -> 236 | AL82: =IF(AND($F82=0,$T82>0,$O82=0),"QUIEBRE Y SIN STOCK PARA ENVIAR",IF(AND($F82=0,$T82>0),"QUIEBRE",IF($F82=0,"SIN STOCK SIN DEMANDA",IF(AND($AF82>0,$AG82<>"",OR($AB82="",$AB82>$AG82)),"STOCK VIEJO EN RIESGO",IF(AND($T82=0,$H82=0),"SIN ROTACION",IF($AB82="","-",IF($AB82<14,"REPONER",IF($AB82>84,"SOBRE-STOCK","EN RANGO")))))))) -> EN RANGO
A83: IT | B83: HKMR11070 | C83: MONI-OFFICE-27IFHD | D83: 1498545659 | 3535868688 | E83: Monitor 27 Full Hd 1080p 60hz Hdmi + Vga Global Negro | F83: 0 | G83: 0 | H83: 5 | I83: =ROUND($H83/30,2) -> 0.17 | J83: =IF($Z83="CENSURADO",ROUND($T83/MAX($V83,3),2),ROUND($T83/$G$3,2)) -> 0.38 | K83: =ROUNDUP($J83*$C$3*7,0) -> 8 | L83: =MAX(0,$K83-$F83-$G83) -> 8 | M83: 136 | N83: 0 | O83: =$M83+$N83 -> 136 | P83: =MIN($L83,$O83) -> 8 | R83: 1 | S83: Grande | T83: 5 | U83: 3 | V83: 13 | W83: 17 | X83: 2 | Y83: =IF($X83=0,"",ROUND($H83/$X83,2)) -> 2.5 | Z83: =IF(AND($F83=0,$T83>=5,$W83>=3),"CENSURADO",IF(AND($Y83<>"",$Y83>=3,$T83>=10),"CENSURADO",IF($T83=0,"SIN DATO","CONFIABLE"))) -> CENSURADO | AA83: =IF($I83=0,"",ROUND($J83/MAX($I83,0.01),2)) -> 2.24 | AB83: =IF($J83<=0,"",ROUND(($F83+$G83)/$J83,0)) -> 0 | AC83: =IF($AB83="","",$J$3+$AB83) -> 46245 | AD83: 0 | AE83: 0 | AF83: 0 | AG83: =IF($AF83=0,"",MAX(0,180-$AE83)) | AH83: 0 | AI83: =IF($AF83=0,"",$AF83*$Q$3-$AF83*$N$3) | AJ83: 40.02 | AK83: =ROUND($F83*$AJ83,0) -> 0 | AL83: =IF(AND($F83=0,$T83>0,$O83=0),"QUIEBRE Y SIN STOCK PARA ENVIAR",IF(AND($F83=0,$T83>0),"QUIEBRE",IF($F83=0,"SIN STOCK SIN DEMANDA",IF(AND($AF83>0,$AG83<>"",OR($AB83="",$AB83>$AG83)),"STOCK VIEJO EN RIESGO",IF(AND($T83=0,$H83=0),"SIN ROTACION",IF($AB83="","-",IF($AB83<14,"REPONER",IF($AB83>84,"SOBRE-STOCK","EN RANGO")))))))) -> QUIEBRE
A84: IT | B84: VXPL12567 | C84: MPADGAMER-RGB-80X30 | D84: 1367417403 | E84: Mouse Pad Gamer Retroiluminado Rgb Global 80x30 Cm Negro | F84: 5 | G84: 0 | H84: 4 | I84: =ROUND($H84/30,2) -> 0.13 | J84: =IF($Z84="CENSURADO",ROUND($T84/MAX($V84,3),2),ROUND($T84/$G$3,2)) -> 0.16 | K84: =ROUNDUP($J84*$C$3*7,0) -> 4 | L84: =MAX(0,$K84-$F84-$G84) -> 0 | M84: 3497 | N84: 189 | O84: =$M84+$N84 -> 3686 | P84: =MIN($L84,$O84) -> 0 | Q84: Activa | R84: 1 | S84: Mediano | T84: 5 | U84: 3 | V84: 5 | W84: 14 | X84: 7 | Y84: =IF($X84=0,"",ROUND($H84/$X84,2)) -> 0.57 | Z84: =IF(AND($F84=0,$T84>=5,$W84>=3),"CENSURADO",IF(AND($Y84<>"",$Y84>=3,$T84>=10),"CENSURADO",IF($T84=0,"SIN DATO","CONFIABLE"))) -> CONFIABLE | AA84: =IF($I84=0,"",ROUND($J84/MAX($I84,0.01),2)) -> 1.23 | AB84: =IF($J84<=0,"",ROUND(($F84+$G84)/$J84,0)) -> 31 | AC84: =IF($AB84="","",$J$3+$AB84) -> 46276 | AD84: 0 | AE84: 130 | AF84: 9 | AG84: =IF($AF84=0,"",MAX(0,180-$AE84)) -> 50 | AH84: 4230 | AI84: =IF($AF84=0,"",$AF84*$Q$3-$AF84*$N$3) -> 36135 | AJ84: 7.01 | AK84: =ROUND($F84*$AJ84,0) -> 35 | AL84: =IF(AND($F84=0,$T84>0,$O84=0),"QUIEBRE Y SIN STOCK PARA ENVIAR",IF(AND($F84=0,$T84>0),"QUIEBRE",IF($F84=0,"SIN STOCK SIN DEMANDA",IF(AND($AF84>0,$AG84<>"",OR($AB84="",$AB84>$AG84)),"STOCK VIEJO EN RIESGO",IF(AND($T84=0,$H84=0),"SIN ROTACION",IF($AB84="","-",IF($AB84<14,"REPONER",IF($AB84>84,"SOBRE-STOCK","EN RANGO")))))))) -> EN RANGO
A85: IT | B85: NYFH95409 | C85: CABLEIPHLIGHT1MW | D85: 645405242 | E85: Cable Usb 5 5s 5c 7 6 Plus Touch 4 Air Min Blanco | F85: 22 | G85: 5 | H85: 3 | I85: =ROUND($H85/30,2) -> 0.1 | J85: =IF($Z85="CENSURADO",ROUND($T85/MAX($V85,3),2),ROUND($T85/$G$3,2)) -> 0.13 | K85: =ROUNDUP($J85*$C$3*7,0) -> 3 | L85: =MAX(0,$K85-$F85-$G85) -> 0 | M85: 6174 | N85: 417 | O85: =$M85+$N85 -> 6591 | P85: =MIN($L85,$O85) -> 0 | Q85: Activa | R85: 1 | S85: Pequeño | T85: 4 | U85: 2 | V85: 9 | W85: 4 | X85: 23 | Y85: =IF($X85=0,"",ROUND($H85/$X85,2)) -> 0.13 | Z85: =IF(AND($F85=0,$T85>=5,$W85>=3),"CENSURADO",IF(AND($Y85<>"",$Y85>=3,$T85>=10),"CENSURADO",IF($T85=0,"SIN DATO","CONFIABLE"))) -> CONFIABLE | AA85: =IF($I85=0,"",ROUND($J85/MAX($I85,0.01),2)) -> 1.3 | AB85: =IF($J85<=0,"",ROUND(($F85+$G85)/$J85,0)) -> 208 | AC85: =IF($AB85="","",$J$3+$AB85) -> 46453 | AD85: 0 | AE85: 0 | AF85: 0 | AG85: =IF($AF85=0,"",MAX(0,180-$AE85)) | AH85: 0 | AI85: =IF($AF85=0,"",$AF85*$Q$3-$AF85*$N$3) | AJ85: 1.05 | AK85: =ROUND($F85*$AJ85,0) -> 23 | AL85: =IF(AND($F85=0,$T85>0,$O85=0),"QUIEBRE Y SIN STOCK PARA ENVIAR",IF(AND($F85=0,$T85>0),"QUIEBRE",IF($F85=0,"SIN STOCK SIN DEMANDA",IF(AND($AF85>0,$AG85<>"",OR($AB85="",$AB85>$AG85)),"STOCK VIEJO EN RIESGO",IF(AND($T85=0,$H85=0),"SIN ROTACION",IF($AB85="","-",IF($AB85<14,"REPONER",IF($AB85>84,"SOBRE-STOCK","EN RANGO")))))))) -> SOBRE-STOCK
A86: IT | B86: JCUL11544 | C86: FOILGOLD-M-32X6MT | D86: 1876615926 | E86: Papel Foil Metalizado Textil Para Telas 32cmx6mt Gold Metalizado Mate | F86: 0 | G86: 0 | H86: 0 | I86: =ROUND($H86/30,2) -> 0 | J86: =IF($Z86="CENSURADO",ROUND($T86/MAX($V86,3),2),ROUND($T86/$G$3,2)) -> 0.13 | K86: =ROUNDUP($J86*$C$3*7,0) -> 3 | L86: =MAX(0,$K86-$F86-$G86) -> 3 | M86: 756 | N86: 212 | O86: =$M86+$N86 -> 968 | P86: =MIN($L86,$O86) -> 3 | Q86: Activa | R86: 1 | S86: Mediano | T86: 4 | U86: 2 | V86: 14 | W86: 14 | X86: 0 | Y86: =IF($X86=0,"",ROUND($H86/$X86,2)) | Z86: =IF(AND($F86=0,$T86>=5,$W86>=3),"CENSURADO",IF(AND($Y86<>"",$Y86>=3,$T86>=10),"CENSURADO",IF($T86=0,"SIN DATO","CONFIABLE"))) -> CONFIABLE | AA86: =IF($I86=0,"",ROUND($J86/MAX($I86,0.01),2)) | AB86: =IF($J86<=0,"",ROUND(($F86+$G86)/$J86,0)) -> 0 | AC86: =IF($AB86="","",$J$3+$AB86) -> 46245 | AD86: 0 | AE86: 0 | AF86: 0 | AG86: =IF($AF86=0,"",MAX(0,180-$AE86)) | AH86: 0 | AI86: =IF($AF86=0,"",$AF86*$Q$3-$AF86*$N$3) | AJ86: 1.28 | AK86: =ROUND($F86*$AJ86,0) -> 0 | AL86: =IF(AND($F86=0,$T86>0,$O86=0),"QUIEBRE Y SIN STOCK PARA ENVIAR",IF(AND($F86=0,$T86>0),"QUIEBRE",IF($F86=0,"SIN STOCK SIN DEMANDA",IF(AND($AF86>0,$AG86<>"",OR($AB86="",$AB86>$AG86)),"STOCK VIEJO EN RIESGO",IF(AND($T86=0,$H86=0),"SIN ROTACION",IF($AB86="","-",IF($AB86<14,"REPONER",IF($AB86>84,"SOBRE-STOCK","EN RANGO")))))))) -> QUIEBRE
A87: IT | B87: WMJD20272 | C87: BILLCOUNTER-1 | D87: 1635370518 | 1957815150 | E87: Contadora De Billetes Maquina Cuenta Dinero Detector Falsos | F87: 22 | G87: 5 | H87: 3 | I87: =ROUND($H87/30,2) -> 0.1 | J87: =IF($Z87="CENSURADO",ROUND($T87/MAX($V87,3),2),ROUND($T87/$G$3,2)) -> 0.13 | K87: =ROUNDUP($J87*$C$3*7,0) -> 3 | L87: =MAX(0,$K87-$F87-$G87) -> 0 | M87: 2680 | N87: 1498 | O87: =$M87+$N87 -> 4178 | P87: =MIN($L87,$O87) -> 0 | Q87: Activa | R87: 2 | S87: Mediano | T87: 4 | U87: 3 | V87: 4 | W87: 18 | X87: 31 | Y87: =IF($X87=0,"",ROUND($H87/$X87,2)) -> 0.1 | Z87: =IF(AND($F87=0,$T87>=5,$W87>=3),"CENSURADO",IF(AND($Y87<>"",$Y87>=3,$T87>=10),"CENSURADO",IF($T87=0,"SIN DATO","CONFIABLE"))) -> CONFIABLE | AA87: =IF($I87=0,"",ROUND($J87/MAX($I87,0.01),2)) -> 1.3 | AB87: =IF($J87<=0,"",ROUND(($F87+$G87)/$J87,0)) -> 208 | AC87: =IF($AB87="","",$J$3+$AB87) -> 46453 | AD87: 0 | AE87: 130 | AF87: 9 | AG87: =IF($AF87=0,"",MAX(0,180-$AE87)) -> 50 | AH87: 4230 | AI87: =IF($AF87=0,"",$AF87*$Q$3-$AF87*$N$3) -> 36135 | AJ87: 31.79 | AK87: =ROUND($F87*$AJ87,0) -> 699 | AL87: =IF(AND($F87=0,$T87>0,$O87=0),"QUIEBRE Y SIN STOCK PARA ENVIAR",IF(AND($F87=0,$T87>0),"QUIEBRE",IF($F87=0,"SIN STOCK SIN DEMANDA",IF(AND($AF87>0,$AG87<>"",OR($AB87="",$AB87>$AG87)),"STOCK VIEJO EN RIESGO",IF(AND($T87=0,$H87=0),"SIN ROTACION",IF($AB87="","-",IF($AB87<14,"REPONER",IF($AB87>84,"SOBRE-STOCK","EN RANGO")))))))) -> STOCK VIEJO EN RIESGO
A88: IT | B88: USDY68617 | C88: TVS-TILT-26-55I-400X400 | D88: 1458499628 | 899088022 | E88: Soporte Tv Lcd Basculante Vesa 400x400 26 A 55 Negro | F88: 27 | G88: 0 | H88: 2 | I88: =ROUND($H88/30,2) -> 0.07 | J88: =IF($Z88="CENSURADO",ROUND($T88/MAX($V88,3),2),ROUND($T88/$G$3,2)) -> 0.09 | K88: =ROUNDUP($J88*$C$3*7,0) -> 2 | L88: =MAX(0,$K88-$F88-$G88) -> 0 | M88: 1 | N88: 10 | O88: =$M88+$N88 -> 11 | P88: =MIN($L88,$O88) -> 0 | Q88: Activa | R88: 1 | S88: Mediano | T88: 3 | U88: 2 | V88: 2 | W88: 29 | X88: 27 | Y88: =IF($X88=0,"",ROUND($H88/$X88,2)) -> 0.07 | Z88: =IF(AND($F88=0,$T88>=5,$W88>=3),"CENSURADO",IF(AND($Y88<>"",$Y88>=3,$T88>=10),"CENSURADO",IF($T88=0,"SIN DATO","CONFIABLE"))) -> CONFIABLE | AA88: =IF($I88=0,"",ROUND($J88/MAX($I88,0.01),2)) -> 1.29 | AB88: =IF($J88<=0,"",ROUND(($F88+$G88)/$J88,0)) -> 300 | AC88: =IF($AB88="","",$J$3+$AB88) -> 46545 | AD88: 0 | AE88: 170 | AF88: 23 | AG88: =IF($AF88=0,"",MAX(0,180-$AE88)) -> 10 | AH88: 10810 | AI88: =IF($AF88=0,"",$AF88*$Q$3-$AF88*$N$3) -> 92345 | AJ88: 4.46 | AK88: =ROUND($F88*$AJ88,0) -> 120 | AL88: =IF(AND($F88=0,$T88>0,$O88=0),"QUIEBRE Y SIN STOCK PARA ENVIAR",IF(AND($F88=0,$T88>0),"QUIEBRE",IF($F88=0,"SIN STOCK SIN DEMANDA",IF(AND($AF88>0,$AG88<>"",OR($AB88="",$AB88>$AG88)),"STOCK VIEJO EN RIESGO",IF(AND($T88=0,$H88=0),"SIN ROTACION",IF($AB88="","-",IF($AB88<14,"REPONER",IF($AB88>84,"SOBRE-STOCK","EN RANGO")))))))) -> STOCK VIEJO EN RIESGO
A89: IT | B89: XXUG12355 | C89: EXPDISC+DOUWIRE-2IN1-MINI-P | D89: 3484868310 | 3546936634 | E89: Encuadernadora Manual 2 En 1 Discos Y Doble Wire 15 Hojas Rosa | F89: 19 | G89: 0 | H89: 1 | I89: =ROUND($H89/30,2) -> 0.03 | J89: =IF($Z89="CENSURADO",ROUND($T89/MAX($V89,3),2),ROUND($T89/$G$3,2)) -> 0.09 | K89: =ROUNDUP($J89*$C$3*7,0) -> 2 | L89: =MAX(0,$K89-$F89-$G89) -> 0 | M89: 118 | N89: 101 | O89: =$M89+$N89 -> 219 | P89: =MIN($L89,$O89) -> 0 | Q89: Activa | R89: 1 | S89: Mediano | T89: 3 | U89: 3 | V89: 22 | W89: 8 | X89: 20 | Y89: =IF($X89=0,"",ROUND($H89/$X89,2)) -> 0.05 | Z89: =IF(AND($F89=0,$T89>=5,$W89>=3),"CENSURADO",IF(AND($Y89<>"",$Y89>=3,$T89>=10),"CENSURADO",IF($T89=0,"SIN DATO","CONFIABLE"))) -> CONFIABLE | AA89: =IF($I89=0,"",ROUND($J89/MAX($I89,0.01),2)) -> 3 | AB89: =IF($J89<=0,"",ROUND(($F89+$G89)/$J89,0)) -> 211 | AC89: =IF($AB89="","",$J$3+$AB89) -> 46456 | AD89: 0 | AE89: 0 | AF89: 0 | AG89: =IF($AF89=0,"",MAX(0,180-$AE89)) | AH89: 0 | AI89: =IF($AF89=0,"",$AF89*$Q$3-$AF89*$N$3) | AJ89: 0 | AK89: =ROUND($F89*$AJ89,0) -> 0 | AL89: =IF(AND($F89=0,$T89>0,$O89=0),"QUIEBRE Y SIN STOCK PARA ENVIAR",IF(AND($F89=0,$T89>0),"QUIEBRE",IF($F89=0,"SIN STOCK SIN DEMANDA",IF(AND($AF89>0,$AG89<>"",OR($AB89="",$AB89>$AG89)),"STOCK VIEJO EN RIESGO",IF(AND($T89=0,$H89=0),"SIN ROTACION",IF($AB89="","-",IF($AB89<14,"REPONER",IF($AB89>84,"SOBRE-STOCK","EN RANGO")))))))) -> SOBRE-STOCK
A90: IT | B90: XVFV46244 | C90: SMARTLOCK-WT1 | D90: 2859298958 | 2900941722 | E90: Cerradura Inteligente Huella Digital App Tuya Wifi Global Negro | F90: 50 | G90: 0 | H90: 3 | I90: =ROUND($H90/30,2) -> 0.1 | J90: =IF($Z90="CENSURADO",ROUND($T90/MAX($V90,3),2),ROUND($T90/$G$3,2)) -> 0.09 | K90: =ROUNDUP($J90*$C$3*7,0) -> 2 | L90: =MAX(0,$K90-$F90-$G90) -> 0 | M90: 3 | N90: 0 | O90: =$M90+$N90 -> 3 | P90: =MIN($L90,$O90) -> 0 | Q90: Activa | R90: 1 | S90: Mediano | T90: 3 | U90: 3 | V90: 10 | W90: 6 | X90: 52 | Y90: =IF($X90=0,"",ROUND($H90/$X90,2)) -> 0.06 | Z90: =IF(AND($F90=0,$T90>=5,$W90>=3),"CENSURADO",IF(AND($Y90<>"",$Y90>=3,$T90>=10),"CENSURADO",IF($T90=0,"SIN DATO","CONFIABLE"))) -> CONFIABLE | AA90: =IF($I90=0,"",ROUND($J90/MAX($I90,0.01),2)) -> 0.9 | AB90: =IF($J90<=0,"",ROUND(($F90+$G90)/$J90,0)) -> 556 | AC90: =IF($AB90="","",$J$3+$AB90) -> 46801 | AD90: 0 | AE90: 0 | AF90: 0 | AG90: =IF($AF90=0,"",MAX(0,180-$AE90)) | AH90: 0 | AI90: =IF($AF90=0,"",$AF90*$Q$3-$AF90*$N$3) | AJ90: 27.29 | AK90: =ROUND($F90*$AJ90,0) -> 1365 | AL90: =IF(AND($F90=0,$T90>0,$O90=0),"QUIEBRE Y SIN STOCK PARA ENVIAR",IF(AND($F90=0,$T90>0),"QUIEBRE",IF($F90=0,"SIN STOCK SIN DEMANDA",IF(AND($AF90>0,$AG90<>"",OR($AB90="",$AB90>$AG90)),"STOCK VIEJO EN RIESGO",IF(AND($T90=0,$H90=0),"SIN ROTACION",IF($AB90="","-",IF($AB90<14,"REPONER",IF($AB90>84,"SOBRE-STOCK","EN RANGO")))))))) -> SOBRE-STOCK
A91: IT | B91: HQVW06525 | C91: SANDMAK3IN1 | D91: 1550520415 | E91: Sandwichera Waflera Eléctrica Con Placa Antiadherente Negro | F91: 14 | G91: 0 | H91: 1 | I91: =ROUND($H91/30,2) -> 0.03 | J91: =IF($Z91="CENSURADO",ROUND($T91/MAX($V91,3),2),ROUND($T91/$G$3,2)) -> 0.09 | K91: =ROUNDUP($J91*$C$3*7,0) -> 2 | L91: =MAX(0,$K91-$F91-$G91) -> 0 | M91: 896 | N91: 282 | O91: =$M91+$N91 -> 1178 | P91: =MIN($L91,$O91) -> 0 | Q91: Activa | R91: 1 | S91: Mediano | T91: 3 | U91: 3 | V91: 15 | W91: 2 | X91: 15 | Y91: =IF($X91=0,"",ROUND($H91/$X91,2)) -> 0.07 | Z91: =IF(AND($F91=0,$T91>=5,$W91>=3),"CENSURADO",IF(AND($Y91<>"",$Y91>=3,$T91>=10),"CENSURADO",IF($T91=0,"SIN DATO","CONFIABLE"))) -> CONFIABLE | AA91: =IF($I91=0,"",ROUND($J91/MAX($I91,0.01),2)) -> 3 | AB91: =IF($J91<=0,"",ROUND(($F91+$G91)/$J91,0)) -> 156 | AC91: =IF($AB91="","",$J$3+$AB91) -> 46401 | AD91: 0 | AE91: 0 | AF91: 0 | AG91: =IF($AF91=0,"",MAX(0,180-$AE91)) | AH91: 0 | AI91: =IF($AF91=0,"",$AF91*$Q$3-$AF91*$N$3) | AJ91: 11.85 | AK91: =ROUND($F91*$AJ91,0) -> 166 | AL91: =IF(AND($F91=0,$T91>0,$O91=0),"QUIEBRE Y SIN STOCK PARA ENVIAR",IF(AND($F91=0,$T91>0),"QUIEBRE",IF($F91=0,"SIN STOCK SIN DEMANDA",IF(AND($AF91>0,$AG91<>"",OR($AB91="",$AB91>$AG91)),"STOCK VIEJO EN RIESGO",IF(AND($T91=0,$H91=0),"SIN ROTACION",IF($AB91="","-",IF($AB91<14,"REPONER",IF($AB91>84,"SOBRE-STOCK","EN RANGO")))))))) -> SOBRE-STOCK
A92: IT | B92: TCDN10710 | C92: EPINEARMIC-2W | D92: 1613135290 | 921860739 | E92: Auricular Con Microfono Con Cable Plug Fino Jack 3.5 Blanco | F92: 25 | G92: 5 | H92: 0 | I92: =ROUND($H92/30,2) -> 0 | J92: =IF($Z92="CENSURADO",ROUND($T92/MAX($V92,3),2),ROUND($T92/$G$3,2)) -> 0.09 | K92: =ROUNDUP($J92*$C$3*7,0) -> 2 | L92: =MAX(0,$K92-$F92-$G92) -> 0 | M92: 12038 | N92: 50 | O92: =$M92+$N92 -> 12088 | P92: =MIN($L92,$O92) -> 0 | Q92: Activa | R92: 1 | S92: Pequeño | T92: 3 | U92: 3 | V92: 10 | W92: 3 | X92: 24 | Y92: =IF($X92=0,"",ROUND($H92/$X92,2)) -> 0 | Z92: =IF(AND($F92=0,$T92>=5,$W92>=3),"CENSURADO",IF(AND($Y92<>"",$Y92>=3,$T92>=10),"CENSURADO",IF($T92=0,"SIN DATO","CONFIABLE"))) -> CONFIABLE | AA92: =IF($I92=0,"",ROUND($J92/MAX($I92,0.01),2)) | AB92: =IF($J92<=0,"",ROUND(($F92+$G92)/$J92,0)) -> 333 | AC92: =IF($AB92="","",$J$3+$AB92) -> 46578 | AD92: 0 | AE92: 0 | AF92: 0 | AG92: =IF($AF92=0,"",MAX(0,180-$AE92)) | AH92: 0 | AI92: =IF($AF92=0,"",$AF92*$Q$3-$AF92*$N$3) | AJ92: 0.93 | AK92: =ROUND($F92*$AJ92,0) -> 23 | AL92: =IF(AND($F92=0,$T92>0,$O92=0),"QUIEBRE Y SIN STOCK PARA ENVIAR",IF(AND($F92=0,$T92>0),"QUIEBRE",IF($F92=0,"SIN STOCK SIN DEMANDA",IF(AND($AF92>0,$AG92<>"",OR($AB92="",$AB92>$AG92)),"STOCK VIEJO EN RIESGO",IF(AND($T92=0,$H92=0),"SIN ROTACION",IF($AB92="","-",IF($AB92<14,"REPONER",IF($AB92>84,"SOBRE-STOCK","EN RANGO")))))))) -> SOBRE-STOCK
A93: IT | B93: YFLE02140 | C93: PLANCHA-SUB-TERMO | D93: 1476006109 | E93: Plancha Estampadora De Termos 30oz Negro | F93: 0 | G93: 0 | H93: 0 | I93: =ROUND($H93/30,2) -> 0 | J93: =IF($Z93="CENSURADO",ROUND($T93/MAX($V93,3),2),ROUND($T93/$G$3,2)) -> 0.06 | K93: =ROUNDUP($J93*$C$3*7,0) -> 2 | L93: =MAX(0,$K93-$F93-$G93) -> 2 | M93: 26 | N93: 161 | O93: =$M93+$N93 -> 187 | P93: =MIN($L93,$O93) -> 2 | R93: 1 | S93: Grande | T93: 2 | U93: 2 | V93: 7 | W93: 1 | X93: 0 | Y93: =IF($X93=0,"",ROUND($H93/$X93,2)) | Z93: =IF(AND($F93=0,$T93>=5,$W93>=3),"CENSURADO",IF(AND($Y93<>"",$Y93>=3,$T93>=10),"CENSURADO",IF($T93=0,"SIN DATO","CONFIABLE"))) -> CONFIABLE | AA93: =IF($I93=0,"",ROUND($J93/MAX($I93,0.01),2)) | AB93: =IF($J93<=0,"",ROUND(($F93+$G93)/$J93,0)) -> 0 | AC93: =IF($AB93="","",$J$3+$AB93) -> 46245 | AD93: 0 | AE93: 0 | AF93: 0 | AG93: =IF($AF93=0,"",MAX(0,180-$AE93)) | AH93: 0 | AI93: =IF($AF93=0,"",$AF93*$Q$3-$AF93*$N$3) | AJ93: 41.8 | AK93: =ROUND($F93*$AJ93,0) -> 0 | AL93: =IF(AND($F93=0,$T93>0,$O93=0),"QUIEBRE Y SIN STOCK PARA ENVIAR",IF(AND($F93=0,$T93>0),"QUIEBRE",IF($F93=0,"SIN STOCK SIN DEMANDA",IF(AND($AF93>0,$AG93<>"",OR($AB93="",$AB93>$AG93)),"STOCK VIEJO EN RIESGO",IF(AND($T93=0,$H93=0),"SIN ROTACION",IF($AB93="","-",IF($AB93<14,"REPONER",IF($AB93>84,"SOBRE-STOCK","EN RANGO")))))))) -> QUIEBRE
A94: IT | B94: AKKQ44424 | C94: FAN-BLADELESSCOOL | D94: 2765525516 | E94: Ventilador Portátil Mini De Mesa Pleglable Usb 6 Velocidades Blanco | F94: 11 | G94: 0 | H94: 2 | I94: =ROUND($H94/30,2) -> 0.07 | J94: =IF($Z94="CENSURADO",ROUND($T94/MAX($V94,3),2),ROUND($T94/$G$3,2)) -> 0.06 | K94: =ROUNDUP($J94*$C$3*7,0) -> 2 | L94: =MAX(0,$K94-$F94-$G94) -> 0 | M94: 184 | N94: 207 | O94: =$M94+$N94 -> 391 | P94: =MIN($L94,$O94) -> 0 | Q94: Activa | R94: 1 | S94: Mediano | T94: 2 | U94: 1 | V94: 1 | W94: 12 | X94: 12 | Y94: =IF($X94=0,"",ROUND($H94/$X94,2)) -> 0.17 | Z94: =IF(AND($F94=0,$T94>=5,$W94>=3),"CENSURADO",IF(AND($Y94<>"",$Y94>=3,$T94>=10),"CENSURADO",IF($T94=0,"SIN DATO","CONFIABLE"))) -> CONFIABLE | AA94: =IF($I94=0,"",ROUND($J94/MAX($I94,0.01),2)) -> 0.86 | AB94: =IF($J94<=0,"",ROUND(($F94+$G94)/$J94,0)) -> 183 | AC94: =IF($AB94="","",$J$3+$AB94) -> 46428 | AD94: 0 | AE94: 0 | AF94: 0 | AG94: =IF($AF94=0,"",MAX(0,180-$AE94)) | AH94: 0 | AI94: =IF($AF94=0,"",$AF94*$Q$3-$AF94*$N$3) | AJ94: 6.68 | AK94: =ROUND($F94*$AJ94,0) -> 73 | AL94: =IF(AND($F94=0,$T94>0,$O94=0),"QUIEBRE Y SIN STOCK PARA ENVIAR",IF(AND($F94=0,$T94>0),"QUIEBRE",IF($F94=0,"SIN STOCK SIN DEMANDA",IF(AND($AF94>0,$AG94<>"",OR($AB94="",$AB94>$AG94)),"STOCK VIEJO EN RIESGO",IF(AND($T94=0,$H94=0),"SIN ROTACION",IF($AB94="","-",IF($AB94<14,"REPONER",IF($AB94>84,"SOBRE-STOCK","EN RANGO")))))))) -> SOBRE-STOCK
A95: IT | B95: BOLC77583 | C95: CELU-WL-BK | D95: 1549840747 | E95: Joystick Bluetooth Recargable Global Ecom Para Celulares | F95: 33 | G95: 0 | H95: 0 | I95: =ROUND($H95/30,2) -> 0 | J95: =IF($Z95="CENSURADO",ROUND($T95/MAX($V95,3),2),ROUND($T95/$G$3,2)) -> 0.06 | K95: =ROUNDUP($J95*$C$3*7,0) -> 2 | L95: =MAX(0,$K95-$F95-$G95) -> 0 | M95: 0 | N95: 85 | O95: =$M95+$N95 -> 85 | P95: =MIN($L95,$O95) -> 0 | Q95: Activa | R95: 1 | S95: Pequeño | T95: 2 | U95: 2 | V95: 5 | W95: 13 | X95: 34 | Y95: =IF($X95=0,"",ROUND($H95/$X95,2)) -> 0 | Z95: =IF(AND($F95=0,$T95>=5,$W95>=3),"CENSURADO",IF(AND($Y95<>"",$Y95>=3,$T95>=10),"CENSURADO",IF($T95=0,"SIN DATO","CONFIABLE"))) -> CONFIABLE | AA95: =IF($I95=0,"",ROUND($J95/MAX($I95,0.01),2)) | AB95: =IF($J95<=0,"",ROUND(($F95+$G95)/$J95,0)) -> 550 | AC95: =IF($AB95="","",$J$3+$AB95) -> 46795 | AD95: 1 | AE95: 170 | AF95: 20 | AG95: =IF($AF95=0,"",MAX(0,180-$AE95)) -> 10 | AH95: 7000 | AI95: =IF($AF95=0,"",$AF95*$Q$3-$AF95*$N$3) -> 80300 | AJ95: 12.05 | AK95: =ROUND($F95*$AJ95,0) -> 398 | AL95: =IF(AND($F95=0,$T95>0,$O95=0),"QUIEBRE Y SIN STOCK PARA ENVIAR",IF(AND($F95=0,$T95>0),"QUIEBRE",IF($F95=0,"SIN STOCK SIN DEMANDA",IF(AND($AF95>0,$AG95<>"",OR($AB95="",$AB95>$AG95)),"STOCK VIEJO EN RIESGO",IF(AND($T95=0,$H95=0),"SIN ROTACION",IF($AB95="","-",IF($AB95<14,"REPONER",IF($AB95>84,"SOBRE-STOCK","EN RANGO")))))))) -> STOCK VIEJO EN RIESGO
A96: IT | B96: KTCC59332 | C96: TP-POS58-USB | D96: 1416848103 | E96: Impresora Térmica Comandera Tickets Usb 58mm Global Negro | F96: 4 | G96: 0 | H96: 0 | I96: =ROUND($H96/30,2) -> 0 | J96: =IF($Z96="CENSURADO",ROUND($T96/MAX($V96,3),2),ROUND($T96/$G$3,2)) -> 0.06 | K96: =ROUNDUP($J96*$C$3*7,0) -> 2 | L96: =MAX(0,$K96-$F96-$G96) -> 0 | M96: 393 | N96: 2 | O96: =$M96+$N96 -> 395 | P96: =MIN($L96,$O96) -> 0 | Q96: Activa | R96: 1 | S96: Pequeño | T96: 2 | U96: 2 | V96: 6 | W96: 14 | X96: 4 | Y96: =IF($X96=0,"",ROUND($H96/$X96,2)) -> 0 | Z96: =IF(AND($F96=0,$T96>=5,$W96>=3),"CENSURADO",IF(AND($Y96<>"",$Y96>=3,$T96>=10),"CENSURADO",IF($T96=0,"SIN DATO","CONFIABLE"))) -> CONFIABLE | AA96: =IF($I96=0,"",ROUND($J96/MAX($I96,0.01),2)) | AB96: =IF($J96<=0,"",ROUND(($F96+$G96)/$J96,0)) -> 67 | AC96: =IF($AB96="","",$J$3+$AB96) -> 46312 | AD96: 0 | AE96: 0 | AF96: 0 | AG96: =IF($AF96=0,"",MAX(0,180-$AE96)) | AH96: 0 | AI96: =IF($AF96=0,"",$AF96*$Q$3-$AF96*$N$3) | AJ96: 9.19 | AK96: =ROUND($F96*$AJ96,0) -> 37 | AL96: =IF(AND($F96=0,$T96>0,$O96=0),"QUIEBRE Y SIN STOCK PARA ENVIAR",IF(AND($F96=0,$T96>0),"QUIEBRE",IF($F96=0,"SIN STOCK SIN DEMANDA",IF(AND($AF96>0,$AG96<>"",OR($AB96="",$AB96>$AG96)),"STOCK VIEJO EN RIESGO",IF(AND($T96=0,$H96=0),"SIN ROTACION",IF($AB96="","-",IF($AB96<14,"REPONER",IF($AB96>84,"SOBRE-STOCK","EN RANGO")))))))) -> EN RANGO
A97: IT | B97: NSOC10809 | C97: SAFEBOX-D-31X20X20 | D97: 1142489057 | 3364516090 | E97: Caja Fuerte Digital Global 31x20x20cm Apertura Electronica Negro | F97: 24 | G97: 5 | H97: 1 | I97: =ROUND($H97/30,2) -> 0.03 | J97: =IF($Z97="CENSURADO",ROUND($T97/MAX($V97,3),2),ROUND($T97/$G$3,2)) -> 0.06 | K97: =ROUNDUP($J97*$C$3*7,0) -> 2 | L97: =MAX(0,$K97-$F97-$G97) -> 0 | M97: 324 | N97: 45 | O97: =$M97+$N97 -> 369 | P97: =MIN($L97,$O97) -> 0 | Q97: Activa | R97: 1 | S97: Mediano | T97: 2 | U97: 2 | V97: 25 | W97: 6 | X97: 23 | Y97: =IF($X97=0,"",ROUND($H97/$X97,2)) -> 0.04 | Z97: =IF(AND($F97=0,$T97>=5,$W97>=3),"CENSURADO",IF(AND($Y97<>"",$Y97>=3,$T97>=10),"CENSURADO",IF($T97=0,"SIN DATO","CONFIABLE"))) -> CONFIABLE | AA97: =IF($I97=0,"",ROUND($J97/MAX($I97,0.01),2)) -> 2 | AB97: =IF($J97<=0,"",ROUND(($F97+$G97)/$J97,0)) -> 483 | AC97: =IF($AB97="","",$J$3+$AB97) -> 46728 | AD97: 0 | AE97: 0 | AF97: 0 | AG97: =IF($AF97=0,"",MAX(0,180-$AE97)) | AH97: 0 | AI97: =IF($AF97=0,"",$AF97*$Q$3-$AF97*$N$3) | AJ97: 17.31 | AK97: =ROUND($F97*$AJ97,0) -> 415 | AL97: =IF(AND($F97=0,$T97>0,$O97=0),"QUIEBRE Y SIN STOCK PARA ENVIAR",IF(AND($F97=0,$T97>0),"QUIEBRE",IF($F97=0,"SIN STOCK SIN DEMANDA",IF(AND($AF97>0,$AG97<>"",OR($AB97="",$AB97>$AG97)),"STOCK VIEJO EN RIESGO",IF(AND($T97=0,$H97=0),"SIN ROTACION",IF($AB97="","-",IF($AB97<14,"REPONER",IF($AB97>84,"SOBRE-STOCK","EN RANGO")))))))) -> SOBRE-STOCK
A98: IT | B98: UKPN16842 | C98: INKCARTHP22XL | D98: 1480717461 | 702753322 | E98: Cartucho Alternativo Para 22xl 22 Color 3940 3920 F4180 Hp | F98: 18 | G98: 0 | H98: 1 | I98: =ROUND($H98/30,2) -> 0.03 | J98: =IF($Z98="CENSURADO",ROUND($T98/MAX($V98,3),2),ROUND($T98/$G$3,2)) -> 0.06 | K98: =ROUNDUP($J98*$C$3*7,0) -> 2 | L98: =MAX(0,$K98-$F98-$G98) -> 0 | M98: 1148 | N98: 40 | O98: =$M98+$N98 -> 1188 | P98: =MIN($L98,$O98) -> 0 | Q98: Activa | R98: 1 | S98: Pequeño | T98: 2 | U98: 2 | V98: 16 | W98: 4 | X98: 18 | Y98: =IF($X98=0,"",ROUND($H98/$X98,2)) -> 0.06 | Z98: =IF(AND($F98=0,$T98>=5,$W98>=3),"CENSURADO",IF(AND($Y98<>"",$Y98>=3,$T98>=10),"CENSURADO",IF($T98=0,"SIN DATO","CONFIABLE"))) -> CONFIABLE | AA98: =IF($I98=0,"",ROUND($J98/MAX($I98,0.01),2)) -> 2 | AB98: =IF($J98<=0,"",ROUND(($F98+$G98)/$J98,0)) -> 300 | AC98: =IF($AB98="","",$J$3+$AB98) -> 46545 | AD98: 0 | AE98: 0 | AF98: 0 | AG98: =IF($AF98=0,"",MAX(0,180-$AE98)) | AH98: 0 | AI98: =IF($AF98=0,"",$AF98*$Q$3-$AF98*$N$3) | AJ98: 6.27 | AK98: =ROUND($F98*$AJ98,0) -> 113 | AL98: =IF(AND($F98=0,$T98>0,$O98=0),"QUIEBRE Y SIN STOCK PARA ENVIAR",IF(AND($F98=0,$T98>0),"QUIEBRE",IF($F98=0,"SIN STOCK SIN DEMANDA",IF(AND($AF98>0,$AG98<>"",OR($AB98="",$AB98>$AG98)),"STOCK VIEJO EN RIESGO",IF(AND($T98=0,$H98=0),"SIN ROTACION",IF($AB98="","-",IF($AB98<14,"REPONER",IF($AB98>84,"SOBRE-STOCK","EN RANGO")))))))) -> SOBRE-STOCK
A99: IT | B99: BMQJ10401 | C99: CABLEHDGOLD10M | D99: 2797167350 | 3655836792 | 867766727 | E99: Cable Hd 10 M Premium Mallado Oro 1.4 Full Hd 4k Ps4 Led | F99: 19 | G99: 0 | H99: 1 | I99: =ROUND($H99/30,2) -> 0.03 | J99: =IF($Z99="CENSURADO",ROUND($T99/MAX($V99,3),2),ROUND($T99/$G$3,2)) -> 0.03 | K99: =ROUNDUP($J99*$C$3*7,0) -> 1 | L99: =MAX(0,$K99-$F99-$G99) -> 0 | M99: 1529 | N99: 81 | O99: =$M99+$N99 -> 1610 | P99: =MIN($L99,$O99) -> 0 | Q99: Activa | R99: 1 | S99: Mediano | T99: 1 | U99: 1 | V99: 1 | W99: 4 | X99: 20 | Y99: =IF($X99=0,"",ROUND($H99/$X99,2)) -> 0.05 | Z99: =IF(AND($F99=0,$T99>=5,$W99>=3),"CENSURADO",IF(AND($Y99<>"",$Y99>=3,$T99>=10),"CENSURADO",IF($T99=0,"SIN DATO","CONFIABLE"))) -> CONFIABLE | AA99: =IF($I99=0,"",ROUND($J99/MAX($I99,0.01),2)) -> 1 | AB99: =IF($J99<=0,"",ROUND(($F99+$G99)/$J99,0)) -> 633 | AC99: =IF($AB99="","",$J$3+$AB99) -> 46878 | AD99: 0 | AE99: 0 | AF99: 0 | AG99: =IF($AF99=0,"",MAX(0,180-$AE99)) | AH99: 0 | AI99: =IF($AF99=0,"",$AF99*$Q$3-$AF99*$N$3) | AJ99: 3.27 | AK99: =ROUND($F99*$AJ99,0) -> 62 | AL99: =IF(AND($F99=0,$T99>0,$O99=0),"QUIEBRE Y SIN STOCK PARA ENVIAR",IF(AND($F99=0,$T99>0),"QUIEBRE",IF($F99=0,"SIN STOCK SIN DEMANDA",IF(AND($AF99>0,$AG99<>"",OR($AB99="",$AB99>$AG99)),"STOCK VIEJO EN RIESGO",IF(AND($T99=0,$H99=0),"SIN ROTACION",IF($AB99="","-",IF($AB99<14,"REPONER",IF($AB99>84,"SOBRE-STOCK","EN RANGO")))))))) -> SOBRE-STOCK
A100: IT | B100: ZVYA48199 | C100: BILLCOUNTERPORT-1 | D100: 1461403711 | 1756435104 | E100: Contadora De Billetes Portátil Display Digital | F100: 7 | G100: 0 | H100: 1 | I100: =ROUND($H100/30,2) -> 0.03 | J100: =IF($Z100="CENSURADO",ROUND($T100/MAX($V100,3),2),ROUND($T100/$G$3,2)) -> 0.03 | K100: =ROUNDUP($J100*$C$3*7,0) -> 1 | L100: =MAX(0,$K100-$F100-$G100) -> 0 | M100: 561 | N100: 237 | O100: =$M100+$N100 -> 798 | P100: =MIN($L100,$O100) -> 0 | Q100: Activa | R100: 1 | S100: Mediano | T100: 1 | U100: 1 | V100: 1 | W100: 21 | X100: 7 | Y100: =IF($X100=0,"",ROUND($H100/$X100,2)) -> 0.14 | Z100: =IF(AND($F100=0,$T100>=5,$W100>=3),"CENSURADO",IF(AND($Y100<>"",$Y100>=3,$T100>=10),"CENSURADO",IF($T100=0,"SIN DATO","CONFIABLE"))) -> CONFIABLE | AA100: =IF($I100=0,"",ROUND($J100/MAX($I100,0.01),2)) -> 1 | AB100: =IF($J100<=0,"",ROUND(($F100+$G100)/$J100,0)) -> 233 | AC100: =IF($AB100="","",$J$3+$AB100) -> 46478 | AD100: 0 | AE100: 123 | AF100: 3 | AG100: =IF($AF100=0,"",MAX(0,180-$AE100)) -> 57 | AH100: 1410 | AI100: =IF($AF100=0,"",$AF100*$Q$3-$AF100*$N$3) -> 12045 | AJ100: 20.19 | AK100: =ROUND($F100*$AJ100,0) -> 141 | AL100: =IF(AND($F100=0,$T100>0,$O100=0),"QUIEBRE Y SIN STOCK PARA ENVIAR",IF(AND($F100=0,$T100>0),"QUIEBRE",IF($F100=0,"SIN STOCK SIN DEMANDA",IF(AND($AF100>0,$AG100<>"",OR($AB100="",$AB100>$AG100)),"STOCK VIEJO EN RIESGO",IF(AND($T100=0,$H100=0),"SIN ROTACION",IF($AB100="","-",IF($AB100<14,"REPONER",IF($AB100>84,"SOBRE-STOCK","EN RANGO")))))))) -> STOCK VIEJO EN RIESGO
A101: IT | B101: HIEY48927 | C101: BILLCOUNTER-4 | D101: 2113214146 | 2305765700 | E101: Contadora De Billetes Detecta Billetes Falsos Doble Visor | F101: 0 | G101: 5 | H101: 0 | I101: =ROUND($H101/30,2) -> 0 | J101: =IF($Z101="CENSURADO",ROUND($T101/MAX($V101,3),2),ROUND($T101/$G$3,2)) -> 0.03 | K101: =ROUNDUP($J101*$C$3*7,0) -> 1 | L101: =MAX(0,$K101-$F101-$G101) -> 0 | M101: 1292 | N101: 101 | O101: =$M101+$N101 -> 1393 | P101: =MIN($L101,$O101) -> 0 | Q101: Activa | R101: 1 | S101: Mediano | T101: 1 | U101: 1 | V101: 1 | W101: 18 | X101: 2 | Y101: =IF($X101=0,"",ROUND($H101/$X101,2)) -> 0 | Z101: =IF(AND($F101=0,$T101>=5,$W101>=3),"CENSURADO",IF(AND($Y101<>"",$Y101>=3,$T101>=10),"CENSURADO",IF($T101=0,"SIN DATO","CONFIABLE"))) -> CONFIABLE | AA101: =IF($I101=0,"",ROUND($J101/MAX($I101,0.01),2)) | AB101: =IF($J101<=0,"",ROUND(($F101+$G101)/$J101,0)) -> 167 | AC101: =IF($AB101="","",$J$3+$AB101) -> 46412 | AD101: 0 | AE101: 123 | AF101: 10 | AG101: =IF($AF101=0,"",MAX(0,180-$AE101)) -> 57 | AH101: 4700 | AI101: =IF($AF101=0,"",$AF101*$Q$3-$AF101*$N$3) -> 40150 | AJ101: 30.02 | AK101: =ROUND($F101*$AJ101,0) -> 0 | AL101: =IF(AND($F101=0,$T101>0,$O101=0),"QUIEBRE Y SIN STOCK PARA ENVIAR",IF(AND($F101=0,$T101>0),"QUIEBRE",IF($F101=0,"SIN STOCK SIN DEMANDA",IF(AND($AF101>0,$AG101<>"",OR($AB101="",$AB101>$AG101)),"STOCK VIEJO EN RIESGO",IF(AND($T101=0,$H101=0),"SIN ROTACION",IF($AB101="","-",IF($AB101<14,"REPONER",IF($AB101>84,"SOBRE-STOCK","EN RANGO")))))))) -> QUIEBRE
A102: IT | B102: JNTX73414 | C102: BS-COM-2DUSB | D102: 1568150293 | 3105645508 | E102: Lectora De Códigos De Barras 2d Lineales Y Qr - Usb Negro Usb | F102: 13 | G102: 0 | H102: 0 | I102: =ROUND($H102/30,2) -> 0 | J102: =IF($Z102="CENSURADO",ROUND($T102/MAX($V102,3),2),ROUND($T102/$G$3,2)) -> 0.03 | K102: =ROUNDUP($J102*$C$3*7,0) -> 1 | L102: =MAX(0,$K102-$F102-$G102) -> 0 | M102: 59 | N102: 10 | O102: =$M102+$N102 -> 69 | P102: =MIN($L102,$O102) -> 0 | Q102: Activa | R102: 1 | S102: Pequeño | T102: 1 | U102: 1 | V102: 1 | W102: 1 | X102: 13 | Y102: =IF($X102=0,"",ROUND($H102/$X102,2)) -> 0 | Z102: =IF(AND($F102=0,$T102>=5,$W102>=3),"CENSURADO",IF(AND($Y102<>"",$Y102>=3,$T102>=10),"CENSURADO",IF($T102=0,"SIN DATO","CONFIABLE"))) -> CONFIABLE | AA102: =IF($I102=0,"",ROUND($J102/MAX($I102,0.01),2)) | AB102: =IF($J102<=0,"",ROUND(($F102+$G102)/$J102,0)) -> 433 | AC102: =IF($AB102="","",$J$3+$AB102) -> 46678 | AD102: 0 | AE102: 0 | AF102: 0 | AG102: =IF($AF102=0,"",MAX(0,180-$AE102)) | AH102: 0 | AI102: =IF($AF102=0,"",$AF102*$Q$3-$AF102*$N$3) | AJ102: 19.01 | AK102: =ROUND($F102*$AJ102,0) -> 247 | AL102: =IF(AND($F102=0,$T102>0,$O102=0),"QUIEBRE Y SIN STOCK PARA ENVIAR",IF(AND($F102=0,$T102>0),"QUIEBRE",IF($F102=0,"SIN STOCK SIN DEMANDA",IF(AND($AF102>0,$AG102<>"",OR($AB102="",$AB102>$AG102)),"STOCK VIEJO EN RIESGO",IF(AND($T102=0,$H102=0),"SIN ROTACION",IF($AB102="","-",IF($AB102<14,"REPONER",IF($AB102>84,"SOBRE-STOCK","EN RANGO")))))))) -> SOBRE-STOCK
A103: IT | B103: VYSI92550 | C103: BLENDER1.5L | D103: 1650182329 | 2800288016 | E103: Licuadora Y Procesadora 4 Velocidades 1,5 Lts/36 Gr Blanco | F103: 8 | G103: 0 | H103: 1 | I103: =ROUND($H103/30,2) -> 0.03 | J103: =IF($Z103="CENSURADO",ROUND($T103/MAX($V103,3),2),ROUND($T103/$G$3,2)) -> 0.03 | K103: =ROUNDUP($J103*$C$3*7,0) -> 1 | L103: =MAX(0,$K103-$F103-$G103) -> 0 | M103: 164 | N103: 104 | O103: =$M103+$N103 -> 268 | P103: =MIN($L103,$O103) -> 0 | Q103: Activa | R103: 1 | S103: Mediano | T103: 1 | U103: 1 | V103: 1 | W103: 9 | X103: 9 | Y103: =IF($X103=0,"",ROUND($H103/$X103,2)) -> 0.11 | Z103: =IF(AND($F103=0,$T103>=5,$W103>=3),"CENSURADO",IF(AND($Y103<>"",$Y103>=3,$T103>=10),"CENSURADO",IF($T103=0,"SIN DATO","CONFIABLE"))) -> CONFIABLE | AA103: =IF($I103=0,"",ROUND($J103/MAX($I103,0.01),2)) -> 1 | AB103: =IF($J103<=0,"",ROUND(($F103+$G103)/$J103,0)) -> 267 | AC103: =IF($AB103="","",$J$3+$AB103) -> 46512 | AD103: 0 | AE103: 0 | AF103: 0 | AG103: =IF($AF103=0,"",MAX(0,180-$AE103)) | AH103: 0 | AI103: =IF($AF103=0,"",$AF103*$Q$3-$AF103*$N$3) | AJ103: 14.37 | AK103: =ROUND($F103*$AJ103,0) -> 115 | AL103: =IF(AND($F103=0,$T103>0,$O103=0),"QUIEBRE Y SIN STOCK PARA ENVIAR",IF(AND($F103=0,$T103>0),"QUIEBRE",IF($F103=0,"SIN STOCK SIN DEMANDA",IF(AND($AF103>0,$AG103<>"",OR($AB103="",$AB103>$AG103)),"STOCK VIEJO EN RIESGO",IF(AND($T103=0,$H103=0),"SIN ROTACION",IF($AB103="","-",IF($AB103<14,"REPONER",IF($AB103>84,"SOBRE-STOCK","EN RANGO")))))))) -> SOBRE-STOCK
A104: IT | B104: ZFDA21654 | C104: JS8000-SC-220V | D104: 2012430988 | E104: Cargador Batería Auto Moto 12v 24v Con Pinzas | F104: 0 | G104: 0 | H104: 1 | I104: =ROUND($H104/30,2) -> 0.03 | J104: =IF($Z104="CENSURADO",ROUND($T104/MAX($V104,3),2),ROUND($T104/$G$3,2)) -> 0.03 | K104: =ROUNDUP($J104*$C$3*7,0) -> 1 | L104: =MAX(0,$K104-$F104-$G104) -> 1 | M104: 171 | N104: 196 | O104: =$M104+$N104 -> 367 | P104: =MIN($L104,$O104) -> 1 | Q104: Activa | R104: 1 | S104: Mediano | T104: 1 | U104: 1 | V104: 1 | W104: 3 | X104: 1 | Y104: =IF($X104=0,"",ROUND($H104/$X104,2)) -> 1 | Z104: =IF(AND($F104=0,$T104>=5,$W104>=3),"CENSURADO",IF(AND($Y104<>"",$Y104>=3,$T104>=10),"CENSURADO",IF($T104=0,"SIN DATO","CONFIABLE"))) -> CONFIABLE | AA104: =IF($I104=0,"",ROUND($J104/MAX($I104,0.01),2)) -> 1 | AB104: =IF($J104<=0,"",ROUND(($F104+$G104)/$J104,0)) -> 0 | AC104: =IF($AB104="","",$J$3+$AB104) -> 46245 | AD104: 0 | AE104: 0 | AF104: 0 | AG104: =IF($AF104=0,"",MAX(0,180-$AE104)) | AH104: 0 | AI104: =IF($AF104=0,"",$AF104*$Q$3-$AF104*$N$3) | AJ104: 13.11 | AK104: =ROUND($F104*$AJ104,0) -> 0 | AL104: =IF(AND($F104=0,$T104>0,$O104=0),"QUIEBRE Y SIN STOCK PARA ENVIAR",IF(AND($F104=0,$T104>0),"QUIEBRE",IF($F104=0,"SIN STOCK SIN DEMANDA",IF(AND($AF104>0,$AG104<>"",OR($AB104="",$AB104>$AG104)),"STOCK VIEJO EN RIESGO",IF(AND($T104=0,$H104=0),"SIN ROTACION",IF($AB104="","-",IF($AB104<14,"REPONER",IF($AB104>84,"SOBRE-STOCK","EN RANGO")))))))) -> QUIEBRE
A105: IT | B105: EFMY16111 | C105: X2 Q2612ACOMP | D105: 668551314 | E105: Toner Alternativo Para Q2612a 2612a 12a 1010 1020 Pack X 2 Negro | F105: 13 | G105: 0 | H105: 1 | I105: =ROUND($H105/30,2) -> 0.03 | J105: =IF($Z105="CENSURADO",ROUND($T105/MAX($V105,3),2),ROUND($T105/$G$3,2)) -> 0.03 | K105: =ROUNDUP($J105*$C$3*7,0) -> 1 | L105: =MAX(0,$K105-$F105-$G105) -> 0 | M105: 0 | N105: 0 | O105: =$M105+$N105 -> 0 | P105: =MIN($L105,$O105) -> 0 | Q105: Activa | R105: 1 | S105: Mediano | T105: 1 | U105: 1 | V105: 1 | W105: 11 | X105: 14 | Y105: =IF($X105=0,"",ROUND($H105/$X105,2)) -> 0.07 | Z105: =IF(AND($F105=0,$T105>=5,$W105>=3),"CENSURADO",IF(AND($Y105<>"",$Y105>=3,$T105>=10),"CENSURADO",IF($T105=0,"SIN DATO","CONFIABLE"))) -> CONFIABLE | AA105: =IF($I105=0,"",ROUND($J105/MAX($I105,0.01),2)) -> 1 | AB105: =IF($J105<=0,"",ROUND(($F105+$G105)/$J105,0)) -> 433 | AC105: =IF($AB105="","",$J$3+$AB105) -> 46678 | AD105: 0 | AE105: 0 | AF105: 0 | AG105: =IF($AF105=0,"",MAX(0,180-$AE105)) | AH105: 0 | AI105: =IF($AF105=0,"",$AF105*$Q$3-$AF105*$N$3) | AJ105: 0 | AK105: =ROUND($F105*$AJ105,0) -> 0 | AL105: =IF(AND($F105=0,$T105>0,$O105=0),"QUIEBRE Y SIN STOCK PARA ENVIAR",IF(AND($F105=0,$T105>0),"QUIEBRE",IF($F105=0,"SIN STOCK SIN DEMANDA",IF(AND($AF105>0,$AG105<>"",OR($AB105="",$AB105>$AG105)),"STOCK VIEJO EN RIESGO",IF(AND($T105=0,$H105=0),"SIN ROTACION",IF($AB105="","-",IF($AB105<14,"REPONER",IF($AB105>84,"SOBRE-STOCK","EN RANGO")))))))) -> SOBRE-STOCK
... A114: IT | B114: LECW18578 | C114: FOILHOLOMULTICOLOR-G-32X6MT | D114: 1606669903 | 2669141946 | E114: Foil Holográfico Pet Metalizado Glossy 32cm De Ancho X 6 Mt Multicolor | F114: 0 | G114: 0 | H114: 0 | I114: =ROUND($H114/30,2) -> 0 | J114: =IF($Z114="CENSURADO",ROUND($T114/MAX($V114,3),2),ROUND($T114/$G$3,2)) -> 0 | K114: =ROUNDUP($J114*$C$3*7,0) -> 0 | L114: =MAX(0,$K114-$F114-$G114) -> 0 | M114: 189 | N114: 307 | O114: =$M114+$N114 -> 496 | P114: =MIN($L114,$O114) -> 0 | Q114: Activa | R114: 1 | S114: Mediano | T114: 0 | U114: 0 | V114: 0 | W114: 0 | X114: 0 | Y114: =IF($X114=0,"",ROUND($H114/$X114,2)) | Z114: =IF(AND($F114=0,$T114>=5,$W114>=3),"CENSURADO",IF(AND($Y114<>"",$Y114>=3,$T114>=10),"CENSURADO",IF($T114=0,"SIN DATO","CONFIABLE"))) -> SIN DATO | AA114: =IF($I114=0,"",ROUND($J114/MAX($I114,0.01),2)) | AB114: =IF($J114<=0,"",ROUND(($F114+$G114)/$J114,0)) | AC114: =IF($AB114="","",$J$3+$AB114) | AD114: 0 | AE114: 0 | AF114: 0 | AG114: =IF($AF114=0,"",MAX(0,180-$AE114)) | AH114: 0 | AI114: =IF($AF114=0,"",$AF114*$Q$3-$AF114*$N$3) | AJ114: 0 | AK114: =ROUND($F114*$AJ114,0) -> 0 | AL114: =IF(AND($F114=0,$T114>0,$O114=0),"QUIEBRE Y SIN STOCK PARA ENVIAR",IF(AND($F114=0,$T114>0),"QUIEBRE",IF($F114=0,"SIN STOCK SIN DEMANDA",IF(AND($AF114>0,$AG114<>"",OR($AB114="",$AB114>$AG114)),"STOCK VIEJO EN RIESGO",IF(AND($T114=0,$H114=0),"SIN ROTACION",IF($AB114="","-",IF($AB114<14,"REPONER",IF($AB114>84,"SOBRE-STOCK","EN RANGO")))))))) -> SIN STOCK SIN DEMANDA
A115: IT | B115: ZTDG44993 | C115: FAN-20I | D115: 2416042722 | 3655836968 | E115: Ventilador Turbo 20 Potente Mesa Piso 3 Velocidades 50.8 Cm Negro Plástico | F115: 0 | G115: 0 | H115: 0 | I115: =ROUND($H115/30,2) -> 0 | J115: =IF($Z115="CENSURADO",ROUND($T115/MAX($V115,3),2),ROUND($T115/$G$3,2)) -> 0 | K115: =ROUNDUP($J115*$C$3*7,0) -> 0 | L115: =MAX(0,$K115-$F115-$G115) -> 0 | M115: 441 | N115: 0 | O115: =$M115+$N115 -> 441 | P115: =MIN($L115,$O115) -> 0 | R115: 1 | S115: Grande | T115: 0 | U115: 0 | V115: 0 | W115: 0 | X115: 1 | Y115: =IF($X115=0,"",ROUND($H115/$X115,2)) -> 0 | Z115: =IF(AND($F115=0,$T115>=5,$W115>=3),"CENSURADO",IF(AND($Y115<>"",$Y115>=3,$T115>=10),"CENSURADO",IF($T115=0,"SIN DATO","CONFIABLE"))) -> SIN DATO | AA115: =IF($I115=0,"",ROUND($J115/MAX($I115,0.01),2)) | AB115: =IF($J115<=0,"",ROUND(($F115+$G115)/$J115,0)) | AC115: =IF($AB115="","",$J$3+$AB115) | AD115: 0 | AE115: 127 | AF115: 5 | AG115: =IF($AF115=0,"",MAX(0,180-$AE115)) -> 53 | AH115: 6775 | AI115: =IF($AF115=0,"",$AF115*$Q$3-$AF115*$N$3) -> 20075 | AJ115: 18.68 | AK115: =ROUND($F115*$AJ115,0) -> 0 | AL115: =IF(AND($F115=0,$T115>0,$O115=0),"QUIEBRE Y SIN STOCK PARA ENVIAR",IF(AND($F115=0,$T115>0),"QUIEBRE",IF($F115=0,"SIN STOCK SIN DEMANDA",IF(AND($AF115>0,$AG115<>"",OR($AB115="",$AB115>$AG115)),"STOCK VIEJO EN RIESGO",IF(AND($T115=0,$H115=0),"SIN ROTACION",IF($AB115="","-",IF($AB115<14,"REPONER",IF($AB115>84,"SOBRE-STOCK","EN RANGO")))))))) -> SIN STOCK SIN DEMANDA
A116: IT | B116: BGMU45960 | C116: FAN-COOL300-USB | D116: 2416042724 | E116: Ventilador Con Agua Fría Humidificador Purificador Usb Blanco | F116: 0 | G116: 0 | H116: 0 | I116: =ROUND($H116/30,2) -> 0 | J116: =IF($Z116="CENSURADO",ROUND($T116/MAX($V116,3),2),ROUND($T116/$G$3,2)) -> 0 | K116: =ROUNDUP($J116*$C$3*7,0) -> 0 | L116: =MAX(0,$K116-$F116-$G116) -> 0 | M116: 228 | N116: 225 | O116: =$M116+$N116 -> 453 | P116: =MIN($L116,$O116) -> 0 | Q116: Activa | R116: 1 | S116: Pequeño | T116: 0 | U116: 0 | V116: 0 | W116: 0 | X116: 5 | Y116: =IF($X116=0,"",ROUND($H116/$X116,2)) -> 0 | Z116: =IF(AND($F116=0,$T116>=5,$W116>=3),"CENSURADO",IF(AND($Y116<>"",$Y116>=3,$T116>=10),"CENSURADO",IF($T116=0,"SIN DATO","CONFIABLE"))) -> SIN DATO | AA116: =IF($I116=0,"",ROUND($J116/MAX($I116,0.01),2)) | AB116: =IF($J116<=0,"",ROUND(($F116+$G116)/$J116,0)) | AC116: =IF($AB116="","",$J$3+$AB116) | AD116: 0 | AE116: 130 | AF116: 5 | AG116: =IF($AF116=0,"",MAX(0,180-$AE116)) -> 50 | AH116: 1750 | AI116: =IF($AF116=0,"",$AF116*$Q$3-$AF116*$N$3) -> 20075 | AJ116: 8.74 | AK116: =ROUND($F116*$AJ116,0) -> 0 | AL116: =IF(AND($F116=0,$T116>0,$O116=0),"QUIEBRE Y SIN STOCK PARA ENVIAR",IF(AND($F116=0,$T116>0),"QUIEBRE",IF($F116=0,"SIN STOCK SIN DEMANDA",IF(AND($AF116>0,$AG116<>"",OR($AB116="",$AB116>$AG116)),"STOCK VIEJO EN RIESGO",IF(AND($T116=0,$H116=0),"SIN ROTACION",IF($AB116="","-",IF($AB116<14,"REPONER",IF($AB116>84,"SOBRE-STOCK","EN RANGO")))))))) -> SIN STOCK SIN DEMANDA
A117: IT | B117: FRMW13126 | C117: EXPDISC+DOUWIRE-2IN1-MINI-G | D117: 3484868312 | E117: Encuadernadora Manual 2 En 1 Discos Y Doble Wire 15 Hojas Turquesa | F117: 20 | G117: 0 | H117: 0 | I117: =ROUND($H117/30,2) -> 0 | J117: =IF($Z117="CENSURADO",ROUND($T117/MAX($V117,3),2),ROUND($T117/$G$3,2)) -> 0 | K117: =ROUNDUP($J117*$C$3*7,0) -> 0 | L117: =MAX(0,$K117-$F117-$G117) -> 0 | M117: 118 | N117: 105 | O117: =$M117+$N117 -> 223 | P117: =MIN($L117,$O117) -> 0 | Q117: Activa | R117: 1 | S117: Mediano | T117: 0 | U117: 0 | V117: 0 | W117: 0 | X117: 20 | Y117: =IF($X117=0,"",ROUND($H117/$X117,2)) -> 0 | Z117: =IF(AND($F117=0,$T117>=5,$W117>=3),"CENSURADO",IF(AND($Y117<>"",$Y117>=3,$T117>=10),"CENSURADO",IF($T117=0,"SIN DATO","CONFIABLE"))) -> SIN DATO | AA117: =IF($I117=0,"",ROUND($J117/MAX($I117,0.01),2)) | AB117: =IF($J117<=0,"",ROUND(($F117+$G117)/$J117,0)) | AC117: =IF($AB117="","",$J$3+$AB117) | AD117: 0 | AE117: 0 | AF117: 0 | AG117: =IF($AF117=0,"",MAX(0,180-$AE117)) | AH117: 0 | AI117: =IF($AF117=0,"",$AF117*$Q$3-$AF117*$N$3) | AJ117: 0 | AK117: =ROUND($F117*$AJ117,0) -> 0 | AL117: =IF(AND($F117=0,$T117>0,$O117=0),"QUIEBRE Y SIN STOCK PARA ENVIAR",IF(AND($F117=0,$T117>0),"QUIEBRE",IF($F117=0,"SIN STOCK SIN DEMANDA",IF(AND($AF117>0,$AG117<>"",OR($AB117="",$AB117>$AG117)),"STOCK VIEJO EN RIESGO",IF(AND($T117=0,$H117=0),"SIN ROTACION",IF($AB117="","-",IF($AB117<14,"REPONER",IF($AB117>84,"SOBRE-STOCK","EN RANGO")))))))) -> SIN ROTACION
A118: IT | B118: DVNJ46510 | C118: ESPIRALADORA-M-A4-R | D118: 1380302329 | 2827065470 | E118: Espiraladora Manual Reforzada A4 Perfora 12 Hojas 80grs | F118: 6 | G118: 0 | H118: 0 | I118: =ROUND($H118/30,2) -> 0 | J118: =IF($Z118="CENSURADO",ROUND($T118/MAX($V118,3),2),ROUND($T118/$G$3,2)) -> 0 | K118: =ROUNDUP($J118*$C$3*7,0) -> 0 | L118: =MAX(0,$K118-$F118-$G118) -> 0 | M118: 840 | N118: 352 | O118: =$M118+$N118 -> 1192 | P118: =MIN($L118,$O118) -> 0 | Q118: Activa | R118: 2 | S118: Grande | T118: 0 | U118: 0 | V118: 0 | W118: 0 | X118: 6 | Y118: =IF($X118=0,"",ROUND($H118/$X118,2)) -> 0 | Z118: =IF(AND($F118=0,$T118>=5,$W118>=3),"CENSURADO",IF(AND($Y118<>"",$Y118>=3,$T118>=10),"CENSURADO",IF($T118=0,"SIN DATO","CONFIABLE"))) -> SIN DATO | AA118: =IF($I118=0,"",ROUND($J118/MAX($I118,0.01),2)) | AB118: =IF($J118<=0,"",ROUND(($F118+$G118)/$J118,0)) | AC118: =IF($AB118="","",$J$3+$AB118) | AD118: 0 | AE118: 0 | AF118: 0 | AG118: =IF($AF118=0,"",MAX(0,180-$AE118)) | AH118: 0 | AI118: =IF($AF118=0,"",$AF118*$Q$3-$AF118*$N$3) | AJ118: 63.3 | AK118: =ROUND($F118*$AJ118,0) -> 380 | AL118: =IF(AND($F118=0,$T118>0,$O118=0),"QUIEBRE Y SIN STOCK PARA ENVIAR",IF(AND($F118=0,$T118>0),"QUIEBRE",IF($F118=0,"SIN STOCK SIN DEMANDA",IF(AND($AF118>0,$AG118<>"",OR($AB118="",$AB118>$AG118)),"STOCK VIEJO EN RIESGO",IF(AND($T118=0,$H118=0),"SIN ROTACION",IF($AB118="","-",IF($AB118<14,"REPONER",IF($AB118>84,"SOBRE-STOCK","EN RANGO")))))))) -> SIN ROTACION
A119: IT | B119: MMFT59805 | C119: COFRE-20X15X9-BL | D119: 1142306808 | 2028543192 | E119: Cofre Portavalores Con Bandeja Global 20x15x9cm 2 Llaves Azul | F119: 0 | G119: 0 | H119: 0 | I119: =ROUND($H119/30,2) -> 0 | J119: =IF($Z119="CENSURADO",ROUND($T119/MAX($V119,3),2),ROUND($T119/$G$3,2)) -> 0 | K119: =ROUNDUP($J119*$C$3*7,0) -> 0 | L119: =MAX(0,$K119-$F119-$G119) -> 0 | M119: 932 | N119: 318 | O119: =$M119+$N119 -> 1250 | P119: =MIN($L119,$O119) -> 0 | Q119: Activa | R119: 1 | S119: Mediano | T119: 0 | U119: 0 | V119: 0 | W119: 0 | X119: 0 | Y119: =IF($X119=0,"",ROUND($H119/$X119,2)) | Z119: =IF(AND($F119=0,$T119>=5,$W119>=3),"CENSURADO",IF(AND($Y119<>"",$Y119>=3,$T119>=10),"CENSURADO",IF($T119=0,"SIN DATO","CONFIABLE"))) -> SIN DATO | AA119: =IF($I119=0,"",ROUND($J119/MAX($I119,0.01),2)) | AB119: =IF($J119<=0,"",ROUND(($F119+$G119)/$J119,0)) | AC119: =IF($AB119="","",$J$3+$AB119) | AD119: 0 | AE119: 0 | AF119: 0 | AG119: =IF($AF119=0,"",MAX(0,180-$AE119)) | AH119: 0 | AI119: =IF($AF119=0,"",$AF119*$Q$3-$AF119*$N$3) | AJ119: 5.83 | AK119: =ROUND($F119*$AJ119,0) -> 0 | AL119: =IF(AND($F119=0,$T119>0,$O119=0),"QUIEBRE Y SIN STOCK PARA ENVIAR",IF(AND($F119=0,$T119>0),"QUIEBRE",IF($F119=0,"SIN STOCK SIN DEMANDA",IF(AND($AF119>0,$AG119<>"",OR($AB119="",$AB119>$AG119)),"STOCK VIEJO EN RIESGO",IF(AND($T119=0,$H119=0),"SIN ROTACION",IF($AB119="","-",IF($AB119<14,"REPONER",IF($AB119>84,"SOBRE-STOCK","EN RANGO")))))))) -> SIN STOCK SIN DEMANDA
A120: IT | B120: JGZN23257 | C120: CAM-OUT-WIFI-1080P | D120: 3504397400 | E120: Cámara Seguridad Wifi Exterior 1080p Ptz Audio App Ycc Blanco | F120: 0 | G120: 30 | H120: 0 | I120: =ROUND($H120/30,2) -> 0 | J120: =IF($Z120="CENSURADO",ROUND($T120/MAX($V120,3),2),ROUND($T120/$G$3,2)) -> 0 | K120: =ROUNDUP($J120*$C$3*7,0) -> 0 | L120: =MAX(0,$K120-$F120-$G120) -> 0 | M120: 791 | N120: 32 | O120: =$M120+$N120 -> 823 | P120: =MIN($L120,$O120) -> 0 | Q120: Activa | R120: 1 | S120: Mediano (Estimado) | T120: 0 | U120: 0 | V120: 0 | W120: 0 | X120: 0 | Y120: =IF($X120=0,"",ROUND($H120/$X120,2)) | Z120: =IF(AND($F120=0,$T120>=5,$W120>=3),"CENSURADO",IF(AND($Y120<>"",$Y120>=3,$T120>=10),"CENSURADO",IF($T120=0,"SIN DATO","CONFIABLE"))) -> SIN DATO | AA120: =IF($I120=0,"",ROUND($J120/MAX($I120,0.01),2)) | AB120: =IF($J120<=0,"",ROUND(($F120+$G120)/$J120,0)) | AC120: =IF($AB120="","",$J$3+$AB120) | AD120: 0 | AE120: 0 | AF120: 0 | AG120: =IF($AF120=0,"",MAX(0,180-$AE120)) | AH120: 0 | AI120: =IF($AF120=0,"",$AF120*$Q$3-$AF120*$N$3) | AJ120: 7.89 | AK120: =ROUND($F120*$AJ120,0) -> 0 | AL120: =IF(AND($F120=0,$T120>0,$O120=0),"QUIEBRE Y SIN STOCK PARA ENVIAR",IF(AND($F120=0,$T120>0),"QUIEBRE",IF($F120=0,"SIN STOCK SIN DEMANDA",IF(AND($AF120>0,$AG120<>"",OR($AB120="",$AB120>$AG120)),"STOCK VIEJO EN RIESGO",IF(AND($T120=0,$H120=0),"SIN ROTACION",IF($AB120="","-",IF($AB120<14,"REPONER",IF($AB120>84,"SOBRE-STOCK","EN RANGO")))))))) -> SIN STOCK SIN DEMANDA
A121: IT | B121: PTKV37093 | C121: CALCU-12D-837B | D121: 1791793656 | 826874563 | E121: Calculadora De Mesa De 12 Dígitos Plastica Negra 837b Negro | F121: 1 | G121: 0 | H121: 0 | I121: =ROUND($H121/30,2) -> 0 | J121: =IF($Z121="CENSURADO",ROUND($T121/MAX($V121,3),2),ROUND($T121/$G$3,2)) -> 0 | K121: =ROUNDUP($J121*$C$3*7,0) -> 0 | L121: =MAX(0,$K121-$F121-$G121) -> 0 | M121: 0 | N121: 0 | O121: =$M121+$N121 -> 0 | P121: =MIN($L121,$O121) -> 0 | R121: 1 | S121: Pequeño | T121: 0 | U121: 0 | V121: 0 | W121: 0 | X121: 1 | Y121: =IF($X121=0,"",ROUND($H121/$X121,2)) -> 0 | Z121: =IF(AND($F121=0,$T121>=5,$W121>=3),"CENSURADO",IF(AND($Y121<>"",$Y121>=3,$T121>=10),"CENSURADO",IF($T121=0,"SIN DATO","CONFIABLE"))) -> SIN DATO | AA121: =IF($I121=0,"",ROUND($J121/MAX($I121,0.01),2)) | AB121: =IF($J121<=0,"",ROUND(($F121+$G121)/$J121,0)) | AC121: =IF($AB121="","",$J$3+$AB121) | AD121: 0 | AE121: 0 | AF121: 0 | AG121: =IF($AF121=0,"",MAX(0,180-$AE121)) | AH121: 0 | AI121: =IF($AF121=0,"",$AF121*$Q$3-$AF121*$N$3) | AJ121: 1.56 | AK121: =ROUND($F121*$AJ121,0) -> 2 | AL121: =IF(AND($F121=0,$T121>0,$O121=0),"QUIEBRE Y SIN STOCK PARA ENVIAR",IF(AND($F121=0,$T121>0),"QUIEBRE",IF($F121=0,"SIN STOCK SIN DEMANDA",IF(AND($AF121>0,$AG121<>"",OR($AB121="",$AB121>$AG121)),"STOCK VIEJO EN RIESGO",IF(AND($T121=0,$H121=0),"SIN ROTACION",IF($AB121="","-",IF($AB121<14,"REPONER",IF($AB121>84,"SOBRE-STOCK","EN RANGO")))))))) -> SIN ROTACION
A122: IT | B122: YCAZ23815 | C122: CAMX4-OUT-SOLAR-4G-1080P | D122: 3498026800 | E122: Cámara Solar Exterior 4g Wifi 1080p Ptz Visión Nocturna Gris Oscuro | F122: 0 | G122: 10 | H122: 0 | I122: =ROUND($H122/30,2) -> 0 | J122: =IF($Z122="CENSURADO",ROUND($T122/MAX($V122,3),2),ROUND($T122/$G$3,2)) -> 0 | K122: =ROUNDUP($J122*$C$3*7,0) -> 0 | L122: =MAX(0,$K122-$F122-$G122) -> 0 | M122: 215 | N122: 2 | O122: =$M122+$N122 -> 217 | P122: =MIN($L122,$O122) -> 0 | Q122: Activa | R122: 1 | S122: Mediano (Estimado) | T122: 0 | U122: 0 | V122: 0 | W122: 0 | X122: 0 | Y122: =IF($X122=0,"",ROUND($H122/$X122,2)) | Z122: =IF(AND($F122=0,$T122>=5,$W122>=3),"CENSURADO",IF(AND($Y122<>"",$Y122>=3,$T122>=10),"CENSURADO",IF($T122=0,"SIN DATO","CONFIABLE"))) -> SIN DATO | AA122: =IF($I122=0,"",ROUND($J122/MAX($I122,0.01),2)) | AB122: =IF($J122<=0,"",ROUND(($F122+$G122)/$J122,0)) | AC122: =IF($AB122="","",$J$3+$AB122) | AD122: 0 | AE122: 0 | AF122: 0 | AG122: =IF($AF122=0,"",MAX(0,180-$AE122)) | AH122: 0 | AI122: =IF($AF122=0,"",$AF122*$Q$3-$AF122*$N$3) | AJ122: 30.43 | AK122: =ROUND($F122*$AJ122,0) -> 0 | AL122: =IF(AND($F122=0,$T122>0,$O122=0),"QUIEBRE Y SIN STOCK PARA ENVIAR",IF(AND($F122=0,$T122>0),"QUIEBRE",IF($F122=0,"SIN STOCK SIN DEMANDA",IF(AND($AF122>0,$AG122<>"",OR($AB122="",$AB122>$AG122)),"STOCK VIEJO EN RIESGO",IF(AND($T122=0,$H122=0),"SIN ROTACION",IF($AB122="","-",IF($AB122<14,"REPONER",IF($AB122>84,"SOBRE-STOCK","EN RANGO")))))))) -> SIN STOCK SIN DEMANDA
A123: IT | B123: IOBM29701 | C123: MONS-ARM2-13-30I-100X100 | D123: 1377607289 | E123: Soporte Para Monitor Doble Brazo Neumático Movil 13 A 30 Negro | F123: 31 | G123: 0 | H123: 0 | I123: =ROUND($H123/30,2) -> 0 | J123: =IF($Z123="CENSURADO",ROUND($T123/MAX($V123,3),2),ROUND($T123/$G$3,2)) -> 0 | K123: =ROUNDUP($J123*$C$3*7,0) -> 0 | L123: =MAX(0,$K123-$F123-$G123) -> 0 | M123: 19 | N123: 0 | O123: =$M123+$N123 -> 19 | P123: =MIN($L123,$O123) -> 0 | Q123: Activa | R123: 1 | S123: Mediano | T123: 0 | U123: 0 | V123: 0 | W123: 0 | X123: 31 | Y123: =IF($X123=0,"",ROUND($H123/$X123,2)) -> 0 | Z123: =IF(AND($F123=0,$T123>=5,$W123>=3),"CENSURADO",IF(AND($Y123<>"",$Y123>=3,$T123>=10),"CENSURADO",IF($T123=0,"SIN DATO","CONFIABLE"))) -> SIN DATO | AA123: =IF($I123=0,"",ROUND($J123/MAX($I123,0.01),2)) | AB123: =IF($J123<=0,"",ROUND(($F123+$G123)/$J123,0)) | AC123: =IF($AB123="","",$J$3+$AB123) | AD123: 0 | AE123: 0 | AF123: 0 | AG123: =IF($AF123=0,"",MAX(0,180-$AE123)) | AH123: 0 | AI123: =IF($AF123=0,"",$AF123*$Q$3-$AF123*$N$3) | AJ123: 28.32 | AK123: =ROUND($F123*$AJ123,0) -> 878 | AL123: =IF(AND($F123=0,$T123>0,$O123=0),"QUIEBRE Y SIN STOCK PARA ENVIAR",IF(AND($F123=0,$T123>0),"QUIEBRE",IF($F123=0,"SIN STOCK SIN DEMANDA",IF(AND($AF123>0,$AG123<>"",OR($AB123="",$AB123>$AG123)),"STOCK VIEJO EN RIESGO",IF(AND($T123=0,$H123=0),"SIN ROTACION",IF($AB123="","-",IF($AB123<14,"REPONER",IF($AB123>84,"SOBRE-STOCK","EN RANGO")))))))) -> SIN ROTACION
A124: IT | B124: YGIG10948 | C124: MONI-OFFICE-23.6IFHD | D124: 2087405722 | 3532134760 | E124: Monitor 24 Pulgadas Hdmi Vga Full Hd 1080p 60hz Negro | F124: 5 | G124: 0 | H124: 0 | I124: =ROUND($H124/30,2) -> 0 | J124: =IF($Z124="CENSURADO",ROUND($T124/MAX($V124,3),2),ROUND($T124/$G$3,2)) -> 0 | K124: =ROUNDUP($J124*$C$3*7,0) -> 0 | L124: =MAX(0,$K124-$F124-$G124) -> 0 | M124: 10 | N124: 0 | O124: =$M124+$N124 -> 10 | P124: =MIN($L124,$O124) -> 0 | Q124: Activa | R124: 1 | S124: Grande | T124: 0 | U124: 0 | V124: 0 | W124: 0 | X124: 5 | Y124: =IF($X124=0,"",ROUND($H124/$X124,2)) -> 0 | Z124: =IF(AND($F124=0,$T124>=5,$W124>=3),"CENSURADO",IF(AND($Y124<>"",$Y124>=3,$T124>=10),"CENSURADO",IF($T124=0,"SIN DATO","CONFIABLE"))) -> SIN DATO | AA124: =IF($I124=0,"",ROUND($J124/MAX($I124,0.01),2)) | AB124: =IF($J124<=0,"",ROUND(($F124+$G124)/$J124,0)) | AC124: =IF($AB124="","",$J$3+$AB124) | AD124: 0 | AE124: 0 | AF124: 0 | AG124: =IF($AF124=0,"",MAX(0,180-$AE124)) | AH124: 0 | AI124: =IF($AF124=0,"",$AF124*$Q$3-$AF124*$N$3) | AJ124: 27.85 | AK124: =ROUND($F124*$AJ124,0) -> 139 | AL124: =IF(AND($F124=0,$T124>0,$O124=0),"QUIEBRE Y SIN STOCK PARA ENVIAR",IF(AND($F124=0,$T124>0),"QUIEBRE",IF($F124=0,"SIN STOCK SIN DEMANDA",IF(AND($AF124>0,$AG124<>"",OR($AB124="",$AB124>$AG124)),"STOCK VIEJO EN RIESGO",IF(AND($T124=0,$H124=0),"SIN ROTACION",IF($AB124="","-",IF($AB124<14,"REPONER",IF($AB124>84,"SOBRE-STOCK","EN RANGO")))))))) -> SIN ROTACION
A125: IT | B125: XBIE81701 | C125: MONS-ARM2-10-27I-100X100 | D125: 1451180082 | E125: Soporte Monitor Doble Brazo Movil 10 A 27 Vesa 100x100 10kg Negro | F125: 5 | G125: 0 | H125: 0 | I125: =ROUND($H125/30,2) -> 0 | J125: =IF($Z125="CENSURADO",ROUND($T125/MAX($V125,3),2),ROUND($T125/$G$3,2)) -> 0 | K125: =ROUNDUP($J125*$C$3*7,0) -> 0 | L125: =MAX(0,$K125-$F125-$G125) -> 0 | M125: 0 | N125: 11 | O125: =$M125+$N125 -> 11 | P125: =MIN($L125,$O125) -> 0 | Q125: Activa | R125: 1 | S125: Mediano | T125: 0 | U125: 0 | V125: 0 | W125: 0 | X125: 5 | Y125: =IF($X125=0,"",ROUND($H125/$X125,2)) -> 0 | Z125: =IF(AND($F125=0,$T125>=5,$W125>=3),"CENSURADO",IF(AND($Y125<>"",$Y125>=3,$T125>=10),"CENSURADO",IF($T125=0,"SIN DATO","CONFIABLE"))) -> SIN DATO | AA125: =IF($I125=0,"",ROUND($J125/MAX($I125,0.01),2)) | AB125: =IF($J125<=0,"",ROUND(($F125+$G125)/$J125,0)) | AC125: =IF($AB125="","",$J$3+$AB125) | AD125: 0 | AE125: 0 | AF125: 0 | AG125: =IF($AF125=0,"",MAX(0,180-$AE125)) | AH125: 0 | AI125: =IF($AF125=0,"",$AF125*$Q$3-$AF125*$N$3) | AJ125: 15.02 | AK125: =ROUND($F125*$AJ125,0) -> 75 | AL125: =IF(AND($F125=0,$T125>0,$O125=0),"QUIEBRE Y SIN STOCK PARA ENVIAR",IF(AND($F125=0,$T125>0),"QUIEBRE",IF($F125=0,"SIN STOCK SIN DEMANDA",IF(AND($AF125>0,$AG125<>"",OR($AB125="",$AB125>$AG125)),"STOCK VIEJO EN RIESGO",IF(AND($T125=0,$H125=0),"SIN ROTACION",IF($AB125="","-",IF($AB125<14,"REPONER",IF($AB125>84,"SOBRE-STOCK","EN RANGO")))))))) -> SIN ROTACION
A126: IT | B126: WEPI53171 | C126: PB211COMP | D126: 1112894883 | E126: Cartucho De Toner Pantum Pb-211 Alternativo 1.6k | F126: 0 | G126: 0 | H126: 0 | I126: =ROUND($H126/30,2) -> 0 | J126: =IF($Z126="CENSURADO",ROUND($T126/MAX($V126,3),2),ROUND($T126/$G$3,2)) -> 0 | K126: =ROUNDUP($J126*$C$3*7,0) -> 0 | L126: =MAX(0,$K126-$F126-$G126) -> 0 | M126: 8 | N126: 0 | O126: =$M126+$N126 -> 8 | P126: =MIN($L126,$O126) -> 0 | Q126: Inactiva | R126: 1 | S126: Mediano | T126: 0 | U126: 0 | V126: 0 | W126: 0 | X126: 0 | Y126: =IF($X126=0,"",ROUND($H126/$X126,2)) | Z126: =IF(AND($F126=0,$T126>=5,$W126>=3),"CENSURADO",IF(AND($Y126<>"",$Y126>=3,$T126>=10),"CENSURADO",IF($T126=0,"SIN DATO","CONFIABLE"))) -> SIN DATO | AA126: =IF($I126=0,"",ROUND($J126/MAX($I126,0.01),2)) | AB126: =IF($J126<=0,"",ROUND(($F126+$G126)/$J126,0)) | AC126: =IF($AB126="","",$J$3+$AB126) | AD126: 0 | AE126: 0 | AF126: 0 | AG126: =IF($AF126=0,"",MAX(0,180-$AE126)) | AH126: 0 | AI126: =IF($AF126=0,"",$AF126*$Q$3-$AF126*$N$3) | AJ126: 3.25 | AK126: =ROUND($F126*$AJ126,0) -> 0 | AL126: =IF(AND($F126=0,$T126>0,$O126=0),"QUIEBRE Y SIN STOCK PARA ENVIAR",IF(AND($F126=0,$T126>0),"QUIEBRE",IF($F126=0,"SIN STOCK SIN DEMANDA",IF(AND($AF126>0,$AG126<>"",OR($AB126="",$AB126>$AG126)),"STOCK VIEJO EN RIESGO",IF(AND($T126=0,$H126=0),"SIN ROTACION",IF($AB126="","-",IF($AB126<14,"REPONER",IF($AB126>84,"SOBRE-STOCK","EN RANGO")))))))) -> SIN STOCK SIN DEMANDA
A127: IT | B127: KXQQ58394 | C127: TP-POS80-USB | D127: 1416860243 | E127: Impresora Termica 80mm Comandera Tickets Usb Negro | F127: 22 | G127: 0 | H127: 0 | I127: =ROUND($H127/30,2) -> 0 | J127: =IF($Z127="CENSURADO",ROUND($T127/MAX($V127,3),2),ROUND($T127/$G$3,2)) -> 0 | K127: =ROUNDUP($J127*$C$3*7,0) -> 0 | L127: =MAX(0,$K127-$F127-$G127) -> 0 | M127: 0 | N127: 0 | O127: =$M127+$N127 -> 0 | P127: =MIN($L127,$O127) -> 0 | R127: 1 | S127: Mediano | T127: 0 | U127: 0 | V127: 0 | W127: 0 | X127: 22 | Y127: =IF($X127=0,"",ROUND($H127/$X127,2)) -> 0 | Z127: =IF(AND($F127=0,$T127>=5,$W127>=3),"CENSURADO",IF(AND($Y127<>"",$Y127>=3,$T127>=10),"CENSURADO",IF($T127=0,"SIN DATO","CONFIABLE"))) -> SIN DATO | AA127: =IF($I127=0,"",ROUND($J127/MAX($I127,0.01),2)) | AB127: =IF($J127<=0,"",ROUND(($F127+$G127)/$J127,0)) | AC127: =IF($AB127="","",$J$3+$AB127) | AD127: 0 | AE127: 0 | AF127: 0 | AG127: =IF($AF127=0,"",MAX(0,180-$AE127)) | AH127: 0 | AI127: =IF($AF127=0,"",$AF127*$Q$3-$AF127*$N$3) | AJ127: 20.66 | AK127: =ROUND($F127*$AJ127,0) -> 455 | AL127: =IF(AND($F127=0,$T127>0,$O127=0),"QUIEBRE Y SIN STOCK PARA ENVIAR",IF(AND($F127=0,$T127>0),"QUIEBRE",IF($F127=0,"SIN STOCK SIN DEMANDA",IF(AND($AF127>0,$AG127<>"",OR($AB127="",$AB127>$AG127)),"STOCK VIEJO EN RIESGO",IF(AND($T127=0,$H127=0),"SIN ROTACION",IF($AB127="","-",IF($AB127<14,"REPONER",IF($AB127>84,"SOBRE-STOCK","EN RANGO")))))))) -> SIN ROTACION
A128: IT | B128: UVJP81772 | C128: X10 STRC200BKCOMP | D128: 2654087308 | E128: Pack De 10 Cintas Ribbon Alternativa Global Sp200 Sp216 Negro | F128: 0 | G128: 0 | H128: 0 | I128: =ROUND($H128/30,2) -> 0 | J128: =IF($Z128="CENSURADO",ROUND($T128/MAX($V128,3),2),ROUND($T128/$G$3,2)) -> 0 | K128: =ROUNDUP($J128*$C$3*7,0) -> 0 | L128: =MAX(0,$K128-$F128-$G128) -> 0 | M128: 0 | N128: 0 | O128: =$M128+$N128 -> 0 | P128: =MIN($L128,$O128) -> 0 | Q128: Activa | R128: 1 | S128: Mediano | T128: 0 | U128: 0 | V128: 0 | W128: 0 | X128: 0 | Y128: =IF($X128=0,"",ROUND($H128/$X128,2)) | Z128: =IF(AND($F128=0,$T128>=5,$W128>=3),"CENSURADO",IF(AND($Y128<>"",$Y128>=3,$T128>=10),"CENSURADO",IF($T128=0,"SIN DATO","CONFIABLE"))) -> SIN DATO | AA128: =IF($I128=0,"",ROUND($J128/MAX($I128,0.01),2)) | AB128: =IF($J128<=0,"",ROUND(($F128+$G128)/$J128,0)) | AC128: =IF($AB128="","",$J$3+$AB128) | AD128: 0 | AE128: 0 | AF128: 0 | AG128: =IF($AF128=0,"",MAX(0,180-$AE128)) | AH128: 0 | AI128: =IF($AF128=0,"",$AF128*$Q$3-$AF128*$N$3) | AJ128: 0 | AK128: =ROUND($F128*$AJ128,0) -> 0 | AL128: =IF(AND($F128=0,$T128>0,$O128=0),"QUIEBRE Y SIN STOCK PARA ENVIAR",IF(AND($F128=0,$T128>0),"QUIEBRE",IF($F128=0,"SIN STOCK SIN DEMANDA",IF(AND($AF128>0,$AG128<>"",OR($AB128="",$AB128>$AG128)),"STOCK VIEJO EN RIESGO",IF(AND($T128=0,$H128=0),"SIN ROTACION",IF($AB128="","-",IF($AB128<14,"REPONER",IF($AB128>84,"SOBRE-STOCK","EN RANGO")))))))) -> SIN STOCK SIN DEMANDA
C129: TOTAL | F129: =SUM(F7:F128) -> 2183 | G129: =SUM(G7:G128) -> 1120 | H129: =SUM(H7:H128) -> 4174 | L129: =SUM(L7:L128) -> 2628 | M129: =SUM(M7:M128) -> 158194 | N129: =SUM(N7:N128) -> 28491 | O129: =SUM(O7:O128) -> 186685 | P129: =SUM(P7:P128) -> 1314 | AD129: =SUM(AD7:AD128) -> 2 | AF129: =SUM(AF7:AF128) -> 875 | AH129: =SUM(AH7:AH128) -> 482230 | AI129: =SUM(AI7:AI128) -> 3513125 | AK129: =SUM(AK7:AK128) -> 14766

Sheet COLUMNAS
A1: QUÉ ES CADA COLUMNA
A2: Las columnas en celeste se calculan solas. Las grises vienen de un reporte.
A4: BLOQUE | B4: COLUMNA | C4: DE DÓNDE SALE | D4: QUÉ SIGNIFICA
A5: PARA ARMAR EL ENVÍO | B5: Cuenta | C5: Fijo | D5: IT o MT. Hoy solo hay IT cargada.
B6: Código ML | C6: Reporte general de stock de Full | D6: El código interno de ML del producto.
B7: SKU | C7: Reporte general de stock de Full | D7: Nuestro código.
B8: MLA (publicación) | C8: Reporte general de stock de Full | D8: El número de publicación. Si un SKU tiene varias, aparecen todas.
B9: Título | C9: Reporte general de stock de Full | D9: Nombre del producto en ML.
B10: Stock en Full | C10: Reporte general de stock de Full | D10: Unidades aptas para vender que están hoy en el depósito de ML.
B11: Envíos pendientes | C11: Reporte general de stock de Full | D11: Unidades que ya salieron y ML todavía no recibió.
B12: Ventas 30 días | C12: Reporte general de stock de Full | D12: El número que informa ML. OJO: es el que puede estar censurado.
B13: Ventas diarias simple | C13: CALCULADA | D13: Ventas 30 días dividido 30. Es lo que muestra cualquier reporte. Puede estar mal.
B14: Ventas diarias corregida | C14: CALCULADA | D14: Si el dato está censurado, se divide por los días que tuvo stock en lugar de por 30. Esta es la que se usa para todo lo demás.
B15: Stock objetivo | C15: CALCULADA | D15: Ventas diarias corregida por las semanas objetivo por 7. Las semanas se cambian en la celda C3.
B16: Falta enviar | C16: CALCULADA | D16: Stock objetivo menos lo que hay en Full menos lo que va en camino. Nunca da negativo.
B17: Stock Táctica | C17: Sistema Táctica | D17: Unidades disponibles en Táctica.
... B20: ENVIAR POSIBLE | C20: CALCULADA | D20: El menor entre lo que falta enviar y lo que hay disponible. Si es menor que "Falta enviar", el límite no es Full: no tenemos la mercadería.
A21: CONTROL DE LA PUBLICACIÓN | B21: Estado publicación | C21: Reporte general de stock de Full | D21: Activa, pausada, etc. Una pausada vende cero aunque tenga stock.
B22: Publ. | C22: CALCULADA | D22: Cuántas publicaciones tiene ese SKU. Si es más de 1, el stock se comparte.
B23: Tamaño | C23: Reporte general de stock de Full | D23: Chico, mediano, grande. Define la tarifa de almacenamiento.
A24: CÓMO SE MIDIÓ LA DEMANDA | B24: Unidades 32d | C24: Reporte de ventas con fecha | D24: Unidades realmente vendidas en el período, descontando canceladas y devueltas.
B25: Días con venta | C25: Reporte de ventas con fecha | D25: En cuántos días distintos hubo al menos una venta.
B26: Ventana con stock | C26: Reporte de ventas con fecha | D26: Días entre la primera y la última venta. Aproxima cuántos días tuvo stock. ESTE ES EL DATO CLAVE.
B27: Días sin vender | C27: Reporte de ventas con fecha | D27: Cuántos días pasaron desde la última venta hasta hoy. Si son muchos y el stock es cero, se agotó.
B28: Stock prom 30d ML | C28: Reporte general de stock de Full | D28: Stock promedio que tuvo durante el mes, según ML.
B29: Rotación | C29: CALCULADA | D29: Ventas 30 días dividido stock promedio. Arriba de 3 significa que estuvo agotado buena parte del mes.
B30: Estado del dato | C30: CALCULADA | D30: CENSURADO: se agotó, así que la venta es un piso y no una medición. CONFIABLE: tuvo stock. SIN DATO: no vendió.
B31: Factor | C31: CALCULADA | D31: Cuántas veces subestima el reporte mensual. Factor 6 significa que el reporte muestra la sexta parte de la demanda real.
A32: CUÁNDO SE QUIEBRA | B32: Cobertura (días) | C32: CALCULADA | D32: Stock en Full más en camino, dividido las ventas diarias corregidas.
B33: Quiebre estimado | C33: CALCULADA | D33: La fecha en que llega a cero si la venta sigue al mismo ritmo.
A34: ANTIGÜEDAD Y CARGOS | B34: No aptas | C34: Reporte general de stock de Full | D34: Unidades que ML no puede vender. Ocupan lugar igual.
B35: Antigüedad máx | C35: Reporte de cargos por antigüedad | D35: Días de la unidad más vieja de ese SKU.
B36: Unid. 4-6 meses | C36: Reporte de cargos por antigüedad | D36: Unidades entre 120 y 179 días. Hoy pagan la tarifa de la celda N3.
B37: Días al límite 180 | C37: CALCULADA | D37: Cuántos días faltan para que esas unidades pasen al tramo caro.
B38: Cargo actual | C38: Reporte de cargos por antigüedad | D38: Lo que se está pagando por stock antiguo de ese SKU.
B39: Aumento si cruza | C39: CALCULADA | D39: Cuánto más se pagaría si esas unidades cruzan los 180 días. La tarifa salta de $470 a $4.485: nueve veces.
A40: VALOR | B40: Costo USD | C40: Sistema ECOM | D40: Costo unitario. 19 SKUs no lo tienen cargado.
B41: Valor en Full USD | C41: CALCULADA | D41: Stock en Full por el costo. Es un piso, porque falta el costo de algunos SKUs.
A42: ESTADO | B42: ALERTA | C42: CALCULADA | D42: El estado del SKU. Describe la situación, no indica qué hacer.
A44: LOS ESTADOS DE LA COLUMNA ALERTA
B45: QUIEBRE Y SIN STOCK PARA ENVIAR | D45: En cero en Full, con demanda, y sin una sola unidad en Táctica ni ECOM. No es un problema de logística: es de compras.
B46: QUIEBRE | D46: En cero en Full con demanda comprobada. Hay stock para mandar.
B47: REPONER | D47: Menos de 14 días de cobertura.
B48: EN RANGO | D48: Entre 14 y 84 días de cobertura.
B49: SOBRE-STOCK | D49: Más de 84 días de cobertura.
B50: SIN ROTACION | D50: Tiene unidades en Full y no vendió nada en el período.
B51: STOCK VIEJO EN RIESGO | D51: Tiene unidades en la franja 4-6 meses que no van a venderse antes de los 180 días.
B52: SIN STOCK SIN DEMANDA | D52: En cero y sin ventas.
A54: LO QUE ESTA PLANILLA NO PUEDE RESOLVER
B55: La ventana es una estimación | D55: Asume que la última venta es el día que se agotó. El reporte de stock de Full trae la hora exacta de ingreso y de venta de cada unidad, pero hay que abrirlo de a un SKU. Por API el cálculo sería exacto.
B56: No hay dato de visitas | D56: Un SKU con stock y sin ventas puede ser falta de demanda o publicación sin exposición. Con estos reportes las dos se ven iguales.
B57: No se sabe si Full le sirve al SKU | D57: Todo el sentido de Full es que convierte mejor. Si un producto vende lo mismo con Full que sin Full, se paga depósito por nada. Falta comparar la conversión de cada SKU con y sin Full.
B58: Los reportes tienen fechas distintas | D58: El de cargos y el de stock no son del mismo momento. Puede haber más unidades con cargo que unidades en stock. No es un error.
B59: Falta la cuenta MT | D59: La mitad de la operación está afuera de esta planilla.
